sv_common_ips/07_scoreboard_and_reference_model/top.sv
// top.sv - Lesson 07
//
// Focus:
//  - A simple FIFO DUT that is easy to model in C++
//  - C++ scoreboard + reference model can check every transfer
//
// The DUT is intentionally small so the testbench structure is the main lesson.

module top (
    input  logic clk,
    input  logic rst_n,

    input  logic       in_valid,
    input  logic [7:0] in_data,
    output logic       in_ready,

    input  logic       out_ready,
    output logic       out_valid,
    output logic [7:0] out_data,

    output logic [3:0] count
);
    localparam int DEPTH = 8;
    localparam int AW = $clog2(DEPTH);

    logic [7:0] mem [0:DEPTH-1];
    logic [AW-1:0] wptr;
    logic [AW-1:0] rptr;
    logic [AW:0] used;

    logic push;
    logic pop;

    assign in_ready = (int'(used) < DEPTH);
    assign out_valid = (used != 0);
    assign out_data = mem[rptr];
    assign count = used[3:0];

    assign push = in_valid && in_ready;
    assign pop = out_ready && out_valid;

    always_ff @(posedge clk) begin
        if (!rst_n) begin
            wptr <= '0;
            rptr <= '0;
            used <= '0;
        end else begin
            if (push) begin
                mem[wptr] <= in_data;
                wptr <= wptr + 1'b1;
            end

            if (pop) begin
                rptr <= rptr + 1'b1;
            end

            unique case ({push, pop})
                2'b10: used <= used + 1'b1;
                2'b01: used <= used - 1'b1;
                default: used <= used;
            endcase
        end
    end

endmodule

sv_common_ips/07_scoreboard_and_reference_model/waveform.vcd
$version Generated by VerilatedVcd $end
$timescale 1ps $end
 $scope module TOP $end
  $var wire 1 . clk $end
  $var wire 1 / rst_n $end
  $var wire 1 0 in_valid $end
  $var wire 8 1 in_data [7:0] $end
  $var wire 1 2 in_ready $end
  $var wire 1 3 out_ready $end
  $var wire 1 4 out_valid $end
  $var wire 8 5 out_data [7:0] $end
  $var wire 4 6 count [3:0] $end
  $scope module top $end
   $var wire 1 . clk $end
   $var wire 1 / rst_n $end
   $var wire 1 0 in_valid $end
   $var wire 8 1 in_data [7:0] $end
   $var wire 1 2 in_ready $end
   $var wire 1 3 out_ready $end
   $var wire 1 4 out_valid $end
   $var wire 8 5 out_data [7:0] $end
   $var wire 4 6 count [3:0] $end
   $var wire 32 9 DEPTH [31:0] $end
   $var wire 32 : AW [31:0] $end
   $var wire 8 # mem[0] [7:0] $end
   $var wire 8 $ mem[1] [7:0] $end
   $var wire 8 % mem[2] [7:0] $end
   $var wire 8 & mem[3] [7:0] $end
   $var wire 8 ' mem[4] [7:0] $end
   $var wire 8 ( mem[5] [7:0] $end
   $var wire 8 ) mem[6] [7:0] $end
   $var wire 8 * mem[7] [7:0] $end
   $var wire 3 + wptr [2:0] $end
   $var wire 3 , rptr [2:0] $end
   $var wire 4 - used [3:0] $end
   $var wire 1 7 push $end
   $var wire 1 8 pop $end
  $upscope $end
 $upscope $end
$enddefinitions $end


#0
b00000000 #
b00000000 $
b00000000 %
b00000000 &
b00000000 '
b00000000 (
b00000000 )
b00000000 *
b000 +
b000 ,
b0000 -
0.
0/
00
b00000000 1
12
03
04
b00000000 5
b0000 6
07
08
b00000000000000000000000000001000 9
b00000000000000000000000000000011 :
#1
1.
#2
0.
#3
1.
#4
0.
#5
1.
#6
0.
#7
1.
#8
0.
#9
1.
#10
0.
1/
10
b00111000 1
17
#11
b00111000 #
b001 +
b0001 -
1.
14
b00111000 5
b0001 6
#12
0.
b01100000 1
#13
b01100000 $
b010 +
b0010 -
1.
b0010 6
#14
0.
b10101111 1
13
18
#15
b10101111 %
b011 +
b001 ,
1.
b01100000 5
#16
0.
b00010010 1
03
08
#17
b00010010 &
b100 +
b0011 -
1.
b0011 6
#18
0.
b10100001 1
13
18
#19
b10100001 '
b101 +
b010 ,
1.
b10101111 5
#20
0.
00
b00001010 1
03
07
08
#21
1.
#22
0.
10
b01101111 1
17
#23
b01101111 (
b110 +
b0100 -
1.
b0100 6
#24
0.
b10101010 1
#25
b10101010 )
b111 +
b0101 -
1.
b0101 6
#26
0.
b00100010 1
13
18
#27
b00100010 *
b000 +
b011 ,
1.
b00010010 5
#28
0.
b00011110 1
03
08
#29
b00011110 #
b001 +
b0110 -
1.
b0110 6
#30
0.
00
b00101100 1
13
07
18
#31
b100 ,
b0101 -
1.
b10100001 5
b0101 6
#32
0.
10
b10111111 1
17
#33
b10111111 $
b010 +
b101 ,
1.
b01101111 5
#34
0.
00
b10111011 1
07
#35
b110 ,
b0100 -
1.
b10101010 5
b0100 6
#36
0.
b11001110 1
03
08
#37
1.
#38
0.
10
b10110000 1
13
17
18
#39
b10110000 %
b011 +
b111 ,
1.
b00100010 5
#40
0.
b01101011 1
03
08
#41
b01101011 &
b100 +
b0101 -
1.
b0101 6
#42
0.
b10001101 1
13
18
#43
b10001101 '
b101 +
b000 ,
1.
b00011110 5
#44
0.
b01101101 1
03
08
#45
b01101101 (
b110 +
b0110 -
1.
b0110 6
#46
0.
b01011101 1
#47
b01011101 )
b111 +
b0111 -
1.
b0111 6
#48
0.
b11011010 1
13
18
#49
b11011010 *
b000 +
b001 ,
1.
b10111111 5
#50
0.
00
b11010101 1
03
07
08
#51
1.
#52
0.
10
b10000000 1
13
17
18
#53
b10000000 #
b001 +
b010 ,
1.
b10110000 5
#54
0.
b10010011 1
03
08
#55
b10010011 $
b010 +
b1000 -
1.
02
b1000 6
07
#56
0.
b11110110 1
13
18
#57
b011 ,
b0111 -
1.
12
b01101011 5
b0111 6
17
#58
0.
00
b00100100 1
03
07
08
#59
1.
#60
0.
10
b11000101 1
13
17
18
#61
b11000101 %
b011 +
b100 ,
1.
b10001101 5
#62
0.
b10100110 1
03
08
#63
b10100110 &
b100 +
b1000 -
1.
02
b1000 6
07
#64
0.
b01001001 1
13
18
#65
b101 ,
b0111 -
1.
12
b01101101 5
b0111 6
17
#66
0.
00
b11101010 1
03
07
08
#67
1.
#68
0.
10
b11011001 1
13
17
18
#69
b11011001 '
b101 +
b110 ,
1.
b01011101 5
#70
0.
00
b00001010 1
03
07
08
#71
1.
#72
0.
b11101101 1
13
18
#73
b111 ,
b0110 -
1.
b11011010 5
b0110 6
#74
0.
10
b10011011 1
17
#75
b10011011 (
b110 +
b000 ,
1.
b10000000 5
#76
0.
00
b00011111 1
03
07
08
#77
1.
#78
0.
10
b01010111 1
13
17
18
#79
b01010111 )
b111 +
b001 ,
1.
b10010011 5
#80
0.
b01100001 1
03
08
#81
b01100001 *
b000 +
b0111 -
1.
b0111 6
#82
0.
b10010101 1
13
18
#83
b10010101 #
b001 +
b010 ,
1.
b11000101 5
#84
0.
b10101010 1
#85
b10101010 $
b010 +
b011 ,
1.
b10100110 5
#86
0.
b01000010 1
#87
b01000010 %
b011 +
b100 ,
1.
b11011001 5
#88
0.
b11101011 1
03
08
#89
b11101011 &
b100 +
b1000 -
1.
02
b1000 6
07
#90
0.
00
b10010001 1
13
18
#91
b101 ,
b0111 -
1.
12
b10011011 5
b0111 6
#92
0.
b11110000 1
03
08
#93
1.
#94
0.
10
b10101111 1
13
17
18
#95
b10101111 '
b101 +
b110 ,
1.
b01010111 5
#96
0.
b11110000 1
03
08
#97
b11110000 (
b110 +
b1000 -
1.
02
b1000 6
07
#98
0.
00
b00101100 1
13
18
#99
b111 ,
b0111 -
1.
12
b01100001 5
b0111 6
#100
0.
10
b00000111 1
03
17
08
#101
b00000111 )
b111 +
b1000 -
1.
02
b1000 6
07
#102
0.
00
b10000000 1
#103
1.
#104
0.
10
b00010101 1
#105
1.
#106
0.
b00001110 1
#107
1.
#108
0.
00
b00100011 1
13
18
#109
b000 ,
b0111 -
1.
12
b10010101 5
b0111 6
#110
0.
10
b10100000 1
03
17
08
#111
b10100000 *
b000 +
b1000 -
1.
02
b1000 6
07
#112
0.
b11110011 1
#113
1.
#114
0.
00
b11110000 1
#115
1.
#116
0.
10
b01110101 1
13
18
#117
b001 ,
b0111 -
1.
12
b10101010 5
b0111 6
17
#118
0.
b00111101 1
#119
b00111101 #
b001 +
b010 ,
1.
b01000010 5
#120
0.
00
b00001101 1
03
07
08
#121
1.
#122
0.
10
b10001110 1
17
#123
b10001110 $
b010 +
b1000 -
1.
02
b1000 6
07
#124
0.
b10100110 1
#125
1.
#126
0.
b10010000 1
#127
1.
#128
0.
00
b10011110 1
#129
1.
#130
0.
b10000000 1
#131
1.
#132
0.
b01001110 1
13
18
#133
b011 ,
b0111 -
1.
12
b11101011 5
b0111 6
#134
0.
10
b01111100 1
17
#135
b01111100 %
b011 +
b100 ,
1.
b10101111 5
#136
0.
00
b01001111 1
07
#137
b101 ,
b0110 -
1.
b11110000 5
b0110 6
#138
0.
b00000010 1
03
08
#139
1.
#140
0.
10
b11000000 1
13
17
18
#141
b11000000 &
b100 +
b110 ,
1.
b00000111 5
#142
0.
00
b00110001 1
03
07
08
#143
1.
#144
0.
b11001001 1
13
18
#145
b111 ,
b0101 -
1.
b10100000 5
b0101 6
#146
0.
10
b10001110 1
17
#147
b10001110 '
b101 +
b000 ,
1.
b00111101 5
#148
0.
00
b11000001 1
03
07
08
#149
1.
#150
0.
b00000010 1
#151
1.
#152
0.
b11100111 1
13
18
#153
b001 ,
b0100 -
1.
b10001110 5
b0100 6
#154
0.
10
b10101000 1
17
#155
b10101000 (
b110 +
b010 ,
1.
b01111100 5
#156
0.
b11001011 1
#157
b11001011 )
b111 +
b011 ,
1.
b11000000 5
#158
0.
b00111011 1
#159
b00111011 *
b000 +
b100 ,
1.
b10001110 5
#160
0.
b11000011 1
03
08
#161
b11000011 #
b001 +
b0101 -
1.
b0101 6
#162
0.
b10100100 1
13
18
#163
b10100100 $
b010 +
b101 ,
1.
b10101000 5
#164
0.
00
b01100010 1
07
#165
b110 ,
b0100 -
1.
b11001011 5
b0100 6
#166
0.
10
b01110100 1
03
17
08
#167
b01110100 %
b011 +
b0101 -
1.
b0101 6
#168
0.
b01110000 1
#169
b01110000 &
b100 +
b0110 -
1.
b0110 6
#170
0.
b01111000 1
13
18
#171
b01111000 '
b101 +
b111 ,
1.
b00111011 5
#172
0.
b01000101 1
#173
b01000101 (
b110 +
b000 ,
1.
b11000011 5
#174
0.
b10100100 1
03
08
#175
b10100100 )
b111 +
b0111 -
1.
b0111 6
#176
0.
b01101011 1
#177
b01101011 *
b000 +
b1000 -
1.
02
b1000 6
07
#178
0.
b10011100 1
13
18
#179
b001 ,
b0111 -
1.
12
b10100100 5
b0111 6
17
#180
0.
b01100010 1
#181
b01100010 #
b001 +
b010 ,
1.
b01110100 5
#182
0.
00
b10010011 1
07
#183
b011 ,
b0110 -
1.
b01110000 5
b0110 6
#184
0.
10
b11101101 1
17
#185
b11101101 $
b010 +
b100 ,
1.
b01111000 5
#186
0.
00
b10101110 1
07
#187
b101 ,
b0101 -
1.
b01000101 5
b0101 6
#188
0.
b10011100 1
03
08
#189
1.
#190
0.
10
b00101110 1
13
17
18
#191
b00101110 %
b011 +
b110 ,
1.
b10100100 5
#192
0.
00
b10111111 1
03
07
08
#193
1.
#194
0.
10
b00001011 1
13
17
18
#195
b00001011 &
b100 +
b111 ,
1.
b01101011 5
#196
0.
b11110010 1
#197
b11110010 '
b101 +
b000 ,
1.
b01100010 5
#198
0.
b00000110 1
03
08
#199
b00000110 (
b110 +
b0110 -
1.
b0110 6
#200
0.
b10010110 1
#201
b10010110 )
b111 +
b0111 -
1.
b0111 6
#202
0.
b00101100 1
#203
b00101100 *
b000 +
b1000 -
1.
02
b1000 6
07
#204
0.
b00110101 1
13
18
#205
b001 ,
b0111 -
1.
12
b11101101 5
b0111 6
17
#206
0.
00
b00100100 1
03
07
08
#207
1.
#208
0.
b11010100 1
#209
1.
#210
0.
10
b11101010 1
17
#211
b11101010 #
b001 +
b1000 -
1.
02
b1000 6
07
#212
0.
b11110101 1
#213
1.
#214
0.
b11101111 1
#215
1.
#216
0.
b00101000 1
#217
1.
#218
0.
b10001011 1
13
18
#219
b010 ,
b0111 -
1.
12
b00101110 5
b0111 6
17
#220
0.
00
b01001100 1
07
#221
b011 ,
b0110 -
1.
b00001011 5
b0110 6
#222
0.
10
b10010011 1
03
17
08
#223
b10010011 $
b010 +
b0111 -
1.
b0111 6
#224
0.
b01011101 1
#225
b01011101 %
b011 +
b1000 -
1.
02
b1000 6
07
#226
0.
00
b11100111 1
13
18
#227
b100 ,
b0111 -
1.
12
b11110010 5
b0111 6
#228
0.
b01111101 1
#229
b101 ,
b0110 -
1.
b00000110 5
b0110 6
#230
0.
b01110000 1
03
08
#231
1.
#232
0.
b01011011 1
#233
1.
#234
0.
10
b11101010 1
17
#235
b11101010 &
b100 +
b0111 -
1.
b0111 6
#236
0.
00
b10001000 1
13
07
18
#237
b110 ,
b0110 -
1.
b10010110 5
b0110 6
#238
0.
10
b01111101 1
03
17
08
#239
b01111101 '
b101 +
b0111 -
1.
b0111 6
#240
0.
b01110001 1
13
18
#241
b01110001 (
b110 +
b111 ,
1.
b00101100 5
#242
0.
b01110111 1
#243
b01110111 )
b111 +
b000 ,
1.
b11101010 5
#244
0.
b11001101 1
#245
b11001101 *
b000 +
b001 ,
1.
b10010011 5
#246
0.
00
b10110011 1
07
#247
b010 ,
b0110 -
1.
b01011101 5
b0110 6
#248
0.
b00101001 1
03
08
#249
1.
#250
0.
b01011001 1
13
18
#251
b011 ,
b0101 -
1.
b11101010 5
b0101 6
#252
0.
b11100100 1
03
08
#253
1.
#254
0.
b00011111 1
13
18
#255
b100 ,
b0100 -
1.
b01111101 5
b0100 6
#256
0.
10
b11100101 1
17
#257
b11100101 #
b001 +
b101 ,
1.
b01110001 5
#258
0.
b10000110 1
03
08
#259
b10000110 $
b010 +
b0101 -
1.
b0101 6
#260
0.
00
b00101000 1
13
07
18
#261
b110 ,
b0100 -
1.
b01110111 5
b0100 6
#262
0.
10
b11010001 1
03
17
08
#263
b11010001 %
b011 +
b0101 -
1.
b0101 6
#264
0.
00
b01110100 1
13
07
18
#265
b111 ,
b0100 -
1.
b11001101 5
b0100 6
#266
0.
10
b01111011 1
17
#267
b01111011 &
b100 +
b000 ,
1.
b11100101 5
#268
0.
b00001000 1
#269
b00001000 '
b101 +
b001 ,
1.
b10000110 5
#270
0.
00
b11001010 1
07
#271
b010 ,
b0011 -
1.
b11010001 5
b0011 6
#272
0.
10
b10101100 1
03
17
08
#273
b10101100 (
b110 +
b0100 -
1.
b0100 6
#274
0.
00
b00111011 1
13
07
18
#275
b011 ,
b0011 -
1.
b01111011 5
b0011 6
#276
0.
10
b01001100 1
17
#277
b01001100 )
b111 +
b100 ,
1.
b00001000 5
#278
0.
b10111001 1
#279
b10111001 *
b000 +
b101 ,
1.
b10101100 5
#280
0.
b01000110 1
03
08
#281
b01000110 #
b001 +
b0100 -
1.
b0100 6
#282
0.
b00000101 1
#283
b00000101 $
b010 +
b0101 -
1.
b0101 6
#284
0.
b00100000 1
#285
b00100000 %
b011 +
b0110 -
1.
b0110 6
#286
0.
00
b00010100 1
07
#287
1.
#288
0.
b00000000 1
#289
1.
#290
0.
10
b01100001 1
13
17
18
#291
b01100001 &
b100 +
b110 ,
1.
b01001100 5
#292
0.
b01001110 1
03
08
#293
b01001110 '
b101 +
b0111 -
1.
b0111 6
#294
0.
b11100100 1
13
18
#295
b11100100 (
b110 +
b111 ,
1.
b10111001 5
#296
0.
b11000011 1
03
08
#297
b11000011 )
b111 +
b1000 -
1.
02
b1000 6
07
#298
0.
00
b01000100 1
#299
1.
#300
0.
10
b01111001 1
13
18
#301
b000 ,
b0111 -
1.
12
b01000110 5
b0111 6
17
#302
0.
b00101100 1
#303
b00101100 *
b000 +
b001 ,
1.
b00000101 5
#304
0.
b00000010 1
#305
b00000010 #
b001 +
b010 ,
1.
b00100000 5
#306
0.
b10011101 1
#307
b10011101 $
b010 +
b011 ,
1.
b01100001 5
#308
0.
00
b11000010 1
03
07
08
#309
1.
#310
0.
10
b10001010 1
17
#311
b10001010 %
b011 +
b1000 -
1.
02
b1000 6
07
#312
0.
b10110001 1
13
18
#313
b100 ,
b0111 -
1.
12
b01001110 5
b0111 6
17
#314
0.
b10100100 1
#315
b10100100 &
b100 +
b101 ,
1.
b11100100 5
#316
0.
b10111100 1
#317
b10111100 '
b101 +
b110 ,
1.
b11000011 5
#318
0.
b10100111 1
#319
b10100111 (
b110 +
b111 ,
1.
b00101100 5
#320
0.
00
b10110011 1
07
#321
b000 ,
b0110 -
1.
b00000010 5
b0110 6
#322
0.
10
b01010101 1
03
17
08
#323
b01010101 )
b111 +
b0111 -
1.
b0111 6
#324
0.
b10101110 1
13
18
#325
b10101110 *
b000 +
b001 ,
1.
b10011101 5
#326
0.
00
b11100101 1
03
07
08
#327
1.
#328
0.
10
b10110111 1
13
17
18
#329
b10110111 #
b001 +
b010 ,
1.
b10001010 5
#330
0.
b11001110 1
03
08
#331
b11001110 $
b010 +
b1000 -
1.
02
b1000 6
07
#332
0.
b11001100 1
13
18
#333
b011 ,
b0111 -
1.
12
b10100100 5
b0111 6
17
#334
0.
b00111110 1
#335
b00111110 %
b011 +
b100 ,
1.
b10111100 5
#336
0.
00
03
07
08
#337
1.
#338
0.
b10010101 1
#339
1.
#340
0.
b00100000 1
13
18
#341
b101 ,
b0110 -
1.
b10100111 5
b0110 6
#342
0.
10
b00011111 1
03
17
08
#343
b00011111 &
b100 +
b0111 -
1.
b0111 6
#344
0.
b00111001 1
#345
b00111001 '
b101 +
b1000 -
1.
02
b1000 6
07
#346
0.
00
b01000010 1
13
18
#347
b110 ,
b0111 -
1.
12
b01010101 5
b0111 6
#348
0.
10
b10011000 1
03
17
08
#349
b10011000 (
b110 +
b1000 -
1.
02
b1000 6
07
#350
0.
00
b00000010 1
#351
1.
#352
0.
10
b01101100 1
13
18
#353
b111 ,
b0111 -
1.
12
b10101110 5
b0111 6
17
#354
0.
b01101110 1
03
08
#355
b01101110 )
b111 +
b1000 -
1.
02
b1000 6
07
#356
0.
00
b10000010 1
#357
1.
#358
0.
10
b10001111 1
13
18
#359
b000 ,
b0111 -
1.
12
b10110111 5
b0111 6
17
#360
0.
00
b01011100 1
03
07
08
#361
1.
#362
0.
10
b11111110 1
17
#363
b11111110 *
b000 +
b1000 -
1.
02
b1000 6
07
#364
0.
b10101000 1
13
18
#365
b001 ,
b0111 -
1.
12
b11001110 5
b0111 6
17
#366
0.
b11100100 1
#367
b11100100 #
b001 +
b010 ,
1.
b00111110 5
#368
0.
b00101110 1
03
08
#369
b00101110 $
b010 +
b1000 -
1.
02
b1000 6
07
#370
0.
b01000001 1
13
18
#371
b011 ,
b0111 -
1.
12
b00011111 5
b0111 6
17
#372
0.
00
b10010011 1
03
07
08
#373
1.
#374
0.
b11010010 1
#375
1.
#376
0.
10
b10010110 1
13
17
18
#377
b10010110 %
b011 +
b100 ,
1.
b00111001 5
#378
0.
b11111101 1
#379
b11111101 &
b100 +
b101 ,
1.
b10011000 5
#380
0.
b10011011 1
03
08
#381
b10011011 '
b101 +
b1000 -
1.
02
b1000 6
07
#382
0.
b11100011 1
#383
1.
#384
0.
b11010000 1
13
18
#385
b110 ,
b0111 -
1.
12
b01101110 5
b0111 6
17
#386
0.
00
b01001111 1
03
07
08
#387
1.
#388
0.
10
b01111011 1
13
17
18
#389
b01111011 (
b110 +
b111 ,
1.
b11111110 5
#390
0.
b10001011 1
#391
b10001011 )
b111 +
b000 ,
1.
b11100100 5
#392
0.
b00011001 1
03
08
#393
b00011001 *
b000 +
b1000 -
1.
02
b1000 6
07
#394
0.
b10100111 1
#395
1.
#396
0.
b11111110 1
13
18
#397
b001 ,
b0111 -
1.
12
b00101110 5
b0111 6
17
#398
0.
b01101011 1
03
08
#399
b01101011 #
b001 +
b1000 -
1.
02
b1000 6
07
#400
0.
00
b10011001 1
#401
1.
#402
0.
10
b01010000 1
#403
1.
#404
0.
00
b10011110 1
13
18
#405
b010 ,
b0111 -
1.
12
b10010110 5
b0111 6
#406
0.
10
b01101110 1
17
#407
b01101110 $
b010 +
b011 ,
1.
b11111101 5
#408
0.
00
b00100000 1
03
07
08
#409
1.
#410
0.
10
b11000110 1
17
#411
b11000110 %
b011 +
b1000 -
1.
02
b1000 6
07
#412
0.
00
b00110100 1
#413
1.
#414
0.
b01100110 1
13
18
#415
b100 ,
b0111 -
1.
12
b10011011 5
b0111 6
#416
0.
10
b10111100 1
03
17
08
#417
b10111100 &
b100 +
b1000 -
1.
02
b1000 6
07
#418
0.
b01011110 1
13
18
#419
b101 ,
b0111 -
1.
12
b01111011 5
b0111 6
17
#420
0.
00
b10011100 1
03
07
08
#421
1.
#422
0.
b00000010 1
13
18
#423
b110 ,
b0110 -
1.
b10001011 5
b0110 6
#424
0.
10
b00110011 1
03
17
08
#425
b00110011 '
b101 +
b0111 -
1.
b0111 6
#426
0.
00
b00110000 1
07
#427
1.
#428
0.
10
b10011000 1
17
#429
b10011000 (
b110 +
b1000 -
1.
02
b1000 6
07
#430
0.
00
b11001010 1
13
18
#431
b111 ,
b0111 -
1.
12
b00011001 5
b0111 6
#432
0.
10
b10010000 1
17
#433
b10010000 )
b111 +
b000 ,
1.
b01101011 5
#434
0.
b01001010 1
#435
b01001010 *
b000 +
b001 ,
1.
b01101110 5
#436
0.
b11100011 1
#437
b11100011 #
b001 +
b010 ,
1.
b11000110 5
#438
0.
00
b10110011 1
07
#439
b011 ,
b0110 -
1.
b10111100 5
b0110 6
#440
0.
10
b11000100 1
17
#441
b11000100 $
b010 +
b100 ,
1.
b00110011 5
#442
0.
b01010010 1
#443
b01010010 %
b011 +
b101 ,
1.
b10011000 5
#444
0.
b11100111 1
#445
b11100111 &
b100 +
b110 ,
1.
b10010000 5
#446
0.
00
b00100111 1
03
07
08
#447
1.
#448
0.
10
b10100010 1
17
#449
b10100010 '
b101 +
b0111 -
1.
b0111 6
#450
0.
00
b00000000 1
13
07
18
#451
b111 ,
b0110 -
1.
b01001010 5
b0110 6
#452
0.
#453
b000 ,
b0101 -
1.
b11100011 5
b0101 6
#454
0.
#455
b001 ,
b0100 -
1.
b11000100 5
b0100 6
#456
0.
#457
b010 ,
b0011 -
1.
b01010010 5
b0011 6
#458
0.
#459
b011 ,
b0010 -
1.
b11100111 5
b0010 6
#460
0.
#461
b100 ,
b0001 -
1.
b10100010 5
b0001 6
#462
0.
#463
b101 ,
b0000 -
1.
04
b10011000 5
b0000 6
08
