sv_common_ips/11_bus_interconnect_contention/top.sv
// top.sv - Lesson 11
//
// Use-case:
//  - Multiple on-chip bus masters contending for one slave/register block.
//  - Round-robin arbitration across three masters.

module top (
    input  logic clk,
    input  logic rst_n,

    input  logic        m0_valid,
    input  logic        m0_we,
    input  logic [1:0]  m0_addr,
    input  logic [31:0] m0_wdata,
    output logic        m0_ready,
    output logic [31:0] m0_rdata,

    input  logic        m1_valid,
    input  logic        m1_we,
    input  logic [1:0]  m1_addr,
    input  logic [31:0] m1_wdata,
    output logic        m1_ready,
    output logic [31:0] m1_rdata,

    input  logic        m2_valid,
    input  logic        m2_we,
    input  logic [1:0]  m2_addr,
    input  logic [31:0] m2_wdata,
    output logic        m2_ready,
    output logic [31:0] m2_rdata,

    output logic [2:0]  grant,
    output logic [1:0]  rr_ptr_dbg
);
    logic [31:0] regs [0:3];
    logic [1:0] rr_ptr;

    always_comb begin
        logic [2:0] valid;
        valid = {m2_valid, m1_valid, m0_valid};

        grant = 3'b000;
        for (int off = 0; off < 3; off++) begin
            int idx;
            idx = int'(rr_ptr) + off;
            if (idx >= 3) idx = idx - 3;

            if (grant == 3'b000 && valid[idx]) begin
                grant[idx] = 1'b1;
            end
        end
    end

    assign rr_ptr_dbg = rr_ptr;

    always_ff @(posedge clk) begin
        if (!rst_n) begin
            rr_ptr <= 2'd0;
            m0_ready <= 1'b0;
            m1_ready <= 1'b0;
            m2_ready <= 1'b0;
            m0_rdata <= '0;
            m1_rdata <= '0;
            m2_rdata <= '0;
            regs[0] <= 32'h0000_1000;
            regs[1] <= 32'h0000_1001;
            regs[2] <= 32'h0000_1002;
            regs[3] <= 32'h0000_1003;
        end else begin
            m0_ready <= 1'b0;
            m1_ready <= 1'b0;
            m2_ready <= 1'b0;

            if (grant[0]) begin
                m0_ready <= 1'b1;
                if (m0_we) regs[m0_addr] <= m0_wdata;
                else       m0_rdata <= regs[m0_addr];
                rr_ptr <= 2'd1;
            end

            if (grant[1]) begin
                m1_ready <= 1'b1;
                if (m1_we) regs[m1_addr] <= m1_wdata;
                else       m1_rdata <= regs[m1_addr];
                rr_ptr <= 2'd2;
            end

            if (grant[2]) begin
                m2_ready <= 1'b1;
                if (m2_we) regs[m2_addr] <= m2_wdata;
                else       m2_rdata <= regs[m2_addr];
                rr_ptr <= 2'd0;
            end
        end
    end

    always_ff @(posedge clk) begin
        if (rst_n) begin
            assert ($onehot0(grant))
                else $fatal(1, "Bus interconnect violation: grant must be one-hot or zero");

            assert (!(grant[0] && !m0_valid))
                else $fatal(1, "Bus interconnect violation: m0 granted without valid");
            assert (!(grant[1] && !m1_valid))
                else $fatal(1, "Bus interconnect violation: m1 granted without valid");
            assert (!(grant[2] && !m2_valid))
                else $fatal(1, "Bus interconnect violation: m2 granted without valid");
        end
    end

endmodule

sv_common_ips/11_bus_interconnect_contention/waveform.vcd
$version Generated by VerilatedVcd $end
$timescale 1ps $end
 $scope module TOP $end
  $var wire 1 ( clk $end
  $var wire 1 ) rst_n $end
  $var wire 1 * m0_valid $end
  $var wire 1 + m0_we $end
  $var wire 2 , m0_addr [1:0] $end
  $var wire 32 - m0_wdata [31:0] $end
  $var wire 1 . m0_ready $end
  $var wire 32 / m0_rdata [31:0] $end
  $var wire 1 0 m1_valid $end
  $var wire 1 1 m1_we $end
  $var wire 2 2 m1_addr [1:0] $end
  $var wire 32 3 m1_wdata [31:0] $end
  $var wire 1 4 m1_ready $end
  $var wire 32 5 m1_rdata [31:0] $end
  $var wire 1 6 m2_valid $end
  $var wire 1 7 m2_we $end
  $var wire 2 8 m2_addr [1:0] $end
  $var wire 32 9 m2_wdata [31:0] $end
  $var wire 1 : m2_ready $end
  $var wire 32 ; m2_rdata [31:0] $end
  $var wire 3 < grant [2:0] $end
  $var wire 2 = rr_ptr_dbg [1:0] $end
  $scope module top $end
   $var wire 1 ( clk $end
   $var wire 1 ) rst_n $end
   $var wire 1 * m0_valid $end
   $var wire 1 + m0_we $end
   $var wire 2 , m0_addr [1:0] $end
   $var wire 32 - m0_wdata [31:0] $end
   $var wire 1 . m0_ready $end
   $var wire 32 / m0_rdata [31:0] $end
   $var wire 1 0 m1_valid $end
   $var wire 1 1 m1_we $end
   $var wire 2 2 m1_addr [1:0] $end
   $var wire 32 3 m1_wdata [31:0] $end
   $var wire 1 4 m1_ready $end
   $var wire 32 5 m1_rdata [31:0] $end
   $var wire 1 6 m2_valid $end
   $var wire 1 7 m2_we $end
   $var wire 2 8 m2_addr [1:0] $end
   $var wire 32 9 m2_wdata [31:0] $end
   $var wire 1 : m2_ready $end
   $var wire 32 ; m2_rdata [31:0] $end
   $var wire 3 < grant [2:0] $end
   $var wire 2 = rr_ptr_dbg [1:0] $end
   $var wire 32 # regs[0] [31:0] $end
   $var wire 32 $ regs[1] [31:0] $end
   $var wire 32 % regs[2] [31:0] $end
   $var wire 32 & regs[3] [31:0] $end
   $var wire 2 ' rr_ptr [1:0] $end
   $scope module unnamedblk1 $end
    $var wire 3 > valid [2:0] $end
    $scope module unnamedblk2 $end
     $var wire 32 @ off [31:0] $end
     $scope module unnamedblk3 $end
      $var wire 32 ? idx [31:0] $end
     $upscope $end
    $upscope $end
   $upscope $end
  $upscope $end
 $upscope $end
$enddefinitions $end


#0
b00000000000000000000000000000000 #
b00000000000000000000000000000000 $
b00000000000000000000000000000000 %
b00000000000000000000000000000000 &
b00 '
0(
0)
0*
0+
b00 ,
b00000000000000000000000000000000 -
0.
b00000000000000000000000000000000 /
00
01
b00 2
b00000000000000000000000000000000 3
04
b00000000000000000000000000000000 5
06
07
b00 8
b00000000000000000000000000000000 9
0:
b00000000000000000000000000000000 ;
b000 <
b00 =
b000 >
b00000000000000000000000000000010 ?
b00000000000000000000000000000011 @
#1
b00000000000000000001000000000000 #
b00000000000000000001000000000001 $
b00000000000000000001000000000010 %
b00000000000000000001000000000011 &
1(
#2
0(
#3
1(
#4
0(
#5
1(
#6
0(
#7
1(
#8
0(
#9
1(
#10
0(
1)
1+
b10 ,
b00000000000000001111000000011000 -
10
11
b11 2
b00000000000000000010110111110110 3
17
b11 8
b00000000000000000001100000000100 9
b010 <
b010 >
#11
b00000000000000000010110111110110 &
b10 '
1(
14
b10 =
b00000000000000000000000000000001 ?
#12
0(
1*
b00 ,
b00000000000000001101011001101110 -
00
b00000000000000000110001100110001 3
16
07
b01 8
b00000000000000000101001010000000 9
b100 <
b101 >
#13
b00 '
1(
04
1:
b00000000000000000001000000000001 ;
b001 <
b00 =
b00000000000000000000000000000010 ?
#14
0(
0+
b10 ,
b00000000000000001110111100101010 -
b01 2
b00000000000000000000011001111100 3
b10 8
b00000000000000001100000111000000 9
#15
b01 '
1(
1.
b00000000000000000001000000000010 /
0:
b100 <
b01 =
b00000000000000000000000000000000 ?
#16
0(
0*
b11 ,
b00000000000000000001111001100011 -
10
01
b00000000000000001110111000001000 3
06
17
b01 8
b00000000000000000010110001001000 9
b010 <
b010 >
#17
b10 '
1(
0.
14
b00000000000000000001000000000001 5
b10 =
b00000000000000000000000000000001 ?
#18
0(
1+
b00 ,
b00000000000000000111001001011110 -
11
b00 2
b00000000000000001010010000110001 3
07
b00000000000000000010001000001000 9
#19
b00000000000000001010010000110001 #
1(
#20
0(
1*
0+
b11 ,
b00000000000000000110111010101100 -
b00000000000000000010000111101101 3
16
17
b00 8
b00000000000000001011101010111101 9
b100 <
b111 >
#21
b00000000000000001011101010111101 #
b00 '
1(
04
1:
b001 <
b00 =
b00000000000000000000000000000010 ?
#22
0(
1+
b01 ,
b00000000000000001101111100110111 -
b11 2
b00000000000000000000101010000101 3
06
b11 8
b00000000000000000001101011011000 9
b011 >
#23
b00000000000000001101111100110111 $
b01 '
1(
1.
0:
b010 <
b01 =
b00000000000000000000000000000000 ?
#24
0(
0*
0+
b00000000000000000110100001011010 -
00
b01 2
b00000000000000001111110000001110 3
07
b10 8
b00000000000000000111111110111111 9
b000 <
b000 >
#25
1(
0.
#26
0(
1*
b11 ,
b00000000000000000110011100101010 -
b10 2
b00000000000000001010111111010000 3
b11 8
b00000000000000000101111011101110 9
b001 <
b001 >
#27
1(
1.
b00000000000000000010110111110110 /
#28
0(
b10 ,
b00000000000000000010010000100100 -
10
01
b11 2
b00000000000000001001111110100011 3
16
b01 8
b00000000000000000100111000110011 9
b010 <
b111 >
#29
b10 '
1(
0.
14
b00000000000000000010110111110110 5
b100 <
b10 =
b00000000000000000000000000000001 ?
#30
0(
b01 ,
b00000000000000000001110001111001 -
b00 2
b00000000000000000000000000100001 3
06
b11 8
b00000000000000000000111111001001 9
b001 <
b011 >
#31
b01 '
1(
1.
b00000000000000001101111100110111 /
04
b010 <
b01 =
b00000000000000000000000000000000 ?
#32
0(
b11 ,
b00000000000000000100100110110110 -
b11 2
b00000000000000000010001100001000 3
16
b10 8
b00000000000000000010001001011100 9
b111 >
#33
b10 '
1(
0.
14
b100 <
b10 =
b00000000000000000000000000000001 ?
#34
0(
b10 ,
b00000000000000001000111001110001 -
00
b01 2
b00000000000000000001100110010011 3
17
b11 8
b00000000000000001101100100110110 9
b101 >
#35
b00000000000000001101100100110110 &
b00 '
1(
04
1:
b001 <
b00 =
b00000000000000000000000000000010 ?
#36
0(
0*
1+
b00000000000000000100001100101011 -
11
b10 2
b00000000000000000110101110111111 3
06
07
b00 8
b00000000000000001001011100000010 9
b000 <
b000 >
#37
1(
0:
#38
0(
1*
b00 ,
b00000000000000000000111011001110 -
10
b00000000000000000110101001101100 3
b10 8
b00000000000000001001001011011001 9
b001 <
b011 >
#39
b00000000000000000000111011001110 #
b01 '
1(
1.
b010 <
b01 =
b00000000000000000000000000000000 ?
#40
0(
0+
b00000000000000000101001100011100 -
00
b11 2
b00000000000000000001101111001001 3
b01 8
b00000000000000000111010110111011 9
b001 <
b001 >
#41
1(
b00000000000000000000111011001110 /
#42
0(
b01 ,
b00000000000000000110100001001001 -
b00000000000000001101111101001011 3
16
b11 8
b00000000000000001001011100001010 9
b100 <
b101 >
#43
b00 '
1(
0.
1:
b00000000000000001101100100110110 ;
b001 <
b00 =
b00000000000000000000000000000010 ?
#44
0(
b00 ,
b00000000000000000111000110011110 -
10
01
b01 2
b00000000000000001111011011000000 3
06
17
b00000000000000001010011000101000 9
b011 >
#45
b01 '
1(
1.
0:
b010 <
b01 =
b00000000000000000000000000000000 ?
#46
0(
1+
b11 ,
b00000000000000001000101010010111 -
00
b00000000000000001101010110100110 3
16
07
b00000000000000000100110010000001 9
b100 <
b101 >
#47
b00 '
1(
0.
1:
b001 <
b00 =
b00000000000000000000000000000010 ?
#48
0(
0+
b10 ,
b00000000000000000000110001110011 -
10
b00 2
b00000000000000000100001100000101 3
06
b00 8
b00000000000000000100010110100000 9
b011 >
#49
b01 '
1(
1.
b00000000000000000001000000000010 /
0:
b010 <
b01 =
b00000000000000000000000000000000 ?
#50
0(
0*
b00000000000000001111000001000011 -
11
b11 2
b00000000000000001011101111111010 3
17
b00000000000000001001100111110101 9
b010 >
#51
b00000000000000001011101111111010 &
b10 '
1(
0.
14
b10 =
b00000000000000000000000000000001 ?
#52
0(
1*
b00000000000000000001100010000100 -
01
b01 2
b00000000000000001000111011010111 3
07
b11 8
b00000000000000000000011001101110 9
b001 <
b011 >
#53
b01 '
1(
1.
04
b010 <
b01 =
b00000000000000000000000000000000 ?
#54
0(
b11 ,
b00000000000000001011111100101110 -
b10 2
b00000000000000000110001101100110 3
16
b00000000000000000111110010010110 9
b111 >
#55
b10 '
1(
0.
14
b00000000000000000001000000000010 5
b100 <
b10 =
b00000000000000000000000000000001 ?
#56
0(
b00 ,
b00000000000000001110110110001011 -
b00000000000000000000101010011101 3
06
b10 8
b00000000000000001000110011110011 9
b001 <
b011 >
#57
b01 '
1(
1.
b00000000000000000000111011001110 /
04
b010 <
b01 =
b00000000000000000000000000000000 ?
#58
0(
1+
b00000000000000001101110000100111 -
00
11
b00000000000000001100100101000100 3
16
b00000000000000001000111111010111 9
b100 <
b101 >
#59
b00 '
1(
0.
1:
b00000000000000000001000000000010 ;
b001 <
b00 =
b00000000000000000000000000000010 ?
#60
0(
0*
0+
b10 ,
b00000000000000001000011101010000 -
01
b11 2
b00000000000000001100000010100010 3
b11 8
b00000000000000000100011010110100 9
b100 <
b100 >
#61
1(
b00000000000000001011101111111010 ;
#62
0(
1*
b11 ,
b00000000000000000111010101110100 -
b01 2
b00000000000000001001000001000100 3
06
b00 8
b00000000000000001110000010011000 9
b001 <
b001 >
#63
b01 '
1(
1.
b00000000000000001011101111111010 /
0:
b01 =
b00000000000000000000000000000000 ?
#64
0(
1+
b10 ,
b00000000000000000110011001110101 -
10
11
b00000000000000001100101010110110 3
17
b10 8
b00000000000000001010010011011011 9
b010 <
b011 >
#65
b00000000000000001100101010110110 $
b10 '
1(
0.
14
b001 <
b10 =
b00000000000000000000000000000001 ?
#66
0(
0*
0+
b01 ,
b00000000000000000111011000010111 -
01
b00 2
b00000000000000000010001010111001 3
16
07
b11 8
b00000000000000000110101110000101 9
b100 <
b110 >
#67
b00 '
1(
04
1:
b010 <
b00 =
b00000000000000000000000000000010 ?
#68
0(
b10 ,
b00000000000000000001101111001001 -
00
b00000000000000000001101001001100 3
17
b00000000000000000000100001000001 9
b100 <
b100 >
#69
b00000000000000000000100001000001 &
1(
#70
0(
1*
1+
b00000000000000001001101001101000 -
10
11
b00000000000000000000110001001111 3
07
b00000000000000000001100110001110 9
b001 <
b111 >
#71
b00000000000000001001101001101000 %
b01 '
1(
1.
0:
b010 <
b01 =
b00000000000000000000000000000000 ?
#72
0(
0+
b01 ,
b00000000000000000000111111010001 -
00
b11 2
b00000000000000001011010011001101 3
06
b00000000000000000101110101111110 9
b001 <
b001 >
#73
1(
b00000000000000001100101010110110 /
#74
0(
b00000000000000001111000000010010 -
10
b01 2
b00000000000000001000100101110111 3
16
17
b10 8
b00000000000000001011000110101000 9
b010 <
b111 >
#75
b00000000000000001000100101110111 $
b10 '
1(
0.
14
b100 <
b10 =
b00000000000000000000000000000001 ?
#76
0(
1+
b11 ,
b00000000000000000110110101001010 -
00
b10 2
b00000000000000001100100100100111 3
b00000000000000000001100011000111 9
b101 >
#77
b00000000000000000001100011000111 %
b00 '
1(
04
1:
b001 <
b00 =
b00000000000000000000000000000010 ?
#78
0(
0*
b00 ,
b00000000000000001100111011111001 -
10
01
b01 2
b00000000000000001011110111000001 3
b00000000000000000010001001100010 9
b010 <
b110 >
#79
b10 '
1(
14
b00000000000000001000100101110111 5
0:
b100 <
b10 =
b00000000000000000000000000000001 ?
#80
0(
1*
0+
b11 ,
b00000000000000000001000110101010 -
11
b00 2
b00000000000000001000111011110011 3
06
07
b01 8
b00000000000000000101111010100000 9
b001 <
b011 >
#81
b01 '
1(
1.
b00000000000000000000100001000001 /
04
b010 <
b01 =
b00000000000000000000000000000000 ?
#82
0(
1+
b00 ,
b00000000000000000000100010110100 -
00
b01 2
b00000000000000001000111011001111 3
16
17
b00 8
b00000000000000000010000001000000 9
b100 <
b101 >
#83
b00000000000000000010000001000000 #
b00 '
1(
0.
1:
b001 <
b00 =
b00000000000000000000000000000010 ?
#84
0(
0*
b01 ,
b00000000000000001001101000111110 -
01
b00 2
b00000000000000001111100100000010 3
06
07
b00000000000000001101111100110111 9
b000 <
b000 >
#85
1(
0:
#86
0(
1*
b00000000000000000100100000100011 -
10
b00000000000000000010010011100110 3
16
b11 8
b00000000000000000101001111100001 9
b001 <
b111 >
#87
b00000000000000000100100000100011 $
b01 '
1(
1.
b010 <
b01 =
b00000000000000000000000000000000 ?
#88
0(
0+
b00 ,
b00000000000000001000000100011111 -
b00000000000000001100010001111001 3
06
b00 8
b00000000000000000110101111010111 9
b011 >
#89
b10 '
1(
0.
14
b00000000000000000010000001000000 5
b001 <
b10 =
b00000000000000000000000000000001 ?
#90
0(
1+
b10 ,
b00000000000000000100000010000000 -
00
b01 2
b00000000000000000111111001101100 3
16
17
b11 8
b00000000000000000100000010101000 9
b100 <
b101 >
#91
b00000000000000000100000010101000 &
b00 '
1(
04
1:
b001 <
b00 =
b00000000000000000000000000000010 ?
#92
0(
0+
b00 ,
b00000000000000001010111000001111 -
11
b00 2
b00000000000000001111101110110011 3
b01 8
b00000000000000000110100111011100 9
#93
b01 '
1(
1.
b00000000000000000010000001000000 /
0:
b100 <
b01 =
b00000000000000000000000000000000 ?
#94
0(
1+
b01 ,
b00000000000000000110011010110100 -
01
b00000000000000001111011010010011 3
b11 8
b00000000000000000100011000010001 9
#95
b00000000000000000100011000010001 &
b00 '
1(
0.
1:
b001 <
b00 =
b00000000000000000000000000000010 ?
#96
0(
0*
0+
b10 ,
b00000000000000000101001011110100 -
10
b10 2
b00000000000000000110000001010001 3
b00000000000000001001010100011010 9
b010 <
b110 >
#97
b10 '
1(
14
b00000000000000000001100011000111 5
0:
b100 <
b10 =
b00000000000000000000000000000001 ?
#98
0(
1+
b00000000000000001000100001011110 -
b00 2
b00000000000000000010100110000010 3
b00000000000000000011100010011111 9
#99
b00000000000000000011100010011111 &
b00 '
1(
04
1:
b010 <
b00 =
b00000000000000000000000000000010 ?
#100
0(
0+
b00000000000000001100011101101011 -
00
b10 2
b00000000000000001100010000100100 3
06
07
b10 8
b00000000000000001001010000000101 9
b000 <
b000 >
#101
1(
0:
#102
0(
b01 ,
b00000000000000000000101001001001 -
b11 2
b00000000000000001110111101110000 3
17
b00000000000000000000001111100111 9
#103
1(
#104
0(
b00 ,
b00000000000000000111011000010011 -
10
11
b10 2
b00000000000000000011111001101001 3
07
b01 8
b00000000000000001110101000101101 9
b010 <
b010 >
#105
b00000000000000000011111001101001 %
b10 '
1(
14
b10 =
b00000000000000000000000000000001 ?
#106
0(
1+
b11 ,
b00000000000000001000010101000111 -
01
b11 2
b00000000000000000111001101011110 3
16
17
b10 8
b00000000000000000110101110010000 9
b100 <
b110 >
#107
b00000000000000000110101110010000 %
b00 '
1(
04
1:
b010 <
b00 =
b00000000000000000000000000000010 ?
#108
0(
b10 ,
b00000000000000001010100000101110 -
b01 2
b00000000000000000000011011010101 3
b00 8
b00000000000000000010100001111110 9
#109
b10 '
1(
14
b00000000000000000100100000100011 5
0:
b100 <
b10 =
b00000000000000000000000000000001 ?
#110
0(
1*
b11 ,
b00000000000000000101110110001011 -
00
11
b11 2
b00000000000000001111011000100010 3
06
b10 8
b00000000000000000000010011111011 9
b001 <
b001 >
#111
b00000000000000000101110110001011 &
b01 '
1(
1.
04
b01 =
b00000000000000000000000000000000 ?
#112
0(
0+
b00000000000000001100011011100100 -
10
01
b01 2
b00000000000000001011011001011001 3
16
b11 8
b00000000000000001110101010111011 9
b010 <
b111 >
#113
b10 '
1(
0.
14
b100 <
b10 =
b00000000000000000000000000000001 ?
#114
0(
1+
b00000000000000000101101010110011 -
11
b11 2
b00000000000000001001000000011110 3
07
b00000000000000000100011001101110 9
#115
b00 '
1(
04
1:
b00000000000000000101110110001011 ;
b001 <
b00 =
b00000000000000000000000000000010 ?
#116
0(
0+
b01 ,
b00000000000000001101100100110100 -
00
b00 2
b00000000000000001100000010101000 3
17
b10 8
b00000000000000001101111101011110 9
b101 >
#117
b01 '
1(
1.
b00000000000000000100100000100011 /
0:
b100 <
b01 =
b00000000000000000000000000000000 ?
#118
0(
0*
1+
b00 ,
b00000000000000001000110111100000 -
b01 2
b00000000000000001100001111000110 3
06
07
b11 8
b00000000000000001110100000000010 9
b000 <
b000 >
#119
1(
0.
#120
0(
0+
b01 ,
b00000000000000001011101010001100 -
10
01
b10 2
b00000000000000000000100110000010 3
16
17
b10 8
b00000000000000001111011000100101 9
b010 <
b110 >
#121
b10 '
1(
14
b00000000000000000110101110010000 5
b100 <
b10 =
b00000000000000000000000000000001 ?
#122
0(
1*
b11 ,
b00000000000000000110101110001010 -
00
b11 2
b00000000000000000010100101000000 3
b11 8
b00000000000000001100011101101111 9
b101 >
#123
b00000000000000001100011101101111 &
b00 '
1(
04
1:
b001 <
b00 =
b00000000000000000000000000000010 ?
#124
0(
0*
1+
b10 ,
b00000000000000000111110110110100 -
b10 2
b00000000000000000101010001111100 3
06
b00 8
b00000000000000001010011100101001 9
b000 <
b000 >
#125
1(
0:
#126
0(
1*
0+
b01 ,
b00000000000000001111101010000011 -
b01 2
b00000000000000000010001001010111 3
16
07
b10 8
b00000000000000001101110011000110 9
b001 <
b101 >
#127
b01 '
1(
1.
b100 <
b01 =
b00000000000000000000000000000000 ?
#128
0(
b11 ,
b00000000000000000010111000101001 -
b11 2
b00000000000000000110000111010011 3
06
b01 8
b00000000000000000001001100110010 9
b001 <
b001 >
#129
1(
b00000000000000001100011101101111 /
#130
0(
0*
b00000000000000001010100000110111 -
10
11
b00000000000000000000101010110101 3
16
17
b10 8
b00000000000000000010001000101011 9
b010 <
b110 >
#131
b00000000000000000000101010110101 &
b10 '
1(
0.
14
b100 <
b10 =
b00000000000000000000000000000001 ?
#132
0(
1*
b10 ,
b00000000000000001011011001011000 -
b00 2
b00000000000000000101101001100110 3
06
b11 8
b00000000000000000011010111010101 9
b001 <
b011 >
#133
b01 '
1(
1.
b00000000000000000110101110010000 /
04
b010 <
b01 =
b00000000000000000000000000000000 ?
#134
0(
1+
b11 ,
b00000000000000000000110010010110 -
b01 2
b00000000000000001000110111011010 3
16
b01 8
b00000000000000001101001111010000 9
b111 >
#135
b00000000000000001000110111011010 $
b10 '
1(
0.
14
b100 <
b10 =
b00000000000000000000000000000001 ?
#136
0(
0*
b10 ,
b00000000000000000011111000100110 -
01
b00000000000000001100111001001011 3
07
b11 8
b00000000000000000110001010000010 9
b110 >
#137
b00 '
1(
04
1:
b00000000000000000000101010110101 ;
b010 <
b00 =
b00000000000000000000000000000010 ?
#138
0(
1*
0+
b11 ,
b00000000000000001011101111110011 -
11
b00 2
b00000000000000001101000011000000 3
06
b10 8
b00000000000000001101001000011010 9
b001 <
b011 >
#139
b01 '
1(
1.
b00000000000000000000101010110101 /
0:
b010 <
b01 =
b00000000000000000000000000000000 ?
#140
0(
b01 ,
b00000000000000000001010111001100 -
01
b10 2
b00000000000000000001010001111110 3
b01 8
b00000000000000001011111100001011 9
#141
b10 '
1(
0.
14
b001 <
b10 =
b00000000000000000000000000000001 ?
#142
0(
b11 ,
b00000000000000001111000011100011 -
00
11
b01 2
b00000000000000001110110001011001 3
16
17
b10 8
b00000000000000001011001001111011 9
b100 <
b101 >
#143
b00000000000000001011001001111011 %
b00 '
1(
04
1:
b001 <
b00 =
b00000000000000000000000000000010 ?
#144
0(
1+
b01 ,
b00000000000000001110100011110111 -
b10 2
b00000000000000001110101011111000 3
07
b01 8
b00000000000000001100111000001100 9
#145
b00000000000000001110100011110111 $
b01 '
1(
1.
0:
b100 <
b01 =
b00000000000000000000000000000000 ?
#146
0(
b00000000000000000010110011001100 -
01
b00 2
b00000000000000001000000011101011 3
06
17
b10 8
b00000000000000001110000111001111 9
b001 <
b001 >
#147
b00000000000000000010110011001100 $
1(
#148
0(
b11 ,
b00000000000000000111111000000001 -
b01 2
b00000000000000001110101110100010 3
16
07
b11 8
b00000000000000000110111000101011 9
b100 <
b101 >
#149
b00 '
1(
0.
1:
b001 <
b00 =
b00000000000000000000000000000010 ?
#150
0(
b01 ,
b00000000000000000001001011110111 -
10
b00000000000000001111010101010110 3
17
b10 8
b00000000000000000100111011110100 9
b111 >
#151
b00000000000000000001001011110111 $
b01 '
1(
1.
0:
b010 <
b01 =
b00000000000000000000000000000000 ?
#152
0(
0*
b11 ,
b00000000000000001110111001000100 -
11
b00 2
b00000000000000001011010111000011 3
06
07
b01 8
b00000000000000000100000110000110 9
b010 >
#153
b00000000000000001011010111000011 #
b10 '
1(
0.
14
b10 =
b00000000000000000000000000000001 ?
#154
0(
0+
b01 ,
b00000000000000001101111100010101 -
00
b11 2
b00000000000000001111110101010111 3
16
b11 8
b00000000000000001000101000011110 9
b100 <
b100 >
#155
b00 '
1(
04
1:
b00 =
b00000000000000000000000000000010 ?
#156
0(
b00000000000000001011110101010101 -
01
b00000000000000000101110000010100 3
17
b00 8
b00000000000000001111011001111110 9
#157
b00000000000000001111011001111110 #
1(
#158
0(
1+
b00 ,
b00000000000000000000001011111101 -
10
b00000000000000001000010001011000 3
06
07
b10 8
b00000000000000001110111100101100 9
b010 <
b010 >
#159
b10 '
1(
14
b00000000000000000000101010110101 5
0:
b10 =
b00000000000000000000000000000001 ?
#160
0(
1*
b10 ,
b00000000000000001101110011010110 -
11
b00000000000000000000111110110101 3
b01 8
b00000000000000001101110001111001 9
b001 <
b011 >
#161
b00000000000000001101110011010110 %
b01 '
1(
1.
04
b010 <
b01 =
b00000000000000000000000000000000 ?
#162
0(
0*
b00000000000000001110001111000010 -
00
b00 2
b00000000000000000000010001111100 3
b10 8
b00000000000000001101100000110110 9
b000 <
b000 >
#163
1(
0.
#164
0(
1*
b01 ,
b00000000000000000000100100000101 -
10
b00000000000000001010010101001010 3
16
b00000000000000000110010011011110 9
b010 <
b111 >
#165
b00000000000000001010010101001010 #
b10 '
1(
14
b100 <
b10 =
b00000000000000000000000000000001 ?
#166
0(
0*
b11 ,
b00000000000000000000000000111000 -
01
b10 2
b00000000000000000001000110111110 3
b00000000000000001011100111100000 9
b110 >
#167
b00 '
1(
04
1:
b00000000000000001101110011010110 ;
b010 <
b00 =
b00000000000000000000000000000010 ?
#168
0(
0+
b10 ,
b00000000000000001001110110111110 -
00
b00000000000000000110111010110001 3
b00 8
b00000000000000000011010101001110 9
b100 <
b100 >
#169
1(
b00000000000000001010010101001010 ;
#170
0(
b01 ,
b00000000000000001101011101000010 -
10
11
b00000000000000000000100001101001 3
17
b01 8
b00000000000000000101100001110010 9
b010 <
b110 >
#171
b00000000000000000000100001101001 %
b10 '
1(
14
0:
b100 <
b10 =
b00000000000000000000000000000001 ?
#172
0(
1*
b00 ,
b00000000000000001001110000101111 -
b00 2
b00000000000000000001001110011011 3
b00000000000000000101011011110110 9
b111 >
#173
b00000000000000000101011011110110 $
b00 '
1(
04
1:
b001 <
b00 =
b00000000000000000000000000000010 ?
#174
0(
1+
b10 ,
b00000000000000001000100000110001 -
b10 2
b00000000000000000011011101110010 3
b10 8
b00000000000000000101101010001000 9
#175
b00000000000000001000100000110001 %
b01 '
1(
1.
0:
b010 <
b01 =
b00000000000000000000000000000000 ?
#176
0(
0+
b01 ,
b00000000000000001001100010001100 -
00
01
b11 2
b00000000000000000101001010100000 3
b01 8
b00000000000000000000010110011010 9
b100 <
b101 >
#177
b00000000000000000000010110011010 $
b00 '
1(
0.
1:
b001 <
b00 =
b00000000000000000000000000000010 ?
#178
0(
0*
1+
b10 ,
b00000000000000001110101011101010 -
10
b01 2
b00000000000000000111111000101011 3
06
b00 8
b00000000000000001011110000111110 9
b010 <
b010 >
#179
b10 '
1(
14
b00000000000000000000010110011010 5
0:
b10 =
b00000000000000000000000000000001 ?
#180
0(
b11 ,
b00000000000000000110000000110101 -
00
b11 2
b00000000000000000010010100010100 3
07
b10 8
b00000000000000000010100110000100 9
b000 <
b000 >
#181
1(
04
#182
0(
1*
0+
b00 ,
b00000000000000000110111100011011 -
11
b10 2
b00000000000000000011100011100100 3
16
17
b00 8
b00000000000000001000001001110011 9
b100 <
b101 >
#183
b00000000000000001000001001110011 #
b00 '
1(
1:
b001 <
b00 =
b00000000000000000000000000000010 ?
#184
0(
0*
1+
b10 ,
b00000000000000001001011011001010 -
10
b00 2
b00000000000000000010000010101100 3
07
b00000000000000001111110101111110 9
b010 <
b110 >
#185
b00000000000000000010000010101100 #
b10 '
1(
14
0:
b100 <
b10 =
b00000000000000000000000000000001 ?
#186
0(
1*
b00000000000000000100011000000100 -
01
b01 2
b00000000000000000100111000100110 3
06
b00000000000000000001011000110110 9
b001 <
b011 >
#187
b00000000000000000100011000000100 %
b01 '
1(
1.
04
b010 <
b01 =
b00000000000000000000000000000000 ?
#188
0(
0*
0+
b00000000000000001010101001101011 -
b11 2
b00000000000000001000111111111101 3
b10 8
b00000000000000000000111011111101 9
b010 >
#189
b10 '
1(
0.
14
b00000000000000000000101010110101 5
b10 =
b00000000000000000000000000000001 ?
#190
0(
1+
b00000000000000000001011010000111 -
00
11
b00 2
b00000000000000000010001001011000 3
17
b00000000000000001101010110010011 9
b000 <
b000 >
#191
1(
04
#192
0(
1*
b11 ,
b00000000000000000110111010100011 -
10
01
b00000000000000000110011101011111 3
16
b00 8
b00000000000000001110000111110001 9
b100 <
b111 >
#193
b00000000000000001110000111110001 #
b00 '
1(
1:
b001 <
b00 =
b00000000000000000000000000000010 ?
#194
0(
0+
b00 ,
b00000000000000000000110100100000 -
00
11
b00000000000000001101111100100001 3
07
b00000000000000001011101111111110 9
b101 >
#195
b01 '
1(
1.
b00000000000000001110000111110001 /
0:
b100 <
b01 =
b00000000000000000000000000000000 ?
#196
0(
1+
b10 ,
b00000000000000000111100101101000 -
10
01
b11 2
b00000000000000000011000110110111 3
17
b01 8
b00000000000000000011000111011100 9
b010 <
b111 >
#197
b10 '
1(
0.
14
b100 <
b10 =
b00000000000000000000000000000001 ?
#198
0(
b00000000000000001001011000101100 -
11
b10 2
b00000000000000001001000011011101 3
07
b00 8
b00000000000000001010010010111100 9
#199
b00 '
1(
04
1:
b00000000000000001110000111110001 ;
b001 <
b00 =
b00000000000000000000000000000010 ?
#200
0(
0+
b00000000000000000110000001110110 -
01
b00 2
b00000000000000000101010111000110 3
17
b10 8
b00000000000000001100111001111111 9
#201
b01 '
1(
1.
b00000000000000000100011000000100 /
0:
b010 <
b01 =
b00000000000000000000000000000000 ?
#202
0(
1+
b01 ,
b00000000000000000011010110101001 -
00
11
b01 2
b00000000000000000111000100100110 3
07
b01 8
b00000000000000001010001011010011 9
b100 <
b101 >
