sv_common_ips/15_cache_memory_queue_contention/top.sv
// top.sv - Lesson 15
//
// Use-case:
//  - Cache/memory-system queues contending for a memory port.
//  - Refill queue and miss-status queue both feed one downstream port.

module top (
    input  logic clk,
    input  logic rst_n,

    input  logic       miss_push,
    input  logic [7:0] miss_addr_in,
    output logic       miss_full,

    input  logic        refill_push,
    input  logic [7:0]  refill_addr_in,
    input  logic [31:0] refill_data_in,
    output logic        refill_full,

    input  logic       mem_ready,
    output logic       issue_valid,
    output logic       issue_is_refill,
    output logic [7:0] issue_addr,
    output logic [31:0] issue_wdata,

    output logic [2:0] miss_count,
    output logic [2:0] refill_count
);
    localparam int DEPTH = 4;

    logic [7:0] miss_addr_q [0:DEPTH-1];
    logic [1:0] miss_wptr;
    logic [1:0] miss_rptr;
    logic [2:0] miss_used;

    logic [7:0]  refill_addr_q [0:DEPTH-1];
    logic [31:0] refill_data_q [0:DEPTH-1];
    logic [1:0] refill_wptr;
    logic [1:0] refill_rptr;
    logic [2:0] refill_used;

    logic miss_pop;
    logic refill_pop;
    logic miss_do_push;
    logic refill_do_push;

    assign miss_full = (miss_used == 3'd4);
    assign refill_full = (refill_used == 3'd4);
    assign miss_count = miss_used;
    assign refill_count = refill_used;
    assign miss_do_push = miss_push && !miss_full;
    assign refill_do_push = refill_push && !refill_full;

    always_comb begin
        issue_valid = 1'b0;
        issue_is_refill = 1'b0;
        issue_addr = 8'h00;
        issue_wdata = 32'h0000_0000;

        miss_pop = 1'b0;
        refill_pop = 1'b0;

        if (mem_ready) begin
            if (refill_used != 0) begin
                issue_valid = 1'b1;
                issue_is_refill = 1'b1;
                issue_addr = refill_addr_q[refill_rptr];
                issue_wdata = refill_data_q[refill_rptr];
                refill_pop = 1'b1;
            end else if (miss_used != 0) begin
                issue_valid = 1'b1;
                issue_is_refill = 1'b0;
                issue_addr = miss_addr_q[miss_rptr];
                issue_wdata = 32'h0000_0000;
                miss_pop = 1'b1;
            end
        end
    end

    always_ff @(posedge clk) begin
        if (!rst_n) begin
            miss_wptr <= 2'd0;
            miss_rptr <= 2'd0;
            miss_used <= 3'd0;

            refill_wptr <= 2'd0;
            refill_rptr <= 2'd0;
            refill_used <= 3'd0;
        end else begin
            // Miss queue push
            if (miss_do_push) begin
                miss_addr_q[miss_wptr] <= miss_addr_in;
                miss_wptr <= miss_wptr + 2'd1;
            end

            // Refill queue push
            if (refill_do_push) begin
                refill_addr_q[refill_wptr] <= refill_addr_in;
                refill_data_q[refill_wptr] <= refill_data_in;
                refill_wptr <= refill_wptr + 2'd1;
            end

            // Miss queue pop
            if (miss_pop) begin
                miss_rptr <= miss_rptr + 2'd1;
            end

            // Refill queue pop
            if (refill_pop) begin
                refill_rptr <= refill_rptr + 2'd1;
            end

            unique case ({miss_do_push, miss_pop})
                2'b10: miss_used <= miss_used + 3'd1;
                2'b01: miss_used <= miss_used - 3'd1;
                default: miss_used <= miss_used;
            endcase

            unique case ({refill_do_push, refill_pop})
                2'b10: refill_used <= refill_used + 3'd1;
                2'b01: refill_used <= refill_used - 3'd1;
                default: refill_used <= refill_used;
            endcase
        end
    end

    always_ff @(posedge clk) begin
        if (rst_n) begin
            if (issue_valid && issue_is_refill) begin
                assert (refill_used != 0)
                    else $fatal(1, "Cache queue violation: issued refill with empty refill queue");
            end

            if (issue_valid && !issue_is_refill) begin
                assert ((refill_used == 0) && (miss_used != 0))
                    else $fatal(1, "Cache queue violation: miss issued when refill should have priority");
            end

            assert (miss_used <= 3'd4)
                else $fatal(1, "Cache queue violation: miss queue overflow");
            assert (refill_used <= 3'd4)
                else $fatal(1, "Cache queue violation: refill queue overflow");
        end
    end

endmodule

sv_common_ips/15_cache_memory_queue_contention/waveform.vcd
$version Generated by VerilatedVcd $end
$timescale 1ps $end
 $scope module TOP $end
  $var wire 1 5 clk $end
  $var wire 1 6 rst_n $end
  $var wire 1 7 miss_push $end
  $var wire 8 8 miss_addr_in [7:0] $end
  $var wire 1 9 miss_full $end
  $var wire 1 : refill_push $end
  $var wire 8 ; refill_addr_in [7:0] $end
  $var wire 32 < refill_data_in [31:0] $end
  $var wire 1 = refill_full $end
  $var wire 1 > mem_ready $end
  $var wire 1 ? issue_valid $end
  $var wire 1 @ issue_is_refill $end
  $var wire 8 A issue_addr [7:0] $end
  $var wire 32 B issue_wdata [31:0] $end
  $var wire 3 C miss_count [2:0] $end
  $var wire 3 D refill_count [2:0] $end
  $scope module top $end
   $var wire 1 5 clk $end
   $var wire 1 6 rst_n $end
   $var wire 1 7 miss_push $end
   $var wire 8 8 miss_addr_in [7:0] $end
   $var wire 1 9 miss_full $end
   $var wire 1 : refill_push $end
   $var wire 8 ; refill_addr_in [7:0] $end
   $var wire 32 < refill_data_in [31:0] $end
   $var wire 1 = refill_full $end
   $var wire 1 > mem_ready $end
   $var wire 1 ? issue_valid $end
   $var wire 1 @ issue_is_refill $end
   $var wire 8 A issue_addr [7:0] $end
   $var wire 32 B issue_wdata [31:0] $end
   $var wire 3 C miss_count [2:0] $end
   $var wire 3 D refill_count [2:0] $end
   $var wire 32 I DEPTH [31:0] $end
   $var wire 8 # miss_addr_q[0] [7:0] $end
   $var wire 8 $ miss_addr_q[1] [7:0] $end
   $var wire 8 % miss_addr_q[2] [7:0] $end
   $var wire 8 & miss_addr_q[3] [7:0] $end
   $var wire 2 ' miss_wptr [1:0] $end
   $var wire 2 ( miss_rptr [1:0] $end
   $var wire 3 ) miss_used [2:0] $end
   $var wire 8 * refill_addr_q[0] [7:0] $end
   $var wire 8 + refill_addr_q[1] [7:0] $end
   $var wire 8 , refill_addr_q[2] [7:0] $end
   $var wire 8 - refill_addr_q[3] [7:0] $end
   $var wire 32 . refill_data_q[0] [31:0] $end
   $var wire 32 / refill_data_q[1] [31:0] $end
   $var wire 32 0 refill_data_q[2] [31:0] $end
   $var wire 32 1 refill_data_q[3] [31:0] $end
   $var wire 2 2 refill_wptr [1:0] $end
   $var wire 2 3 refill_rptr [1:0] $end
   $var wire 3 4 refill_used [2:0] $end
   $var wire 1 E miss_pop $end
   $var wire 1 F refill_pop $end
   $var wire 1 G miss_do_push $end
   $var wire 1 H refill_do_push $end
  $upscope $end
 $upscope $end
$enddefinitions $end


#0
b00000000 #
b00000000 $
b00000000 %
b00000000 &
b00 '
b00 (
b000 )
b00000000 *
b00000000 +
b00000000 ,
b00000000 -
b00000000000000000000000000000000 .
b00000000000000000000000000000000 /
b00000000000000000000000000000000 0
b00000000000000000000000000000000 1
b00 2
b00 3
b000 4
05
06
07
b00000000 8
09
0:
b00000000 ;
b00000000000000000000000000000000 <
0=
0>
0?
0@
b00000000 A
b00000000000000000000000000000000 B
b000 C
b000 D
0E
0F
0G
0H
b00000000000000000000000000000100 I
#1
15
#2
05
#3
15
#4
05
#5
15
#6
05
#7
15
#8
05
#9
15
#10
05
16
17
b00100111 8
1:
b01111101 ;
b00000000010110101011001010110111 <
1>
1G
1H
#11
b00100111 #
b01 '
b001 )
b01111101 *
b00000000010110101011001010110111 .
b01 2
b001 4
15
1?
1@
b01111101 A
b00000000010110101011001010110111 B
b001 C
b001 D
1F
#12
05
b10111100 8
0:
b01001000 ;
b00000000011000101100010010101100 <
0>
0?
0@
b00000000 A
b00000000000000000000000000000000 B
0F
0H
#13
b10111100 $
b10 '
b010 )
15
b010 C
#14
05
b00100010 8
1:
b01000000 ;
b00000000100111101100101100100000 <
1>
1?
1@
b01111101 A
b00000000010110101011001010110111 B
1F
1H
#15
b00100010 %
b11 '
b011 )
b01000000 +
b00000000100111101100101100100000 /
b10 2
b01 3
15
b01000000 A
b00000000100111101100101100100000 B
b011 C
#16
05
b01111111 8
0:
b00000111 ;
b00000000000100111011111101100100 <
0H
#17
b01111111 &
b00 '
b100 )
b10 3
b000 4
15
19
0@
b00100111 A
b00000000000000000000000000000000 B
b100 C
b000 D
1E
0F
0G
#18
05
07
b00001101 8
1:
b00110010 ;
b00000000110101111001101100101011 <
1H
#19
b01 (
b011 )
b00110010 ,
b00000000110101111001101100101011 0
b11 2
b001 4
15
09
1@
b00110010 A
b00000000110101111001101100101011 B
b011 C
b001 D
0E
1F
#20
05
17
b01010111 8
b00101011 ;
b00000000100110100010001101101110 <
1G
#21
b01010111 #
b01 '
b100 )
b00101011 -
b00000000100110100010001101101110 1
b00 2
b11 3
15
19
b00101011 A
b00000000100110100010001101101110 B
b100 C
0G
#22
05
07
b10110011 8
0:
b00110001 ;
b00000000001001001111001011101111 <
0H
#23
b00 3
b000 4
15
0@
b10111100 A
b00000000000000000000000000000000 B
b000 D
1E
0F
#24
05
b11001010 8
1:
b10001110 ;
b00000000011011011011100011100001 <
0>
0?
b00000000 A
0E
1H
#25
b10001110 *
b00000000011011011011100011100001 .
b01 2
b001 4
15
b001 D
#26
05
b10010110 8
b11111100 ;
b00000000111001110010011001111010 <
#27
b11111100 +
b00000000111001110010011001111010 /
b10 2
b010 4
15
b010 D
#28
05
b10101101 8
0:
b00010111 ;
b00000000010110101100000101010001 <
1>
1?
1@
b10001110 A
b00000000011011011011100011100001 B
1F
0H
#29
b01 3
b001 4
15
b11111100 A
b00000000111001110010011001111010 B
b001 D
#30
05
b10101100 8
b01001011 ;
b00000000110010111010100001000011 <
#31
b10 3
b000 4
15
0@
b10111100 A
b00000000000000000000000000000000 B
b000 D
1E
0F
#32
05
b11111101 8
1:
b00001011 ;
b00000000110001110100001110011111 <
0>
0?
b00000000 A
0E
1H
#33
b00001011 ,
b00000000110001110100001110011111 0
b11 2
b001 4
15
b001 D
#34
05
b11110111 8
0:
b00101011 ;
b00000000100000000000100101001110 <
1>
1?
1@
b00001011 A
b00000000110001110100001110011111 B
1F
0H
#35
b11 3
b000 4
15
0@
b10111100 A
b00000000000000000000000000000000 B
b000 D
1E
0F
#36
05
b10001011 8
b11000001 ;
b00000000000001101110010111100100 <
0>
0?
b00000000 A
0E
#37
15
#38
05
b10011100 8
1:
b10101110 ;
b00000000110001111011010101011101 <
1H
#39
b10101110 -
b00000000110001111011010101011101 1
b00 2
b001 4
15
b001 D
#40
05
b01000001 8
b11000110 ;
b00000000101000100101010010010011 <
1>
1?
1@
b10101110 A
b00000000110001111011010101011101 B
1F
#41
b11000110 *
b00000000101000100101010010010011 .
b01 2
b00 3
15
b11000110 A
b00000000101000100101010010010011 B
#42
05
b11100101 8
b10001110 ;
b00000000111110111001000101000001 <
#43
b10001110 +
b00000000111110111001000101000001 /
b10 2
b01 3
15
b10001110 A
b00000000111110111001000101000001 B
#44
05
b01000100 8
0:
b10010000 ;
b00000000001101001100011110011010 <
0H
#45
b10 3
b000 4
15
0@
b10111100 A
b00000000000000000000000000000000 B
b000 D
1E
0F
#46
05
b11110101 8
1:
b10010011 ;
b00000000100110111001111110111001 <
1H
#47
b10 (
b011 )
b10010011 ,
b00000000100110111001111110111001 0
b11 2
b001 4
15
09
1@
b10010011 A
b00000000100110111001111110111001 B
b011 C
b001 D
0E
1F
#48
05
b10111010 8
b10100000 ;
b00000000101111001010100110100000 <
#49
b10100000 -
b00000000101111001010100110100000 1
b00 2
b11 3
15
b10100000 A
b00000000101111001010100110100000 B
#50
05
17
b01010101 8
0:
b01111110 ;
b00000000111001100110101010000001 <
0>
0?
0@
b00000000 A
b00000000000000000000000000000000 B
0F
1G
0H
#51
b01010101 $
b10 '
b100 )
15
19
b100 C
0G
#52
05
07
b01101110 8
1:
b10110000 ;
b00000000010000110101001111110011 <
1>
1?
1@
b10100000 A
b00000000101111001010100110100000 B
1F
1H
#53
b10110000 *
b00000000010000110101001111110011 .
b01 2
b00 3
15
b10110000 A
b00000000010000110101001111110011 B
#54
05
b10011001 8
0:
b10101111 ;
b00000000100100101101100011010111 <
0H
#55
b01 3
b000 4
15
0@
b00100010 A
b00000000000000000000000000000000 B
b000 D
1E
0F
#56
05
b11000111 8
b11111000 ;
b00000000100110011101110100111010 <
#57
b11 (
b011 )
15
09
b01111111 A
b011 C
#58
05
17
b01001011 8
b01011111 ;
b00000000001001000111010001110011 <
1G
#59
b01001011 %
b11 '
b00 (
15
b01010111 A
#60
05
b00111000 8
1:
b01101101 ;
b00000000101100101101101000100000 <
1H
#61
b00111000 &
b00 '
b01 (
b01101101 +
b00000000101100101101101000100000 /
b10 2
b001 4
15
1@
b01101101 A
b00000000101100101101101000100000 B
b001 D
0E
1F
#62
05
b00110110 8
0:
b11111011 ;
b00000000000011101011100110010000 <
0H
#63
b00110110 #
b01 '
b100 )
b10 3
b000 4
15
19
0@
b01010101 A
b00000000000000000000000000000000 B
b100 C
b000 D
1E
0F
0G
#64
05
07
b10100111 8
b00101000 ;
b00000000110101010101100001000111 <
#65
b10 (
b011 )
15
09
b01001011 A
b011 C
#66
05
17
b10110110 8
b01100111 ;
b00000000011101111001001000100101 <
1G
#67
b10110110 $
b10 '
b11 (
15
b00111000 A
#68
05
b01001001 8
1:
b10101100 ;
b00000000000100011000001101101010 <
1H
#69
b01001001 %
b11 '
b00 (
b10101100 ,
b00000000000100011000001101101010 0
b11 2
b001 4
15
1@
b10101100 A
b00000000000100011000001101101010 B
b001 D
0E
1F
#70
05
07
b11110001 8
0:
b11001100 ;
b00000000100111111110111101011010 <
0G
0H
#71
b11 3
b000 4
15
0@
b00110110 A
b00000000000000000000000000000000 B
b000 D
1E
0F
#72
05
b10111111 8
b00011001 ;
b00000000010011010011001011100000 <
#73
b01 (
b010 )
15
b10110110 A
b010 C
#74
05
b00110011 8
b01001011 ;
b00000000111000111000111011100011 <
#75
b10 (
b001 )
15
b01001001 A
b001 C
#76
05
17
b00000001 8
1:
b01100110 ;
b00000000011110011010101110001001 <
1G
1H
#77
b00000001 &
b00 '
b11 (
b01100110 -
b00000000011110011010101110001001 1
b00 2
b001 4
15
1@
b01100110 A
b00000000011110011010101110001001 B
b001 D
0E
1F
#78
05
07
b01101100 8
0:
b00110100 ;
b00000000110110000110001110111111 <
0G
0H
#79
b00 3
b000 4
15
0@
b00000001 A
b00000000000000000000000000000000 B
b000 D
1E
0F
#80
05
b10001100 8
1:
b00100100 ;
b00000000011010110000101010111101 <
0>
0?
b00000000 A
0E
1H
#81
b00100100 *
b00000000011010110000101010111101 .
b01 2
b001 4
15
b001 D
#82
05
17
b00100011 8
b00010111 ;
b00000000010001100110000011011100 <
1G
#83
b00100011 #
b01 '
b010 )
b00010111 +
b00000000010001100110000011011100 /
b10 2
b010 4
15
b010 C
b010 D
#84
05
07
b01101100 8
b11111101 ;
b00000000010011101010001010111101 <
1>
1?
1@
b00100100 A
b00000000011010110000101010111101 B
1F
0G
#85
b11111101 ,
b00000000010011101010001010111101 0
b11 2
b01 3
15
b00010111 A
b00000000010001100110000011011100 B
#86
05
b10000000 8
0:
b10000111 ;
b00000000000010010100100001100000 <
0H
#87
b10 3
b001 4
15
b11111101 A
b00000000010011101010001010111101 B
b001 D
#88
05
b00011101 8
b10000110 ;
b00000000001111111110000111000101 <
0>
0?
0@
b00000000 A
b00000000000000000000000000000000 B
0F
#89
15
#90
05
17
b00100011 8
1:
b10011110 ;
b00000000111101000110110101011001 <
1G
1H
#91
b00100011 $
b10 '
b011 )
b10011110 -
b00000000111101000110110101011001 1
b00 2
b010 4
15
b011 C
b010 D
#92
05
b10001110 8
0:
b11000100 ;
b00000000111011001001101101101110 <
1>
1?
1@
b11111101 A
b00000000010011101010001010111101 B
1F
0H
#93
b10001110 %
b11 '
b100 )
b11 3
b001 4
15
19
b10011110 A
b00000000111101000110110101011001 B
b100 C
b001 D
0G
#94
05
07
b00111111 8
b10111110 ;
b00000000101001111011110001011111 <
#95
b00 3
b000 4
15
0@
b00000001 A
b00000000000000000000000000000000 B
b000 D
1E
0F
#96
05
b00011010 8
1:
b10000000 ;
b00000000111011011001001100001010 <
1H
#97
b00 (
b011 )
b10000000 *
b00000000111011011001001100001010 .
b01 2
b001 4
15
09
1@
b10000000 A
b00000000111011011001001100001010 B
b011 C
b001 D
0E
1F
#98
05
b00110010 8
b10110000 ;
b00000000110000111101100101111000 <
#99
b10110000 +
b00000000110000111101100101111000 /
b10 2
b01 3
15
b10110000 A
b00000000110000111101100101111000 B
#100
05
17
b10010010 8
b11011110 ;
b00000000110001001101111101111100 <
1G
#101
b10010010 &
b00 '
b100 )
b11011110 ,
b00000000110001001101111101111100 0
b11 2
b10 3
15
19
b11011110 A
b00000000110001001101111101111100 B
b100 C
0G
#102
05
07
b00111101 8
0:
b11000011 ;
b00000000000001110000010000110001 <
0H
#103
b11 3
b000 4
15
0@
b00100011 A
b00000000000000000000000000000000 B
b000 D
1E
0F
#104
05
b10010001 8
1:
b11010000 ;
b00000000001001011110111011010011 <
0>
0?
b00000000 A
0E
1H
#105
b11010000 -
b00000000001001011110111011010011 1
b00 2
b001 4
15
b001 D
#106
05
b01000100 8
b00000000 ;
b00000000100001111001111100110110 <
#107
b00000000 *
b00000000100001111001111100110110 .
b01 2
b010 4
15
b010 D
#108
05
b00110010 8
b11100101 ;
b00000000110110111100011001000101 <
1>
1?
1@
b11010000 A
b00000000001001011110111011010011 B
1F
#109
b11100101 +
b00000000110110111100011001000101 /
b10 2
b00 3
15
b00000000 A
b00000000100001111001111100110110 B
#110
05
b01011000 8
0:
b11100010 ;
b00000000001001001010111010010101 <
0H
#111
b01 3
b001 4
15
b11100101 A
b00000000110110111100011001000101 B
b001 D
#112
05
b01010001 8
1:
b01010110 ;
b00000000101110010110000001110110 <
1H
#113
b01010110 ,
b00000000101110010110000001110110 0
b11 2
b10 3
15
b01010110 A
b00000000101110010110000001110110 B
#114
05
b11000110 8
0:
b11000000 ;
b00000000011000010000101110011011 <
0>
0?
0@
b00000000 A
b00000000000000000000000000000000 B
0F
0H
#115
15
#116
05
b11000010 8
b01101000 ;
b00000000010100101000111011110001 <
1>
1?
1@
b01010110 A
b00000000101110010110000001110110 B
1F
#117
b11 3
b000 4
15
0@
b00100011 A
b00000000000000000000000000000000 B
b000 D
1E
0F
#118
05
b11001100 8
b01110110 ;
b00000000001000010100100010001000 <
#119
b01 (
b011 )
15
09
b011 C
#120
05
b10011110 8
b00100000 ;
b00000000000100110001100101111001 <
#121
b10 (
b010 )
15
b10001110 A
b010 C
#122
05
b00010101 8
b11110011 ;
b00000000100110011001001101100001 <
#123
b11 (
b001 )
15
b10010010 A
b001 C
#124
05
1:
b01110000 ;
b00000000101111100100101010000111 <
1H
#125
b00 (
b000 )
b01110000 -
b00000000101111100100101010000111 1
b00 2
b001 4
15
1@
b01110000 A
b00000000101111100100101010000111 B
b000 C
b001 D
0E
1F
#126
05
17
b11001100 8
0:
b11010100 ;
b00000000010000110100100010110010 <
1G
0H
#127
b11001100 #
b01 '
b001 )
b00 3
b000 4
15
0@
b11001100 A
b00000000000000000000000000000000 B
b001 C
b000 D
1E
0F
#128
05
b00001001 8
b00101100 ;
b00000000100100000101100001011111 <
#129
b00001001 $
b10 '
b01 (
15
b00001001 A
#130
05
b11001111 8
1:
b10111100 ;
b00000000000101000110000001100101 <
0>
0?
b00000000 A
0E
1H
#131
b11001111 %
b11 '
b010 )
b10111100 *
b00000000000101000110000001100101 .
b01 2
b001 4
15
b010 C
b001 D
#132
05
07
b11011000 8
b01000111 ;
b00000000111110110011101100011101 <
0G
#133
b01000111 +
b00000000111110110011101100011101 /
b10 2
b010 4
15
b010 D
#134
05
17
b00100000 8
b01101100 ;
b00000000010111101101001001010100 <
1>
1?
1@
b10111100 A
b00000000000101000110000001100101 B
1F
1G
#135
b00100000 &
b00 '
b011 )
b01101100 ,
b00000000010111101101001001010100 0
b11 2
b01 3
15
b01000111 A
b00000000111110110011101100011101 B
b011 C
#136
05
b11101100 8
0:
b11100111 ;
b00000000100000101000111101011000 <
0>
0?
0@
b00000000 A
b00000000000000000000000000000000 B
0F
0H
#137
b11101100 #
b01 '
b100 )
15
19
b100 C
0G
#138
05
07
b00000010 8
b11111101 ;
b00000000001101001001101001100111 <
1>
1?
1@
b01000111 A
b00000000111110110011101100011101 B
1F
#139
b10 3
b001 4
15
b01101100 A
b00000000010111101101001001010100 B
b001 D
#140
05
b01011111 8
1:
b10001110 ;
b00000000011111111001101011011010 <
1H
#141
b10001110 -
b00000000011111111001101011011010 1
b00 2
b11 3
15
b10001110 A
b00000000011111111001101011011010 B
#142
05
b00111001 8
b01011000 ;
b00000000111000011010111011111000 <
#143
b01011000 *
b00000000111000011010111011111000 .
b01 2
b00 3
15
b01011000 A
b00000000111000011010111011111000 B
#144
05
b00011011 8
0:
b11110100 ;
b00000000000110000010010011000000 <
0H
#145
b01 3
b000 4
15
0@
b00001001 A
b00000000000000000000000000000000 B
b000 D
1E
0F
#146
05
b10101110 8
b01101010 ;
b00000000101001110111001011000100 <
#147
b10 (
b011 )
15
09
b11001111 A
b011 C
#148
05
b01110111 8
1:
b00000100 ;
b00000000011111001100110100000100 <
1H
#149
b11 (
b010 )
b00000100 +
b00000000011111001100110100000100 /
b10 2
b001 4
15
1@
b00000100 A
b00000000011111001100110100000100 B
b010 C
b001 D
0E
1F
#150
05
17
b01001000 8
b01000010 ;
b00000000001011101011011110100100 <
1G
#151
b01001000 $
b10 '
b011 )
b01000010 ,
b00000000001011101011011110100100 0
b11 2
b10 3
15
b01000010 A
b00000000001011101011011110100100 B
b011 C
#152
05
b01111110 8
0:
b10110111 ;
b00000000001101011011000010111001 <
0H
#153
b01111110 %
b11 '
b100 )
b11 3
b000 4
15
19
0@
b00100000 A
b00000000000000000000000000000000 B
b100 C
b000 D
1E
0F
0G
#154
05
07
b10100001 8
b10000010 ;
b00000000101101111100110101110101 <
#155
b00 (
b011 )
15
09
b11101100 A
b011 C
#156
05
b10110100 8
b10100011 ;
b00000000011000011011101111110111 <
0>
0?
b00000000 A
0E
#157
15
#158
05
b00110100 8
1:
b00110011 ;
b00000000011101110000001010001100 <
1>
1?
b11101100 A
1E
1H
#159
b01 (
b010 )
b00110011 -
b00000000011101110000001010001100 1
b00 2
b001 4
15
1@
b00110011 A
b00000000011101110000001010001100 B
b010 C
b001 D
0E
1F
#160
05
17
b01100001 8
b00011100 ;
b00000000111101011100000110100011 <
1G
#161
b01100001 &
b00 '
b011 )
b00011100 *
b00000000111101011100000110100011 .
b01 2
b00 3
15
b00011100 A
b00000000111101011100000110100011 B
b011 C
#162
05
07
b11101000 8
0:
b00000101 ;
b00000000000010010100101001111000 <
0G
0H
#163
b01 3
b000 4
15
0@
b01001000 A
b00000000000000000000000000000000 B
b000 D
1E
0F
#164
05
b01010011 8
b10110101 ;
b00000000100100111101011111010010 <
0>
0?
b00000000 A
0E
#165
15
#166
05
b01100011 8
b10010100 ;
b00000000100100111010111110000001 <
#167
15
#168
05
b11101000 8
1:
b00011000 ;
b00000000100111001000111001111010 <
1H
#169
b00011000 +
b00000000100111001000111001111010 /
b10 2
b001 4
15
b001 D
#170
05
17
b01111001 8
b11001000 ;
b00000000000101010000000110001011 <
1>
1?
1@
b00011000 A
b00000000100111001000111001111010 B
1F
1G
#171
b01111001 #
b01 '
b100 )
b11001000 ,
b00000000000101010000000110001011 0
b11 2
b10 3
15
19
b11001000 A
b00000000000101010000000110001011 B
b100 C
0G
#172
05
07
b10110110 8
0:
b00001111 ;
b00000000001011000111100010001010 <
0H
#173
b11 3
b000 4
15
0@
b01001000 A
b00000000000000000000000000000000 B
b000 D
1E
0F
#174
05
b00011001 8
1:
b10010010 ;
b00000000100111000100110111000000 <
1H
#175
b10 (
b011 )
b10010010 -
b00000000100111000100110111000000 1
b00 2
b001 4
15
09
1@
b10010010 A
b00000000100111000100110111000000 B
b011 C
b001 D
0E
1F
#176
05
17
b10011011 8
b00010101 ;
b00000000010010110110100110000001 <
1G
#177
b10011011 $
b10 '
b100 )
b00010101 *
b00000000010010110110100110000001 .
b01 2
b00 3
15
19
b00010101 A
b00000000010010110110100110000001 B
b100 C
0G
#178
05
07
b01100111 8
b00010100 ;
b00000000101000101111000110101100 <
#179
b00010100 +
b00000000101000101111000110101100 /
b10 2
b01 3
15
b00010100 A
b00000000101000101111000110101100 B
#180
05
b11011001 8
b00110110 ;
b00000000000110101110011001111101 <
0>
0?
0@
b00000000 A
b00000000000000000000000000000000 B
0F
#181
b00110110 ,
b00000000000110101110011001111101 0
b11 2
b010 4
15
b010 D
#182
05
b11111000 8
b10001011 ;
b00000000100110111111111110000010 <
#183
b10001011 -
b00000000100110111111111110000010 1
b00 2
b011 4
15
b011 D
#184
05
b10010011 8
0:
b01101111 ;
b00000000100010101000100100111011 <
1>
1?
1@
b00010100 A
b00000000101000101111000110101100 B
1F
0H
#185
b10 3
b010 4
15
b00110110 A
b00000000000110101110011001111101 B
b010 D
#186
05
b01011100 8
1:
b10010100 ;
b00000000001010100010011001100000 <
0>
0?
0@
b00000000 A
b00000000000000000000000000000000 B
0F
1H
#187
b10010100 *
b00000000001010100010011001100000 .
b01 2
b011 4
15
b011 D
#188
05
b01010010 8
0:
b01011111 ;
b00000000010101101100101101110110 <
1>
1?
1@
b00110110 A
b00000000000110101110011001111101 B
1F
0H
#189
b11 3
b010 4
15
b10001011 A
b00000000100110111111111110000010 B
b010 D
#190
05
b10100110 8
b11000101 ;
b00000000110110001011111101101101 <
#191
b00 3
b001 4
15
b10010100 A
b00000000001010100010011001100000 B
b001 D
#192
05
b11101100 8
b11100101 ;
b00000000011000000000100011100001 <
#193
b01 3
b000 4
15
0@
b01111110 A
b00000000000000000000000000000000 B
b000 D
1E
0F
#194
05
b00110101 8
1:
b11011001 ;
b00000000011101101000001011001001 <
1H
#195
b11 (
b011 )
b11011001 +
b00000000011101101000001011001001 /
b10 2
b001 4
15
09
1@
b11011001 A
b00000000011101101000001011001001 B
b011 C
b001 D
0E
1F
#196
05
17
b01100010 8
0:
b11111100 ;
b00000000001011101011000100011110 <
1G
0H
#197
b01100010 %
b11 '
b100 )
b10 3
b000 4
15
19
0@
b01100001 A
b00000000000000000000000000000000 B
b100 C
b000 D
1E
0F
0G
#198
05
07
b10100111 8
1:
b10110100 ;
b00000000101100010110011111111111 <
1H
#199
b00 (
b011 )
b10110100 ,
b00000000101100010110011111111111 0
b11 2
b001 4
15
09
1@
b10110100 A
b00000000101100010110011111111111 B
b011 C
b001 D
0E
1F
#200
05
17
b10111011 8
0:
b10000110 ;
b00000000010101001101011000000001 <
0>
0?
0@
b00000000 A
b00000000000000000000000000000000 B
0F
1G
0H
#201
b10111011 &
b00 '
b100 )
15
19
b100 C
0G
#202
05
07
b00110111 8
b10101110 ;
b00000000101000011011010011001100 <
#203
15
#204
05
b11010110 8
b10011110 ;
b00000000110011011001001010101001 <
1>
1?
1@
b10110100 A
b00000000101100010110011111111111 B
1F
#205
b11 3
b000 4
15
0@
b01111001 A
b00000000000000000000000000000000 B
b000 D
1E
0F
#206
05
b00101101 8
b00001010 ;
b00000000101110111000001101011111 <
0>
0?
b00000000 A
0E
#207
15
#208
05
b00011011 8
1:
b01000100 ;
b00000000010110111000100000001001 <
1H
#209
b01000100 -
b00000000010110111000100000001001 1
b00 2
b001 4
15
b001 D
#210
05
b10010010 8
b10010101 ;
b00000000010100011010111101100100 <
#211
b10010101 *
b00000000010100011010111101100100 .
b01 2
b010 4
15
b010 D
#212
05
b10001011 8
b00000000 ;
b00000000111110011010110110011001 <
1>
1?
1@
b01000100 A
b00000000010110111000100000001001 B
1F
#213
b00000000 +
b00000000111110011010110110011001 /
b10 2
b00 3
15
b10010101 A
b00000000010100011010111101100100 B
#214
05
b01001100 8
0:
b01100101 ;
b00000000100111100000001101110110 <
0H
#215
b01 3
b001 4
15
b00000000 A
b00000000111110011010110110011001 B
b001 D
#216
05
b11010000 8
b10001010 ;
b00000000100001000010001101010010 <
#217
b10 3
b000 4
15
0@
b01111001 A
b00000000000000000000000000000000 B
b000 D
1E
0F
#218
05
b10010100 8
b10111011 ;
b00000000110110000010111110110010 <
0>
0?
b00000000 A
0E
#219
15
#220
05
b10010011 8
b01101100 ;
b00000000011101011100011110110000 <
1>
1?
b01111001 A
1E
#221
b01 (
b011 )
15
09
b10011011 A
b011 C
#222
05
b01010000 8
1:
b01100011 ;
b00000000100111101010101011100000 <
1H
#223
b10 (
b010 )
b01100011 ,
b00000000100111101010101011100000 0
b11 2
b001 4
15
1@
b01100011 A
b00000000100111101010101011100000 B
b010 C
b001 D
0E
1F
#224
05
b11010101 8
b11010010 ;
b00000000010011011111010110101010 <
0>
0?
0@
b00000000 A
b00000000000000000000000000000000 B
0F
#225
b11010010 -
b00000000010011011111010110101010 1
b00 2
b010 4
15
b010 D
#226
05
17
b11101011 8
0:
b01010100 ;
b00000000111010010010111010100110 <
1>
1?
1@
b01100011 A
b00000000100111101010101011100000 B
1F
1G
0H
#227
b11101011 #
b01 '
b011 )
b11 3
b001 4
15
b11010010 A
b00000000010011011111010110101010 B
b011 C
b001 D
#228
05
07
b10001010 8
1:
b11101100 ;
b00000000000000110001000101101111 <
0>
0?
0@
b00000000 A
b00000000000000000000000000000000 B
0F
0G
1H
#229
b11101100 *
b00000000000000110001000101101111 .
b01 2
b010 4
15
b010 D
#230
05
b01010000 8
b11111101 ;
b00000000110101111011011001010011 <
1>
1?
1@
b11010010 A
b00000000010011011111010110101010 B
1F
#231
b11111101 +
b00000000110101111011011001010011 /
b10 2
b00 3
15
b11101100 A
b00000000000000110001000101101111 B
#232
05
b01101011 8
b11101000 ;
b00000000101010101111011011011100 <
#233
b11101000 ,
b00000000101010101111011011011100 0
b11 2
b01 3
15
b11111101 A
b00000000110101111011011001010011 B
#234
05
b00011101 8
b01101110 ;
b00000000011011111100001001101111 <
#235
b01101110 -
b00000000011011111100001001101111 1
b00 2
b10 3
15
b11101000 A
b00000000101010101111011011011100 B
#236
05
b01101101 8
0:
b10101110 ;
b00000000101110111111110010010101 <
0H
#237
b11 3
b001 4
15
b01101110 A
b00000000011011111100001001101111 B
b001 D
