sv_common_ips/13_cpu_backend_issue_dispatch/top.sv
// top.sv - Lesson 13
//
// Use-case:
//  - CPU backend issue/dispatch where multiple instruction slots compete
//    for limited execution resources (ALU and MUL pipelines).

module top (
    input  logic clk,
    input  logic rst_n,

    input  logic       s0_valid,
    input  logic       s0_is_mul,
    input  logic [3:0] s0_tag,

    input  logic       s1_valid,
    input  logic       s1_is_mul,
    input  logic [3:0] s1_tag,

    input  logic       s2_valid,
    input  logic       s2_is_mul,
    input  logic [3:0] s2_tag,

    input  logic       alu_ready,
    input  logic       mul_ready,

    output logic       alu_issue_valid,
    output logic [3:0] alu_issue_tag,
    output logic [1:0] alu_issue_slot,

    output logic       mul_issue_valid,
    output logic [3:0] mul_issue_tag,
    output logic [1:0] mul_issue_slot,

    output logic [2:0] alu_grant,
    output logic [2:0] mul_grant,

    output logic [1:0] alu_rr_ptr_dbg,
    output logic [1:0] mul_rr_ptr_dbg
);
    logic [1:0] alu_rr_ptr;
    logic [1:0] mul_rr_ptr;

    logic [2:0] valid_alu;
    logic [2:0] valid_mul;

    function automatic logic [2:0] rr_pick3(
        input logic [2:0] valid,
        input logic [1:0] ptr
    );
        logic [2:0] g;
        g = 3'b000;

        unique case (ptr)
            2'd0: begin
                if (valid[0])      g = 3'b001;
                else if (valid[1]) g = 3'b010;
                else if (valid[2]) g = 3'b100;
            end
            2'd1: begin
                if (valid[1])      g = 3'b010;
                else if (valid[2]) g = 3'b100;
                else if (valid[0]) g = 3'b001;
            end
            default: begin
                if (valid[2])      g = 3'b100;
                else if (valid[0]) g = 3'b001;
                else if (valid[1]) g = 3'b010;
            end
        endcase

        return g;
    endfunction

    assign valid_alu[0] = s0_valid && !s0_is_mul;
    assign valid_alu[1] = s1_valid && !s1_is_mul;
    assign valid_alu[2] = s2_valid && !s2_is_mul;

    assign valid_mul[0] = s0_valid && s0_is_mul;
    assign valid_mul[1] = s1_valid && s1_is_mul;
    assign valid_mul[2] = s2_valid && s2_is_mul;

    always_comb begin
        if (alu_ready) alu_grant = rr_pick3(valid_alu, alu_rr_ptr);
        else           alu_grant = 3'b000;
    end

    always_comb begin
        if (mul_ready) mul_grant = rr_pick3(valid_mul, mul_rr_ptr);
        else           mul_grant = 3'b000;
    end

    assign alu_issue_valid = |alu_grant;
    assign mul_issue_valid = |mul_grant;

    always_comb begin
        alu_issue_tag = 4'h0;
        alu_issue_slot = 2'd0;

        if (alu_grant[0]) begin
            alu_issue_tag = s0_tag;
            alu_issue_slot = 2'd0;
        end else if (alu_grant[1]) begin
            alu_issue_tag = s1_tag;
            alu_issue_slot = 2'd1;
        end else if (alu_grant[2]) begin
            alu_issue_tag = s2_tag;
            alu_issue_slot = 2'd2;
        end
    end

    always_comb begin
        mul_issue_tag = 4'h0;
        mul_issue_slot = 2'd0;

        if (mul_grant[0]) begin
            mul_issue_tag = s0_tag;
            mul_issue_slot = 2'd0;
        end else if (mul_grant[1]) begin
            mul_issue_tag = s1_tag;
            mul_issue_slot = 2'd1;
        end else if (mul_grant[2]) begin
            mul_issue_tag = s2_tag;
            mul_issue_slot = 2'd2;
        end
    end

    assign alu_rr_ptr_dbg = alu_rr_ptr;
    assign mul_rr_ptr_dbg = mul_rr_ptr;

    always_ff @(posedge clk) begin
        if (!rst_n) begin
            alu_rr_ptr <= 2'd0;
            mul_rr_ptr <= 2'd0;
        end else begin
            if (alu_grant[0]) alu_rr_ptr <= 2'd1;
            if (alu_grant[1]) alu_rr_ptr <= 2'd2;
            if (alu_grant[2]) alu_rr_ptr <= 2'd0;

            if (mul_grant[0]) mul_rr_ptr <= 2'd1;
            if (mul_grant[1]) mul_rr_ptr <= 2'd2;
            if (mul_grant[2]) mul_rr_ptr <= 2'd0;
        end
    end

    always_ff @(posedge clk) begin
        if (rst_n) begin
            assert ($onehot0(alu_grant))
                else $fatal(1, "CPU issue violation: ALU grant must be one-hot or zero");

            assert ($onehot0(mul_grant))
                else $fatal(1, "CPU issue violation: MUL grant must be one-hot or zero");

            assert ((alu_grant & mul_grant) == 3'b000)
                else $fatal(1, "CPU issue violation: same slot granted to ALU and MUL");
        end
    end

endmodule

sv_common_ips/13_cpu_backend_issue_dispatch/waveform.vcd
$version Generated by VerilatedVcd $end
$timescale 1ps $end
 $scope module TOP $end
  $var wire 1 # clk $end
  $var wire 1 $ rst_n $end
  $var wire 1 % s0_valid $end
  $var wire 1 & s0_is_mul $end
  $var wire 4 ' s0_tag [3:0] $end
  $var wire 1 ( s1_valid $end
  $var wire 1 ) s1_is_mul $end
  $var wire 4 * s1_tag [3:0] $end
  $var wire 1 + s2_valid $end
  $var wire 1 , s2_is_mul $end
  $var wire 4 - s2_tag [3:0] $end
  $var wire 1 . alu_ready $end
  $var wire 1 / mul_ready $end
  $var wire 1 0 alu_issue_valid $end
  $var wire 4 1 alu_issue_tag [3:0] $end
  $var wire 2 2 alu_issue_slot [1:0] $end
  $var wire 1 3 mul_issue_valid $end
  $var wire 4 4 mul_issue_tag [3:0] $end
  $var wire 2 5 mul_issue_slot [1:0] $end
  $var wire 3 6 alu_grant [2:0] $end
  $var wire 3 7 mul_grant [2:0] $end
  $var wire 2 8 alu_rr_ptr_dbg [1:0] $end
  $var wire 2 9 mul_rr_ptr_dbg [1:0] $end
  $scope module top $end
   $var wire 1 # clk $end
   $var wire 1 $ rst_n $end
   $var wire 1 % s0_valid $end
   $var wire 1 & s0_is_mul $end
   $var wire 4 ' s0_tag [3:0] $end
   $var wire 1 ( s1_valid $end
   $var wire 1 ) s1_is_mul $end
   $var wire 4 * s1_tag [3:0] $end
   $var wire 1 + s2_valid $end
   $var wire 1 , s2_is_mul $end
   $var wire 4 - s2_tag [3:0] $end
   $var wire 1 . alu_ready $end
   $var wire 1 / mul_ready $end
   $var wire 1 0 alu_issue_valid $end
   $var wire 4 1 alu_issue_tag [3:0] $end
   $var wire 2 2 alu_issue_slot [1:0] $end
   $var wire 1 3 mul_issue_valid $end
   $var wire 4 4 mul_issue_tag [3:0] $end
   $var wire 2 5 mul_issue_slot [1:0] $end
   $var wire 3 6 alu_grant [2:0] $end
   $var wire 3 7 mul_grant [2:0] $end
   $var wire 2 8 alu_rr_ptr_dbg [1:0] $end
   $var wire 2 9 mul_rr_ptr_dbg [1:0] $end
   $var wire 2 : alu_rr_ptr [1:0] $end
   $var wire 2 ; mul_rr_ptr [1:0] $end
   $var wire 3 < valid_alu [2:0] $end
   $var wire 3 = valid_mul [2:0] $end
  $upscope $end
 $upscope $end
$enddefinitions $end


#0
0#
0$
0%
0&
b0000 '
0(
0)
b0000 *
0+
0,
b0000 -
0.
0/
00
b0000 1
b00 2
03
b0000 4
b00 5
b000 6
b000 7
b00 8
b00 9
b00 :
b00 ;
b000 <
b000 =
#1
1#
#2
0#
#3
1#
#4
0#
#5
1#
#6
0#
#7
1#
#8
0#
#9
1#
#10
0#
1$
1%
1&
b1110 '
1(
b1010 *
1+
b0011 -
1/
13
b1110 4
b001 7
b110 <
b001 =
#11
1#
b01 9
b01 ;
#12
0#
b1000 '
1)
b0100 *
b0000 -
1.
10
b10 2
b0100 4
b01 5
b100 6
b010 7
b100 <
b011 =
#13
1#
b1000 4
b00 5
b001 7
b10 9
b10 ;
#14
0#
0&
b1011 '
0(
b1011 *
b0111 -
0.
00
b00 2
03
b0000 4
b000 6
b000 7
b101 <
b000 =
#15
1#
#16
0#
0%
b0010 '
b0110 *
1,
b0000 -
1.
13
b10 5
b100 7
b000 <
b100 =
#17
1#
b00 9
b00 ;
#18
0#
b1101 '
1(
b0100 *
0+
b0110 -
0/
03
b00 5
b000 7
b010 =
#19
1#
#20
0#
1%
b0101 '
0(
b0011 *
1+
b1100 -
1/
10
b0101 1
13
b1100 4
b10 5
b001 6
b100 7
b001 <
b100 =
#21
1#
b01 8
b01 :
#22
0#
1&
b0000 '
1(
0)
b1111 *
0,
b0001 -
b1111 1
b01 2
b0000 4
b00 5
b010 6
b001 7
b110 <
b001 =
#23
1#
b0001 1
b10 2
b100 6
b10 8
b01 9
b10 :
b01 ;
#24
0#
b1011 '
0(
b1000 *
0+
1,
b1001 -
00
b0000 1
b00 2
b1011 4
b000 6
b000 <
#25
1#
#26
0#
0&
b1101 '
1(
b0111 *
1+
0,
b1111 -
0.
03
b0000 4
b000 7
b111 <
b000 =
#27
1#
#28
0#
1&
b0010 '
b0011 *
0+
b0101 -
1.
10
b0011 1
b01 2
13
b0010 4
b010 6
b001 7
b010 <
b001 =
#29
1#
#30
0#
0%
b1000 '
1)
b1000 *
1+
b0011 -
b10 2
b1000 4
b01 5
b100 6
b010 7
b100 <
b010 =
#31
1#
b00 8
b10 9
b00 :
b10 ;
#32
0#
b0011 '
0(
0)
b0100 *
1,
b1101 -
00
b0000 1
b00 2
b1101 4
b10 5
b000 6
b100 7
b000 <
b100 =
#33
1#
b00 9
b00 ;
#34
0#
1%
1(
1)
b0111 *
0,
b0101 -
10
b0101 1
b10 2
b0011 4
b00 5
b100 6
b001 7
b100 <
b011 =
#35
1#
b0111 4
b01 5
b010 7
b01 9
b01 ;
#36
0#
0%
0(
b1111 *
0+
1,
b1111 -
00
b0000 1
b00 2
03
b0000 4
b00 5
b000 6
b000 7
b000 <
b000 =
#37
1#
#38
0#
b1011 '
1(
0)
b1010 *
b0110 -
10
b1010 1
b01 2
b010 6
b010 <
#39
1#
b10 8
b10 :
#40
0#
1%
0&
b1110 '
0(
b0011 *
1+
b0101 -
0/
b1110 1
b00 2
b001 6
b001 <
b100 =
#41
1#
b01 8
b01 :
#42
0#
0%
1&
b0011 '
1(
1)
b1110 *
b0011 -
1/
00
b0000 1
13
b1110 4
b01 5
b000 6
b010 7
b000 <
b110 =
#43
1#
b0011 4
b10 5
b100 7
b10 9
b10 ;
#44
0#
1%
b0110 '
0(
b0100 *
0+
0,
b1110 -
b0110 4
b00 5
b001 7
b001 =
#45
1#
b01 9
b01 ;
#46
0#
0&
b1110 '
1(
0)
b1101 *
b1000 -
0.
0/
03
b0000 4
b000 7
b011 <
b000 =
#47
1#
#48
0#
0%
1&
b0110 *
b1001 -
1.
1/
10
b0110 1
b01 2
b010 6
b010 <
#49
1#
b10 8
b10 :
#50
0#
1%
b1101 '
1)
b0001 *
1+
b1000 -
b1000 1
b10 2
13
b0001 4
b01 5
b100 6
b010 7
b100 <
b011 =
#51
1#
b1101 4
b00 5
b001 7
b00 8
b10 9
b00 :
b10 ;
#52
0#
0&
b1110 '
b1011 *
1,
b1001 -
b1110 1
b00 2
b1001 4
b10 5
b001 6
b100 7
b001 <
b110 =
#53
1#
b1011 4
b01 5
b010 7
b01 8
b00 9
b01 :
b00 ;
#54
0#
1&
b0111 '
0,
b1111 -
0/
b1111 1
b10 2
03
b0000 4
b00 5
b100 6
b000 7
b100 <
b011 =
#55
1#
b00 8
b00 :
#56
0#
b1101 '
b1001 *
0+
b1110 -
0.
1/
00
b0000 1
b00 2
13
b1101 4
b000 6
b001 7
b000 <
#57
1#
b1001 4
b01 5
b010 7
b01 9
b01 ;
#58
0#
0&
b0111 '
0)
b0000 *
1+
1,
b1000 -
1.
0/
10
b0111 1
03
b0000 4
b00 5
b001 6
b000 7
b011 <
b100 =
#59
1#
b0000 1
b01 2
b010 6
b01 8
b01 :
#60
0#
0%
1&
b0110 '
0(
b0011 *
0+
0,
b1101 -
0.
1/
00
b00 2
b000 6
b000 <
b000 =
#61
1#
#62
0#
1%
b1010 '
1(
1)
b1010 *
1+
b1000 -
1.
10
b1000 1
b10 2
13
b1010 4
b01 5
b100 6
b010 7
b100 <
b011 =
#63
1#
b00 5
b001 7
b00 8
b10 9
b00 :
b10 ;
#64
0#
0%
b0100 '
0)
b0101 *
b0111 -
0.
00
b0000 1
b00 2
03
b0000 4
b000 6
b000 7
b110 <
b000 =
#65
1#
#66
0#
1%
0&
b0001 '
b1010 *
0+
1,
b0100 -
1.
0/
10
b0001 1
b001 6
b011 <
#67
1#
b1010 1
b01 2
b010 6
b01 8
b01 :
#68
0#
0%
1&
b1011 '
b0010 *
1+
b0000 -
1/
b0010 1
13
b10 5
b100 7
b010 <
b100 =
#69
1#
b10 8
b00 9
b10 :
b00 ;
#70
0#
1%
b1000 '
0(
b1011 *
0+
0,
b0001 -
0.
0/
00
b0000 1
b00 2
03
b00 5
b000 6
b000 7
b000 <
b001 =
#71
1#
#72
0#
0%
b0101 '
1(
1)
b0010 *
b1110 -
1.
1/
13
b0010 4
b01 5
b010 7
b010 =
#73
1#
b10 9
b10 ;
#74
0#
0&
b0010 '
0(
0)
b1101 *
1+
1,
b1011 -
b1011 4
b10 5
b100 7
b100 =
#75
1#
b00 9
b00 ;
#76
0#
1&
1(
b0101 *
0,
b0010 -
0.
03
b0000 4
b00 5
b000 7
b110 <
b000 =
#77
1#
#78
0#
b0100 '
0(
1)
b1001 *
1,
b0101 -
1.
13
b0101 4
b10 5
b100 7
b000 <
b100 =
#79
1#
#80
0#
1%
b1110 '
1(
b0001 *
0,
b0110 -
10
b0110 1
b10 2
b1110 4
b00 5
b100 6
b001 7
b100 <
b011 =
#81
1#
b0001 4
b01 5
b010 7
b00 8
b01 9
b00 :
b01 ;
#82
0#
0%
b1011 '
b0010 *
b1011 -
0.
0/
00
b0000 1
b00 2
03
b0000 4
b00 5
b000 6
b000 7
b010 =
#83
1#
#84
0#
1%
0&
b1111 '
0(
b0000 *
1,
b0111 -
1.
1/
10
b1111 1
13
b0111 4
b10 5
b001 6
b100 7
b001 <
b100 =
#85
1#
b01 8
b00 9
b01 :
b00 ;
#86
0#
0%
1&
b1101 '
b1111 *
b1110 -
0/
00
b0000 1
03
b0000 4
b00 5
b000 6
b000 7
b000 <
#87
1#
#88
0#
1%
1(
0)
b0000 *
b1011 -
0.
1/
13
b1101 4
b001 7
b010 <
b101 =
#89
1#
b1011 4
b10 5
b100 7
b01 9
b01 ;
#90
0#
0%
0&
b1011 '
0(
1)
b0100 *
0+
b0111 -
1.
0/
03
b0000 4
b00 5
b000 7
b000 <
b000 =
#91
1#
#92
0#
1%
b0010 '
b0010 *
0,
1/
10
b0010 1
b001 6
b001 <
#93
1#
#94
0#
b1111 '
0)
b1010 *
1,
b1100 -
b1111 1
#95
1#
#96
0#
1&
b0110 '
1(
1)
b1101 *
b0111 -
00
b0000 1
13
b1101 4
b01 5
b000 6
b010 7
b000 <
b011 =
#97
1#
b0110 4
b00 5
b001 7
b10 9
b10 ;
#98
0#
0&
b0000 '
b0011 *
0,
b0110 -
10
b0011 4
b01 5
b001 6
b010 7
b001 <
b010 =
#99
1#
#100
0#
1&
b1101 '
0)
b1011 *
b1010 -
b1011 1
b01 2
b1101 4
b00 5
b010 6
b001 7
b010 <
b001 =
#101
1#
b10 8
b01 9
b10 :
b01 ;
#102
0#
0%
b1010 '
1)
b0000 *
1+
b1000 -
b1000 1
b10 2
b0000 4
b01 5
b100 6
b010 7
b100 <
b010 =
#103
1#
b00 8
b10 9
b00 :
b10 ;
#104
0#
1%
0&
b1011 '
b0101 *
1,
b1010 -
0.
00
b0000 1
b00 2
b1010 4
b10 5
b000 6
b100 7
b001 <
b110 =
#105
1#
b0101 4
b01 5
b010 7
b00 9
b00 ;
#106
0#
0%
1&
b0100 '
b1101 *
0,
b1110 -
1.
0/
10
b1110 1
b10 2
03
b0000 4
b00 5
b100 6
b000 7
b100 <
b010 =
#107
1#
#108
0#
1%
b1000 '
b1111 *
b0101 -
1/
b0101 1
13
b1000 4
b001 7
b011 =
#109
1#
b1111 4
b01 5
b010 7
b01 9
b01 ;
#110
0#
0%
b0010 '
b1101 *
0+
b1010 -
0/
00
b0000 1
b00 2
03
b0000 4
b00 5
b000 6
b000 7
b000 <
b010 =
#111
1#
#112
0#
1%
0&
b1000 '
0)
b1001 *
b0111 -
10
b1000 1
b001 6
b011 <
b000 =
#113
1#
b1001 1
b01 2
b010 6
b01 8
b01 :
#114
0#
1)
b0000 *
1,
b1111 -
0.
00
b0000 1
b00 2
b000 6
b001 <
b010 =
#115
1#
#116
0#
0%
b1111 '
0)
b0001 *
1+
b0100 -
1/
13
b0100 4
b10 5
b100 7
b010 <
b100 =
#117
1#
b00 9
b00 ;
#118
0#
1&
b1010 '
b1101 *
0+
b0000 -
1.
10
b1101 1
b01 2
03
b0000 4
b00 5
b010 6
b000 7
b000 =
#119
1#
b10 8
b10 :
#120
0#
0&
b0110 '
b0110 *
1+
b1111 -
0/
b0110 1
b100 =
#121
1#
#122
0#
1%
1&
b0011 '
b1111 *
0+
b1001 -
0.
00
b0000 1
b00 2
b000 6
b001 =
#123
1#
#124
0#
b0101 '
0(
b0001 *
1+
0,
b0001 -
b100 <
#125
1#
#126
0#
b0100 '
1(
1)
b0101 *
1,
b1000 -
1.
b000 <
b111 =
#127
1#
#128
0#
0&
b1000 '
0)
b0100 *
0+
b1110 -
0.
1/
b011 <
b000 =
#129
1#
#130
0#
0%
1&
b1101 '
1)
b0101 *
1+
b0101 -
1.
13
b0101 4
b01 5
b010 7
b000 <
b110 =
#131
1#
b10 5
b100 7
b10 9
b10 ;
#132
0#
1%
b1001 '
b1110 *
b0111 -
0/
03
b0000 4
b00 5
b000 7
b111 =
#133
1#
#134
0#
0%
b1101 '
b0010 *
0+
b0011 -
1/
13
b0010 4
b01 5
b010 7
b010 =
#135
1#
#136
0#
1%
b0110 *
1+
0,
b1001 -
0/
10
b1001 1
b10 2
03
b0000 4
b00 5
b100 6
b000 7
b100 <
b011 =
#137
1#
b00 8
b00 :
#138
0#
0%
0&
b0000 *
1,
b1100 -
00
b0000 1
b00 2
b000 6
b000 <
b110 =
#139
1#
#140
0#
b1111 '
0+
0,
b0010 -
1/
13
b01 5
b010 7
b010 =
#141
1#
#142
0#
1%
1&
b1001 '
b0110 *
b1000 -
b1001 4
b00 5
b001 7
b011 =
#143
1#
b0110 4
b01 5
b010 7
b01 9
b01 ;
#144
0#
0%
b0010 '
b0100 *
b0011 -
0/
03
b0000 4
b00 5
b000 7
b010 =
#145
1#
#146
0#
b1110 '
b1110 *
1,
b0010 -
1/
13
b1110 4
b01 5
b010 7
#147
1#
b10 9
b10 ;
#148
0#
b1010 '
0(
0)
b1101 *
1+
0,
b0100 -
10
b0100 1
b10 2
03
b0000 4
b00 5
b100 6
b000 7
b100 <
b000 =
#149
1#
#150
0#
0&
b1001 '
1(
b0100 *
1,
b0111 -
0.
00
b0000 1
b00 2
13
b0111 4
b10 5
b000 6
b100 7
b010 <
b100 =
#151
1#
b00 9
b00 ;
#152
0#
1%
1&
b0000 '
0(
b1001 *
0,
1.
10
b0111 1
b10 2
b0000 4
b00 5
b100 6
b001 7
b100 <
b001 =
#153
1#
b01 9
b01 ;
#154
0#
0&
b0001 '
1(
1)
b0001 *
b1000 -
0.
0/
00
b0000 1
b00 2
03
b000 6
b000 7
b101 <
b010 =
#155
1#
#156
0#
0%
b1001 '
0)
b0101 *
1.
1/
10
b0101 1
b01 2
b010 6
b110 <
b000 =
#157
1#
b1000 1
b10 2
b100 6
b10 8
b10 :
#158
0#
1&
b0101 '
b1010 *
0+
1,
0/
b1010 1
b01 2
b010 6
b010 <
#159
1#
#160
0#
1%
0&
b0011 '
b0111 *
1+
0,
b1011 -
b1011 1
b10 2
b100 6
b111 <
#161
1#
b0011 1
b00 2
b001 6
b00 8
b00 :
#162
0#
0%
1&
b0100 '
1)
b1000 *
b1010 -
1/
b1010 1
b10 2
13
b1000 4
b01 5
b100 6
b010 7
b100 <
b010 =
#163
1#
b10 9
b10 ;
#164
0#
1%
0&
b1001 '
0(
0)
b1101 *
0+
1,
b0001 -
0/
b1001 1
b00 2
03
b0000 4
b00 5
b001 6
b000 7
b001 <
b000 =
#165
1#
b01 8
b01 :
#166
0#
0%
1&
1)
b1001 *
1+
0,
b0000 -
b0000 1
b10 2
b100 6
b100 <
#167
1#
b00 8
b00 :
#168
0#
1%
b1011 '
1(
0)
b0001 *
0+
1,
b1001 -
1/
b0001 1
b01 2
13
b1011 4
b010 6
b001 7
b010 <
b001 =
#169
1#
b10 8
b01 9
b10 :
b01 ;
#170
0#
b0110 '
1)
b0110 *
0/
00
b0000 1
b00 2
03
b0000 4
b000 6
b000 7
b000 <
b011 =
#171
1#
#172
0#
0%
0&
b0001 '
b1000 *
1+
b1000 -
0.
b110 =
#173
1#
#174
0#
1%
1&
b1101 '
0(
b1011 *
0+
b0011 -
1.
b001 =
#175
1#
#176
0#
b0011 '
1(
0)
0,
b0110 -
1/
10
b1011 1
b01 2
13
b0011 4
b010 6
b001 7
b010 <
#177
1#
#178
0#
0&
b0010 '
1)
b0011 *
1+
1,
b1110 -
b0010 1
b00 2
b01 5
b001 6
b010 7
b001 <
b110 =
#179
1#
b1110 4
b10 5
b100 7
b01 8
b10 9
b01 :
b10 ;
#180
0#
0%
b0100 '
0)
b1111 *
0,
b0110 -
0.
0/
00
b0000 1
03
b0000 4
b00 5
b000 6
b000 7
b110 <
b000 =
#181
1#
#182
0#
1%
b1010 '
0+
1,
b0101 -
1.
1/
10
b1111 1
b01 2
b010 6
b011 <
#183
1#
b1010 1
b00 2
b001 6
b10 8
b10 :
#184
0#
0%
1&
b1001 '
b0011 *
1+
b0010 -
0.
00
b0000 1
13
b0010 4
b10 5
b000 6
b100 7
b010 <
b100 =
#185
1#
b00 9
b00 ;
#186
0#
1%
0&
b0101 '
0(
1)
b1011 *
0,
b0001 -
1.
10
b0001 1
b10 2
03
b0000 4
b00 5
b100 6
b000 7
b101 <
b000 =
#187
1#
b0101 1
b00 2
b001 6
b00 8
b00 :
#188
0#
1&
b1111 '
b0010 *
0+
1,
b0010 -
0/
00
b0000 1
b000 6
b000 <
b001 =
#189
1#
#190
0#
b1000 '
0)
b0000 *
1+
b0000 -
b101 =
#191
1#
#192
0#
b1001 '
1)
b0011 *
0+
0,
b0111 -
0.
b001 =
#193
1#
#194
0#
b0101 '
1(
b1001 *
b0101 -
1.
1/
13
b0101 4
b001 7
b011 =
#195
1#
b1001 4
b01 5
b010 7
b01 9
b01 ;
#196
0#
b1100 '
b0101 *
1+
1,
b0001 -
0/
03
b0000 4
b00 5
b000 7
b111 =
#197
1#
#198
0#
b1010 '
0(
b0011 *
0,
b0100 -
10
b0100 1
b10 2
b100 6
b100 <
b001 =
#199
1#
#200
0#
0%
b1001 '
b1101 *
0+
b0111 -
00
b0000 1
b00 2
b000 6
b000 <
b000 =
#201
1#
#202
0#
1%
0&
b0100 '
0)
1+
b1000 -
10
b0100 1
b001 6
b101 <
#203
1#
b1000 1
b10 2
b100 6
b01 8
b01 :
#204
0#
0%
b0000 '
1(
1)
0+
b1010 -
1/
00
b0000 1
b00 2
13
b1101 4
b01 5
b000 6
b010 7
b000 <
b010 =
#205
1#
b10 9
b10 ;
#206
0#
1%
1&
b0100 '
0)
b1000 *
b0010 -
0.
b0100 4
b00 5
b001 7
b010 <
b001 =
#207
1#
b01 9
b01 ;
#208
0#
b0000 '
1)
b0010 *
1+
b0011 -
1.
0/
10
b0011 1
b10 2
03
b0000 4
b100 6
b000 7
b100 <
b011 =
#209
1#
b00 8
b00 :
#210
0#
0%
0&
b1101 '
b1001 *
0+
1,
b1100 -
1/
00
b0000 1
b00 2
13
b1001 4
b01 5
b000 6
b010 7
b000 <
b010 =
#211
1#
b10 9
b10 ;
#212
0#
1%
b1000 '
0(
0)
b1110 *
1+
b0000 -
0/
10
b1000 1
03
b0000 4
b00 5
b001 6
b000 7
b001 <
b100 =
#213
1#
b01 8
b01 :
#214
0#
0%
1&
b0101 '
1(
b1001 *
b0111 -
1/
b1001 1
b01 2
13
b0111 4
b10 5
b010 6
b100 7
b010 <
#215
1#
b10 8
b00 9
b10 :
b00 ;
#216
0#
1%
b0110 '
b0111 *
0+
b1010 -
b0111 1
b0110 4
b00 5
b001 7
b001 =
#217
1#
b01 9
b01 ;
#218
0#
b1111 '
0(
1)
b0010 *
0,
b0001 -
00
b0000 1
b00 2
b1111 4
b000 6
b000 <
#219
1#
#220
0#
0&
b1011 '
b0011 *
1,
b0000 -
0.
0/
03
b0000 4
b000 7
b001 <
b000 =
#221
1#
#222
0#
b0101 '
1(
0)
b1011 *
1+
0,
b0101 -
1.
1/
10
b0101 1
b10 2
b100 6
b111 <
#223
1#
b00 2
b001 6
b00 8
b00 :
#224
0#
b0001 '
b0000 *
b1010 -
0/
b0001 1
#225
1#
b0000 1
b01 2
b010 6
b01 8
b01 :
#226
0#
0%
b1000 '
0(
1)
b0111 *
b0010 -
b0010 1
b10 2
b100 6
b100 <
#227
1#
b00 8
b00 :
#228
0#
1%
b0000 '
1(
b1001 *
1,
b0100 -
0.
00
b0000 1
b00 2
b000 6
b001 <
b110 =
#229
1#
#230
0#
b1010 '
0)
b0011 *
0+
0,
b0001 -
1.
1/
10
b1010 1
b001 6
b011 <
b000 =
#231
1#
b0011 1
b01 2
b010 6
b01 8
b01 :
#232
0#
1&
b1111 '
1)
b0110 *
1+
1,
b1111 -
00
b0000 1
b00 2
13
b0110 4
b01 5
b000 6
b010 7
b000 <
b111 =
#233
1#
b1111 4
b10 5
b100 7
b10 9
b10 ;
#234
0#
0%
0&
b1100 '
0(
0)
b1100 *
b1001 -
0.
b1001 4
b100 =
#235
1#
b00 9
b00 ;
#236
0#
1%
1&
b1000 '
1)
b1110 *
0,
b1100 -
1.
0/
10
b1100 1
b10 2
03
b0000 4
b00 5
b100 6
b000 7
b100 <
b001 =
#237
1#
b00 8
b00 :
#238
0#
b0100 '
0)
b1100 *
0+
b1101 -
0.
1/
00
b0000 1
b00 2
13
b0100 4
b000 6
b001 7
b000 <
#239
1#
b01 9
b01 ;
#240
0#
0&
b0011 '
1(
1)
b0000 *
1+
1,
b0101 -
1.
0/
10
b0011 1
03
b0000 4
b001 6
b000 7
b001 <
b110 =
#241
1#
b01 8
b01 :
#242
0#
b0100 '
0(
b1010 *
b0111 -
1/
b0100 1
13
b0111 4
b10 5
b100 7
b100 =
#243
1#
b00 9
b00 ;
#244
0#
1&
b0010 '
b0111 *
0,
b1101 -
0.
00
b0000 1
b0010 4
b00 5
b000 6
b001 7
b100 <
b001 =
#245
1#
b01 9
b01 ;
#246
0#
0%
0&
b1111 '
1(
b0101 *
b1110 -
1.
10
b1110 1
b10 2
b0101 4
b01 5
b100 6
b010 7
b010 =
#247
1#
b00 8
b10 9
b00 :
b10 ;
#248
0#
1%
b0001 '
0)
b0010 *
1,
b1011 -
b0001 1
b00 2
b1011 4
b10 5
b001 6
b100 7
b011 <
b100 =
#249
1#
b0010 1
b01 2
b010 6
b01 8
b00 9
b01 :
b00 ;
#250
0#
0%
b0110 '
1)
b1011 *
0+
0,
00
b0000 1
b00 2
b01 5
b000 6
b010 7
b000 <
b010 =
#251
1#
b10 9
b10 ;
#252
0#
1%
b1100 '
0(
0)
b0100 *
1+
b0011 -
0.
03
b0000 4
b00 5
b000 7
b101 <
b000 =
#253
1#
#254
0#
1&
b1110 '
1(
1)
b0001 *
b1100 -
1.
10
b1100 1
b10 2
13
b1110 4
b100 6
b001 7
b100 <
b011 =
#255
1#
b0001 4
b01 5
b010 7
b00 8
b01 9
b00 :
b01 ;
#256
0#
b0000 '
0(
b0011 *
0+
b1110 -
00
b0000 1
b00 2
b0000 4
b00 5
b000 6
b001 7
b000 <
b001 =
#257
1#
#258
0#
0&
b1011 '
1(
0)
b1111 *
1+
1,
b1001 -
0.
0/
03
b000 7
b011 <
b100 =
#259
1#
#260
0#
0%
b1000 '
b1000 *
b0001 -
1.
10
b1000 1
b01 2
b010 6
b010 <
#261
1#
b10 8
b10 :
#262
0#
b1101 '
1)
b0100 *
0,
b0100 -
1/
b0100 1
b10 2
13
b0100 4
b01 5
b100 6
b010 7
b100 <
b010 =
#263
1#
b00 8
b10 9
b00 :
b10 ;
#264
0#
1&
b0011 '
b1100 *
b1110 -
0.
00
b0000 1
b00 2
b1100 4
b000 6
#265
1#
#266
0#
1%
0&
b1011 '
0)
b1010 *
0+
b0101 -
1.
0/
10
b1011 1
03
b0000 4
b00 5
b001 6
b000 7
b011 <
b000 =
#267
1#
b1010 1
b01 2
b010 6
b01 8
b01 :
#268
0#
0%
1&
b0111 '
0(
1)
b1010 -
1/
00
b0000 1
b00 2
b000 6
b000 <
#269
1#
#270
0#
1%
b1101 '
1(
b0010 *
1+
b1101 -
10
b1101 1
b10 2
13
b1101 4
b100 6
b001 7
b100 <
b011 =
#271
1#
b0010 4
b01 5
b010 7
b00 8
b01 9
b00 :
b01 ;
#272
0#
b1100 '
0(
b0101 *
1,
b1100 -
0.
0/
00
b0000 1
b00 2
03
b0000 4
b00 5
b000 6
b000 7
b000 <
b101 =
#273
1#
#274
0#
1(
b1010 *
0,
b0000 -
1.
1/
10
b10 2
13
b1010 4
b01 5
b100 6
b010 7
b100 <
b011 =
#275
1#
b1100 4
b00 5
b001 7
b10 9
b10 ;
#276
0#
0%
0&
b0111 '
0(
0)
b0010 *
1,
b0100 -
00
b00 2
b0100 4
b10 5
b000 6
b100 7
b000 <
b100 =
#277
1#
b00 9
b00 ;
#278
0#
1%
1(
b0001 *
0,
b0101 -
10
b0111 1
03
b0000 4
b00 5
b001 6
b000 7
b111 <
b000 =
#279
1#
b0001 1
b01 2
b010 6
b01 8
b01 :
#280
0#
1&
b0001 '
0(
1)
b0110 *
0+
1,
b0110 -
0.
0/
00
b0000 1
b00 2
b000 6
b000 <
b001 =
#281
1#
#282
0#
0&
b0110 '
1(
0)
b0001 *
0,
b1010 -
1.
10
b0001 1
b01 2
b010 6
b011 <
b000 =
#283
1#
b0110 1
b00 2
b001 6
b10 8
b10 :
#284
0#
1&
b1000 '
0(
1)
b0010 *
1+
b0011 -
1/
b0011 1
b10 2
13
b1000 4
b100 6
b001 7
b100 <
b001 =
#285
1#
b00 8
b01 9
b00 :
b01 ;
