quickstart-guide-verilog/ripple-carry-adder/ripple-carry4.v
`timescale 1ns/1ps

module half_adder(
    input  wire A, B,
    output wire Sum, CarryOut
);
    assign Sum      = A ^ B;
    assign CarryOut = A & B;
endmodule

module full_adder(
    input  wire A, B, Cin,
    output wire Sum, Cout
);
    wire s1, c1, c2;

    half_adder ha0 (.A(A),  .B(B),   .Sum(s1),  .CarryOut(c1));
    half_adder ha1 (.A(s1), .B(Cin), .Sum(Sum), .CarryOut(c2));

    assign Cout = c1 | c2;
endmodule

// A[i] + B[i] = S[i] occur in parallel
// CarryOut serializes across the "ripples" of full adders
module ripple_carry4 (
    input wire [3:0] A, B,
    output wire [3:0] Sum,
    output wire CarryOut
);

    wire C1, C2, C3; // intermediate wires
    
    full_adder fa1 (.A(A[0]), .B(B[0]), .Cin(1'b0), .Sum(Sum[0]), .Cout(C1)); // hardcode carry in of 0
    full_adder fa2 (.A(A[1]), .B(B[1]), .Cin(C1), .Sum(Sum[1]), .Cout(C2));
    full_adder fa3 (.A(A[2]), .B(B[2]), .Cin(C2), .Sum(Sum[2]), .Cout(C3));
    full_adder fa4 (.A(A[3]), .B(B[3]), .Cin(C3), .Sum(Sum[3]), .Cout(CarryOut));

endmodule

quickstart-guide-verilog/ripple-carry-adder/waveform.vcd
$version Generated by VerilatedVcd $end
$timescale 1ps $end
 $scope module TOP $end
  $var wire 4 / A [3:0] $end
  $var wire 4 0 B [3:0] $end
  $var wire 4 1 Sum [3:0] $end
  $var wire 1 2 CarryOut $end
  $scope module ripple_carry4 $end
   $var wire 4 / A [3:0] $end
   $var wire 4 0 B [3:0] $end
   $var wire 4 1 Sum [3:0] $end
   $var wire 1 2 CarryOut $end
   $var wire 1 # C1 $end
   $var wire 1 $ C2 $end
   $var wire 1 % C3 $end
   $scope module fa1 $end
    $var wire 1 3 A $end
    $var wire 1 4 B $end
    $var wire 1 ? Cin $end
    $var wire 1 5 Sum $end
    $var wire 1 # Cout $end
    $var wire 1 5 s1 $end
    $var wire 1 # c1 $end
    $var wire 1 ? c2 $end
    $scope module ha0 $end
     $var wire 1 3 A $end
     $var wire 1 4 B $end
     $var wire 1 5 Sum $end
     $var wire 1 # CarryOut $end
    $upscope $end
    $scope module ha1 $end
     $var wire 1 5 A $end
     $var wire 1 ? B $end
     $var wire 1 5 Sum $end
     $var wire 1 ? CarryOut $end
    $upscope $end
   $upscope $end
   $scope module fa2 $end
    $var wire 1 6 A $end
    $var wire 1 7 B $end
    $var wire 1 # Cin $end
    $var wire 1 & Sum $end
    $var wire 1 $ Cout $end
    $var wire 1 ' s1 $end
    $var wire 1 8 c1 $end
    $var wire 1 ( c2 $end
    $scope module ha0 $end
     $var wire 1 6 A $end
     $var wire 1 7 B $end
     $var wire 1 ' Sum $end
     $var wire 1 8 CarryOut $end
    $upscope $end
    $scope module ha1 $end
     $var wire 1 ' A $end
     $var wire 1 # B $end
     $var wire 1 & Sum $end
     $var wire 1 ( CarryOut $end
    $upscope $end
   $upscope $end
   $scope module fa3 $end
    $var wire 1 9 A $end
    $var wire 1 : B $end
    $var wire 1 $ Cin $end
    $var wire 1 ) Sum $end
    $var wire 1 % Cout $end
    $var wire 1 * s1 $end
    $var wire 1 ; c1 $end
    $var wire 1 + c2 $end
    $scope module ha0 $end
     $var wire 1 9 A $end
     $var wire 1 : B $end
     $var wire 1 * Sum $end
     $var wire 1 ; CarryOut $end
    $upscope $end
    $scope module ha1 $end
     $var wire 1 * A $end
     $var wire 1 $ B $end
     $var wire 1 ) Sum $end
     $var wire 1 + CarryOut $end
    $upscope $end
   $upscope $end
   $scope module fa4 $end
    $var wire 1 < A $end
    $var wire 1 = B $end
    $var wire 1 % Cin $end
    $var wire 1 , Sum $end
    $var wire 1 2 Cout $end
    $var wire 1 - s1 $end
    $var wire 1 > c1 $end
    $var wire 1 . c2 $end
    $scope module ha0 $end
     $var wire 1 < A $end
     $var wire 1 = B $end
     $var wire 1 - Sum $end
     $var wire 1 > CarryOut $end
    $upscope $end
    $scope module ha1 $end
     $var wire 1 - A $end
     $var wire 1 % B $end
     $var wire 1 , Sum $end
     $var wire 1 . CarryOut $end
    $upscope $end
   $upscope $end
  $upscope $end
 $upscope $end
$enddefinitions $end


#0
0#
0$
0%
0&
0'
0(
0)
0*
0+
0,
0-
0.
b0000 /
b0000 0
b0000 1
02
03
04
05
06
07
08
09
0:
0;
0<
0=
0>
0?
#1
b0001 /
b0001 1
13
15
#2
b0000 /
b0001 0
03
14
#3
1#
1&
b0001 /
b0010 1
13
05
#4
1$
0&
1'
1(
1)
b0011 /
b0100 1
16
#5
1%
0)
1*
1+
1,
b0111 /
b1000 1
19
#6
0,
1-
1.
b1111 /
b0000 1
12
1<
#7
0#
0$
0%
1&
0(
1)
0+
1,
0.
b1010 /
b0101 0
b1111 1
02
03
15
09
1:
