sandbox/ripple-carry-adder/ripple-carry4-gen-old.v
`timescale 1ns/1ps

module half_adder(
    input  wire A, B,
    output wire Sum, CarryOut
);
    assign Sum      = A ^ B;
    assign CarryOut = A & B;
endmodule

module full_adder(
    input  wire A, B, Cin,
    output wire Sum, Cout
);
    wire s1, c1, c2;

    half_adder ha0 (.A(A),  .B(B),   .Sum(s1),  .CarryOut(c1));
    half_adder ha1 (.A(s1), .B(Cin), .Sum(Sum), .CarryOut(c2));

    assign Cout = c1 | c2;
endmodule

// using traditional verilog syntax we can use a genvar to instantiate clones of some hw module
module ripple_carry4_gen_old (
    input  wire [3:0] A,
    input  wire [3:0] B,
    input  wire       Cin,
    output wire [3:0] Sum,
    output wire       CarryOut
);
    wire [4:0] C;
    assign C[0]    = Cin;
    assign CarryOut = C[4];

    genvar i;
    generate
        for (i = 0; i < 4; i = i + 1) begin : GEN_FA
            full_adder fa (
                .A   (A[i]),
                .B   (B[i]),
                .Cin (C[i]),
                .Sum (Sum[i]),
                .Cout(C[i+1])
            );
        end
    endgenerate
endmodule

sandbox/full-adder/waveform.vcd
$version Generated by VerilatedVcd $end
$timescale 1ps $end
 $scope module TOP $end
  $var wire 1 # A $end
  $var wire 1 $ B $end
  $var wire 1 % Cin $end
  $var wire 1 & Sum $end
  $var wire 1 ' Cout $end
  $scope module full_adder $end
   $var wire 1 # A $end
   $var wire 1 $ B $end
   $var wire 1 % Cin $end
   $var wire 1 & Sum $end
   $var wire 1 ' Cout $end
   $var wire 1 ( s1 $end
   $var wire 1 ) c1 $end
   $var wire 1 * c2 $end
   $scope module ha0 $end
    $var wire 1 # A $end
    $var wire 1 $ B $end
    $var wire 1 ( Sum $end
    $var wire 1 ) CarryOut $end
   $upscope $end
   $scope module ha1 $end
    $var wire 1 ( A $end
    $var wire 1 % B $end
    $var wire 1 & Sum $end
    $var wire 1 * CarryOut $end
   $upscope $end
  $upscope $end
 $upscope $end
$enddefinitions $end


#0
0#
0$
0%
0&
0'
0(
0)
0*
#1
1%
1&
#2
1$
0%
1(
#3
1%
0&
1'
1*
#4
1#
0$
0%
1&
0'
0*
#5
1%
0&
1'
1*
#6
1$
0%
0(
1)
0*
#7
1%
1&
