sv_common_ips/14_dma_peripheral_request_mux/top.sv
// top.sv - Lesson 14
//
// Use-case:
//  - DMA engines and CPU/peripheral accesses sharing one peripheral bus.
//  - CPU control traffic has priority; DMA channels share leftover cycles.

module top (
    input  logic clk,
    input  logic rst_n,

    input  logic        cpu_req,
    input  logic        cpu_we,
    input  logic [3:0]  cpu_addr,
    input  logic [15:0] cpu_wdata,
    output logic        cpu_ready,
    output logic [15:0] cpu_rdata,

    input  logic        dma0_req,
    input  logic        dma0_we,
    input  logic [3:0]  dma0_addr,
    input  logic [15:0] dma0_wdata,
    output logic        dma0_ready,
    output logic [15:0] dma0_rdata,

    input  logic        dma1_req,
    input  logic        dma1_we,
    input  logic [3:0]  dma1_addr,
    input  logic [15:0] dma1_wdata,
    output logic        dma1_ready,
    output logic [15:0] dma1_rdata,

    output logic [2:0]  grant,
    output logic        dma_rr_ptr_dbg
);
    logic [15:0] regs [0:15];
    logic dma_rr_ptr;

    always_comb begin
        grant = 3'b000;

        if (cpu_req) begin
            grant = 3'b001;
        end else if (dma0_req && dma1_req) begin
            grant = dma_rr_ptr ? 3'b100 : 3'b010;
        end else if (dma0_req) begin
            grant = 3'b010;
        end else if (dma1_req) begin
            grant = 3'b100;
        end
    end

    assign dma_rr_ptr_dbg = dma_rr_ptr;

    always_ff @(posedge clk) begin
        if (!rst_n) begin
            dma_rr_ptr <= 1'b0;
            cpu_ready <= 1'b0;
            dma0_ready <= 1'b0;
            dma1_ready <= 1'b0;
            cpu_rdata <= '0;
            dma0_rdata <= '0;
            dma1_rdata <= '0;
            for (int i = 0; i < 16; i++) begin
                regs[i] <= 16'h2000 + i[15:0];
            end
        end else begin
            cpu_ready <= 1'b0;
            dma0_ready <= 1'b0;
            dma1_ready <= 1'b0;

            if (grant[0]) begin
                cpu_ready <= 1'b1;
                if (cpu_we) regs[cpu_addr] <= cpu_wdata;
                else        cpu_rdata <= regs[cpu_addr];
            end

            if (grant[1]) begin
                dma0_ready <= 1'b1;
                if (dma0_we) regs[dma0_addr] <= dma0_wdata;
                else         dma0_rdata <= regs[dma0_addr];
                dma_rr_ptr <= 1'b1;
            end

            if (grant[2]) begin
                dma1_ready <= 1'b1;
                if (dma1_we) regs[dma1_addr] <= dma1_wdata;
                else         dma1_rdata <= regs[dma1_addr];
                dma_rr_ptr <= 1'b0;
            end
        end
    end

    always_ff @(posedge clk) begin
        if (rst_n) begin
            assert ($onehot0(grant))
                else $fatal(1, "DMA mux violation: grant must be one-hot or zero");

            if (cpu_req) begin
                assert (grant == 3'b001)
                    else $fatal(1, "DMA mux violation: CPU request must take priority");
            end
        end
    end

endmodule

sv_common_ips/14_dma_peripheral_request_mux/waveform.vcd
$version Generated by VerilatedVcd $end
$timescale 1ps $end
 $scope module TOP $end
  $var wire 1 5 clk $end
  $var wire 1 6 rst_n $end
  $var wire 1 7 cpu_req $end
  $var wire 1 8 cpu_we $end
  $var wire 4 9 cpu_addr [3:0] $end
  $var wire 16 : cpu_wdata [15:0] $end
  $var wire 1 ; cpu_ready $end
  $var wire 16 < cpu_rdata [15:0] $end
  $var wire 1 = dma0_req $end
  $var wire 1 > dma0_we $end
  $var wire 4 ? dma0_addr [3:0] $end
  $var wire 16 @ dma0_wdata [15:0] $end
  $var wire 1 A dma0_ready $end
  $var wire 16 B dma0_rdata [15:0] $end
  $var wire 1 C dma1_req $end
  $var wire 1 D dma1_we $end
  $var wire 4 E dma1_addr [3:0] $end
  $var wire 16 F dma1_wdata [15:0] $end
  $var wire 1 G dma1_ready $end
  $var wire 16 H dma1_rdata [15:0] $end
  $var wire 3 I grant [2:0] $end
  $var wire 1 J dma_rr_ptr_dbg $end
  $scope module top $end
   $var wire 1 5 clk $end
   $var wire 1 6 rst_n $end
   $var wire 1 7 cpu_req $end
   $var wire 1 8 cpu_we $end
   $var wire 4 9 cpu_addr [3:0] $end
   $var wire 16 : cpu_wdata [15:0] $end
   $var wire 1 ; cpu_ready $end
   $var wire 16 < cpu_rdata [15:0] $end
   $var wire 1 = dma0_req $end
   $var wire 1 > dma0_we $end
   $var wire 4 ? dma0_addr [3:0] $end
   $var wire 16 @ dma0_wdata [15:0] $end
   $var wire 1 A dma0_ready $end
   $var wire 16 B dma0_rdata [15:0] $end
   $var wire 1 C dma1_req $end
   $var wire 1 D dma1_we $end
   $var wire 4 E dma1_addr [3:0] $end
   $var wire 16 F dma1_wdata [15:0] $end
   $var wire 1 G dma1_ready $end
   $var wire 16 H dma1_rdata [15:0] $end
   $var wire 3 I grant [2:0] $end
   $var wire 1 J dma_rr_ptr_dbg $end
   $var wire 16 # regs[0] [15:0] $end
   $var wire 16 $ regs[1] [15:0] $end
   $var wire 16 % regs[2] [15:0] $end
   $var wire 16 & regs[3] [15:0] $end
   $var wire 16 ' regs[4] [15:0] $end
   $var wire 16 ( regs[5] [15:0] $end
   $var wire 16 ) regs[6] [15:0] $end
   $var wire 16 * regs[7] [15:0] $end
   $var wire 16 + regs[8] [15:0] $end
   $var wire 16 , regs[9] [15:0] $end
   $var wire 16 - regs[10] [15:0] $end
   $var wire 16 . regs[11] [15:0] $end
   $var wire 16 / regs[12] [15:0] $end
   $var wire 16 0 regs[13] [15:0] $end
   $var wire 16 1 regs[14] [15:0] $end
   $var wire 16 2 regs[15] [15:0] $end
   $var wire 1 3 dma_rr_ptr $end
   $scope module unnamedblk1 $end
    $var wire 32 4 i [31:0] $end
   $upscope $end
  $upscope $end
 $upscope $end
$enddefinitions $end


#0
b0000000000000000 #
b0000000000000000 $
b0000000000000000 %
b0000000000000000 &
b0000000000000000 '
b0000000000000000 (
b0000000000000000 )
b0000000000000000 *
b0000000000000000 +
b0000000000000000 ,
b0000000000000000 -
b0000000000000000 .
b0000000000000000 /
b0000000000000000 0
b0000000000000000 1
b0000000000000000 2
03
b00000000000000000000000000000000 4
05
06
07
08
b0000 9
b0000000000000000 :
0;
b0000000000000000 <
0=
0>
b0000 ?
b0000000000000000 @
0A
b0000000000000000 B
0C
0D
b0000 E
b0000000000000000 F
0G
b0000000000000000 H
b000 I
0J
#1
b0010000000000000 #
b0010000000000001 $
b0010000000000010 %
b0010000000000011 &
b0010000000000100 '
b0010000000000101 (
b0010000000000110 )
b0010000000000111 *
b0010000000001000 +
b0010000000001001 ,
b0010000000001010 -
b0010000000001011 .
b0010000000001100 /
b0010000000001101 0
b0010000000001110 1
b0010000000001111 2
b00000000000000000000000000010000 4
15
#2
05
#3
15
#4
05
#5
15
#6
05
#7
15
#8
05
#9
15
#10
05
16
18
b0011 9
b1111111100000100 :
1=
b0010 ?
b1010110101001000 @
1C
1D
b1111 E
b1010110111101101 F
b010 I
#11
13
15
1A
b0010000000000010 B
b100 I
1J
#12
05
17
b0000 9
b1011110001111110 :
1>
b0011 ?
b1011101000101001 @
0C
0D
b0110 E
b1111011111110000 F
b001 I
#13
b1011110001111110 #
15
1;
0A
#14
05
07
b0010 9
b1101011100000101 :
0>
b1110 ?
b1101001110100010 @
1C
1D
b1110 E
b0000010001011101 F
b100 I
#15
b0000010001011101 1
03
15
0;
1G
b010 I
0J
#16
05
b1000 9
b0011100110110011 :
0=
1>
b0110 ?
b1001100110001000 @
0D
b1011 E
b0100000101110100 F
b100 I
#17
15
b0010000000001011 H
#18
05
17
08
b1010 9
b1111111111011001 :
1=
b1001 ?
b1010100001010111 @
0C
1D
b1000 E
b0000110001010100 F
b001 I
#19
15
1;
b0010000000001010 <
0G
#20
05
b1111 9
b0010011001101010 :
b1000 ?
b0001101100111010 @
0D
b0011 E
b1101011000111100 F
#21
15
b0010000000001111 <
#22
05
07
b0010 9
b0101101011011111 :
0>
b0111 ?
b0000001001111010 @
b1110 E
b1010001110100000 F
b010 I
#23
13
15
0;
1A
b0010000000000111 B
1J
#24
05
18
b0101 9
b0111110101111101 :
b1101 ?
b0010100011111011 @
1C
b1101 E
b1001101100011000 F
b100 I
#25
03
15
0A
1G
b0010000000001101 H
b010 I
0J
#26
05
17
08
b0110 9
b0011100000110000 :
0=
1>
b0100 ?
b0110010100101111 @
1D
b0001 E
b0001110010110010 F
b001 I
#27
15
1;
b0010000000000110 <
0G
#28
05
07
b0101111000111010 :
b0110 ?
b1111001011011001 @
b0010 E
b1111101100011001 F
b100 I
#29
b1111101100011001 %
15
0;
1G
#30
05
17
18
b0001 9
b1001100000111101 :
1=
0>
b1111 ?
b0101000101000000 @
0D
b1100 E
b1000001000110101 F
b001 I
#31
b1001100000111101 $
15
1;
0G
#32
05
08
b0100 9
b0010011101111010 :
b0011 ?
b1100111110010001 @
0C
1D
b0010 E
b1101111010111111 F
#33
15
b0010000000000100 <
#34
05
07
18
b1000 9
b1010100101110101 :
1>
b0100 ?
b1011010100011011 @
1C
b0011 E
b1101001011111000 F
b010 I
#35
b1011010100011011 '
13
15
0;
1A
b100 I
1J
#36
05
17
08
b0111 9
b0011111110010100 :
0=
b0000 ?
b1001111111110001 @
0D
b0000 E
b1000110000111011 F
b001 I
#37
15
1;
b0010000000000111 <
0A
#38
05
07
18
b0101 9
b1001000101101011 :
b0101 ?
b0110100001001000 @
1D
b0101 E
b1111100110111111 F
b100 I
#39
b1111100110111111 (
03
15
0;
1G
0J
#40
05
17
b1110011011110101 :
1=
b0011 ?
b1001110100000111 @
b0101000110101101 F
b001 I
#41
b1110011011110101 (
15
1;
0G
#42
05
07
b0010 9
b1110101011100110 :
0>
b1100 ?
b1111101010100000 @
0C
0D
b0001 E
b0001001101010101 F
b010 I
#43
13
15
0;
1A
b0010000000001100 B
1J
#44
05
17
08
b1000 9
b0111100111000111 :
1>
b1011 ?
b1010010001110010 @
1D
b1000 E
b0000110100100001 F
b001 I
#45
15
1;
b0010000000001000 <
0A
#46
05
07
18
b0011 9
b0111000111000100 :
0=
b0111 ?
b1111111011010100 @
1C
0D
b1011 E
b0000101101110010 F
b100 I
#47
03
15
0;
1G
b0010000000001011 H
0J
#48
05
b1010 9
b1101110111000100 :
1=
0>
b1111 ?
b0100011100010111 @
1D
b0100 E
b0000010010011010 F
b010 I
#49
13
15
1A
b0010000000001111 B
0G
b100 I
1J
#50
05
08
b0110 9
b0010100001111111 :
b1101 ?
b1101110101100101 @
b1001 E
b1110010101101110 F
#51
b1110010101101110 ,
03
15
0A
1G
b010 I
0J
#52
05
b0001 9
b1000100000100110 :
b1110 ?
b1101011100010010 @
b1000 E
b1111101101001001 F
#53
13
15
1A
b0000010001011101 B
0G
b100 I
1J
#54
05
18
b1100 9
b0111110111010111 :
1>
b1101 ?
b0000000011101001 @
b1011 E
b1111101001010111 F
#55
b1111101001010111 .
03
15
0A
1G
b010 I
0J
#56
05
17
08
b0100 9
b0011011110011000 :
b0100 ?
b1111111110001100 @
b0001001110100011 F
b001 I
#57
15
1;
b1011010100011011 <
0G
#58
05
07
18
b1000 9
b0001001000001111 :
b0000 ?
b0011001000011111 @
0D
b1010 E
b1111111011001100 F
b010 I
#59
b0011001000011111 #
13
15
0;
1A
b100 I
1J
#60
05
17
08
b1011 9
b0010001000000011 :
0>
b1000 ?
b1001011111010001 @
b0101 E
b0001111100110011 F
b001 I
#61
15
1;
b1111101001010111 <
0A
#62
05
b0001 9
b0100010001000100 :
0=
1>
b1101101111011111 @
b1010 E
b0001010100110000 F
#63
15
b1001100000111101 <
#64
05
07
18
b1111 9
b0000101100101001 :
1=
0>
b0000 ?
b1100110101100001 @
b1000 E
b1011100110100100 F
b100 I
#65
03
15
0;
1G
b0010000000001000 H
b010 I
0J
#66
05
08
b0011 9
b0101011111101110 :
1>
b1000 ?
b0010001111001010 @
0C
b1001 E
b0100000011100111 F
#67
b0010001111001010 +
13
15
1A
0G
1J
#68
05
17
18
b0100 9
b0001101101110100 :
0>
b0111 ?
b1110101001000101 @
1D
b0000 E
b0010001000011101 F
b001 I
#69
b0001101101110100 '
15
1;
0A
#70
05
08
b1111 9
b1111011011001100 :
b1101 ?
b0001010100000000 @
b0111 E
b0110001101101100 F
#71
15
b0010000000001111 <
#72
05
07
b1101110011100100 :
1>
b1110 ?
b0101100101101010 @
0D
b1011 E
b1111100000100101 F
b010 I
#73
b0101100101101010 1
15
0;
1A
#74
05
18
b1010 9
b1011011001001000 :
0>
b0001 ?
b1000110101000001 @
1C
b1110 E
b0010001100011110 F
b100 I
#75
03
15
0A
1G
b0101100101101010 H
b010 I
0J
#76
05
17
b1011 9
b1100010000011001 :
1>
b0110 ?
b1111001110001101 @
b1000 E
b1100010000111100 F
b001 I
#77
b1100010000011001 .
15
1;
0G
#78
05
07
b0100011100010100 :
0>
b0111 ?
b0001000110010010 @
b0001 E
b0000110000000011 F
b010 I
#79
13
15
0;
1A
b0010000000000111 B
b100 I
1J
#80
05
08
b0100 9
b1011101011100000 :
0=
1>
b0101 ?
b0001000001011000 @
0C
b0100 E
b1100101100011111 F
b000 I
#81
15
0A
#82
05
17
b1010 9
b1111111111000010 :
1=
b1111 ?
b1111110011001110 @
1D
b1101 E
b1000111110101010 F
b001 I
#83
15
1;
b0010000000001010 <
#84
05
b1000 9
b1001100010101111 :
b0111 ?
b1001101001011100 @
1C
b1000 E
b0111010100001000 F
#85
15
b0010001111001010 <
#86
05
b0010 9
b1001011010010010 :
b1100 ?
b1011100101001111 @
0C
0D
b0010 E
b0011101010110111 F
#87
15
b1111101100011001 <
#88
05
18
b1110 9
b0011110011111111 :
0=
b1110 ?
b0000111000101011 @
1C
1D
b0100 E
b0001010111001100 F
#89
b0011110011111111 1
15
#90
05
b0110 9
b0110010110000000 :
1=
0>
b1001 ?
b1000011111101111 @
0D
b0101 E
b0110111000111110 F
#91
b0110010110000000 )
15
#92
05
07
08
b0000 9
b0110000000111110 :
0=
1>
b1010 ?
b0010010011100101 @
0C
1D
b0111 E
b1110101111010000 F
b000 I
#93
15
0;
#94
05
17
b1101011001101000 :
b0010 ?
b0101100101110101 @
b0011 E
b1011010101110101 F
b001 I
#95
15
1;
b0011001000011111 <
#96
05
b1101 9
b1010011011100100 :
0>
b0110 ?
b0010001000011111 @
1C
0D
b0100 E
b0001100111011001 F
#97
15
b0010000000001101 <
#98
05
07
b1001 9
b0100111101110011 :
1=
b1101 ?
b0111010100001101 @
1D
b0001 E
b0101111010100100 F
b100 I
#99
b0101111010100100 $
03
15
0;
1G
b010 I
0J
#100
05
18
b1111 9
b1000011100001000 :
1>
b1000 ?
b1000000011001011 @
0D
b0100 E
b0011100101011110 F
#101
b1000000011001011 +
13
15
1A
0G
b100 I
1J
#102
05
b1001 9
b0110000000000000 :
0>
b0110 ?
b1010001000001010 @
0C
b0011 E
b0000011010101011 F
b010 I
#103
15
b0110010110000000 B
#104
05
17
08
b0100 9
b0010001001011001 :
1>
b0011 ?
b1100011011100001 @
1D
b1110 E
b0110000110011010 F
b001 I
#105
15
1;
b0001101101110100 <
0A
#106
05
b1110 9
b0001100100111000 :
b1110 ?
b1001101010101100 @
1C
0D
b1100 E
b0110100101100000 F
#107
15
b0011110011111111 <
#108
05
18
b0010 9
b0110101011111111 :
b0110 ?
b1001111001110101 @
0C
b1011 E
b0001000010101111 F
#109
b0110101011111111 %
15
#110
05
b1101101010101000 :
0=
b1010 ?
b0100100011101001 @
1C
b1000 E
b0010111101010101 F
#111
b1101101010101000 %
15
#112
05
08
b1101 9
b1011110000101110 :
1=
0>
b0001 ?
b0000000101011011 @
b1010 E
b0001001010100010 F
#113
15
b0010000000001101 <
#114
05
18
b0011 9
b0111010111110000 :
1>
b0011 ?
b1000011000111100 @
1D
b1000 E
b0100100111101001 F
#115
b0111010111110000 &
15
#116
05
07
08
b1011 9
b1010100101100110 :
b0001 ?
b0110010101101111 @
0D
b1100 E
b0010101101101010 F
b100 I
#117
03
15
0;
1G
b0010000000001100 H
b010 I
0J
#118
05
b1000 9
b0111010011111110 :
b1111 ?
b0010000001101011 @
0C
b0111 E
b0101100001000100 F
#119
b0010000001101011 2
13
15
1A
0G
1J
#120
05
17
b1111 9
b1101101000110110 :
b1110 ?
b0111100010111011 @
1C
b0001 E
b0011100100010101 F
b001 I
#121
15
1;
b0010000001101011 <
0A
#122
05
b0100 9
b0011100010110010 :
b0110 ?
b1011101110101010 @
1D
b0011 E
b1011101110111001 F
#123
15
b0001101101110100 <
#124
05
07
18
b1011 9
b0001000001100001 :
0>
b1000 ?
b0001100001111000 @
0C
0D
b1010 E
b1110111000100000 F
b010 I
#125
15
0;
1A
b1000000011001011 B
#126
05
08
b0001 9
b0111011001000110 :
0=
b1001 ?
b1110011111010101 @
1C
1D
b0000 E
b1100111010101001 F
b100 I
#127
b1100111010101001 #
03
15
0A
1G
0J
#128
05
b1001 9
b0110011100110100 :
1=
1>
b1101 ?
b0001000011100100 @
0D
b1011 E
b0000001010010011 F
b010 I
#129
b0001000011100100 0
13
15
1A
0G
b100 I
1J
#130
05
b0110 9
b0101001000011010 :
0=
b0000 ?
b1101000100101001 @
0C
b0010 E
b0101011010011100 F
b000 I
#131
15
0A
#132
05
17
b1010 9
b0111010010010110 :
b0110 ?
b1011001101100010 @
1C
b0100 E
b0010000000000010 F
b001 I
#133
15
1;
b0010000000001010 <
#134
05
b0010 9
b0110001010101110 :
1=
0>
b1110 ?
b1011100101000011 @
1D
b0001 E
b1001001101100000 F
#135
15
b1101101010101000 <
#136
05
07
b0100 9
b0110110001010001 :
0=
b1101 ?
b1100010100100011 @
b1010 E
b0001110011010000 F
b100 I
#137
b0001110011010000 -
03
15
0;
1G
0J
#138
05
17
b1001111010000001 :
1=
1>
b0001001111110010 @
0D
b1001 E
b0010111011100110 F
b001 I
#139
15
1;
b0001101101110100 <
0G
#140
05
07
18
b1100 9
b0101111000110100 :
0>
b0110 ?
b1101110001101111 @
1D
b0110 E
b0111011001101110 F
b010 I
#141
13
15
0;
1A
b0110010110000000 B
b100 I
1J
#142
05
08
b1011 9
b1111100011111100 :
b1100 ?
b1010110101110111 @
0D
b1101 E
b1001011111110001 F
#143
03
15
0A
1G
b0001000011100100 H
b010 I
0J
#144
05
18
b1101 9
b1011000001101110 :
0=
1>
b0010 ?
b1110101100011111 @
1D
b0001 E
b1011101101001010 F
b100 I
#145
b1011101101001010 $
15
#146
05
08
b1011 9
b0100000011111000 :
1=
b0101 ?
b0101011110111011 @
0C
b0110 E
b0100000011110001 F
b010 I
#147
b0101011110111011 (
13
15
1A
0G
1J
#148
05
b0000 9
b0010000111001000 :
b1110 ?
b0011001110110110 @
b0010 E
b0111111111001001 F
#149
b0011001110110110 1
15
#150
05
17
18
b1011 9
b1110110000001010 :
0=
0>
b0100 ?
b1000100111110100 @
1C
b1110 E
b0110000000000000 F
b001 I
#151
b1110110000001010 .
15
1;
0A
#152
05
07
b1110 9
b0100011111111100 :
1=
b0011 ?
b1110101110100011 @
0D
b1011 E
b1000000010100010 F
b100 I
#153
03
15
0;
1G
b1110110000001010 H
b010 I
0J
#154
05
17
08
b0110 9
b1010010110101100 :
b1010 ?
b0110101110011010 @
1D
b1111 E
b0101000101001001 F
b001 I
#155
15
1;
b0110010110000000 <
0G
#156
05
b1100 9
b1101111011011001 :
b0101 ?
b0100011000111101 @
b1011 E
b1100110000110001 F
#157
15
b0010000000001100 <
#158
05
b1001 9
b0111111000011111 :
1>
b0111 ?
b1111000001001111 @
0D
b0100 E
b1000111100110110 F
#159
15
b1110010101101110 <
#160
05
07
b1000 9
b1100010110011010 :
0>
b0011 ?
b1001110011011011 @
1D
b1110100110011000 F
b010 I
#161
13
15
0;
1A
b0111010111110000 B
b100 I
1J
#162
05
b0100 9
b1101011101010111 :
0=
b0110 ?
b1111101011000010 @
0C
0D
b1001 E
b0100000110001110 F
b000 I
#163
15
0A
#164
05
b0000 9
b1000101100010101 :
1=
1>
b1011 ?
b1101110000001010 @
1D
b1000 E
b0000011001110111 F
b010 I
#165
b1101110000001010 .
15
1A
#166
05
18
b1110 9
b1011110010101010 :
0>
b0101 ?
b0100000011010111 @
1C
0D
b0110 E
b0101000101011001 F
b100 I
#167
03
15
0A
1G
b0110010110000000 H
b010 I
0J
#168
05
17
08
b1101 9
b0000111100111011 :
b0000 ?
b1100011111000001 @
b1011 E
b0011011010001001 F
b001 I
#169
15
1;
b0001000011100100 <
0G
#170
05
07
18
b0111 9
b1100101000110010 :
0=
1>
b1001 ?
b0011000111011110 @
0C
1D
b1111 E
b0001011010110110 F
b000 I
#171
15
0;
#172
05
17
08
b1101 9
b1101011101110111 :
1=
b1100 ?
b0001101001101000 @
1C
0D
b0010 E
b1010110110001010 F
b001 I
#173
15
1;
#174
05
07
b0001 9
b1100000011101011 :
0=
b1101 ?
b1111011111111010 @
1D
b0001 E
b0110111100000110 F
b100 I
#175
b0110111100000110 $
15
0;
1G
#176
05
b0110011000011010 :
b1001 ?
b0000101010001010 @
0C
0D
b0000 E
b0101001001100100 F
b000 I
#177
15
0G
#178
05
17
b0011 9
b0001001001110101 :
1=
b1010 ?
b1010011100001100 @
1C
1D
b0100 E
b0110011101000111 F
b001 I
#179
15
1;
b0111010111110000 <
#180
05
b1100 9
b1100011110100111 :
0>
b1111110011010010 @
0D
b0110 E
b1101101011000001 F
#181
15
b0010000000001100 <
#182
05
07
b0111 9
b0000111111001100 :
b0111000101010110 @
0C
b0001 E
b1111001010101101 F
b010 I
#183
13
15
0;
1A
b0001110011010000 B
1J
#184
05
17
18
b1011 9
b1000101101010001 :
1>
b1100 ?
b0110111001010100 @
1C
b0010 E
b0000011001111110 F
b001 I
#185
b1000101101010001 .
15
1;
0A
#186
05
07
b0000 9
b0101100001101111 :
0>
b1000 ?
b0000101001100101 @
0C
b0001 E
b0000111000001101 F
b010 I
#187
15
0;
1A
b1000000011001011 B
#188
05
08
b0010 9
b1010001111110010 :
1>
b0000 ?
b0010100101011011 @
b1100 E
b1111000011010101 F
#189
b0010100101011011 #
15
#190
05
18
b1101111011000100 :
0>
b1001011111010100 @
1C
1D
b0010 E
b1001001010110011 F
b100 I
#191
b1001001010110011 %
03
15
0A
1G
b010 I
0J
#192
05
17
b1100 9
b1110011010011010 :
b1100 ?
b0100001111101001 @
0D
b1010 E
b0100010101011111 F
b001 I
#193
b1110011010011010 /
15
1;
0G
#194
05
08
b1000 9
b1111010100100110 :
0=
1>
b0101 ?
b1011111110000000 @
b0101 E
b0001100010111110 F
#195
15
b1000000011001011 <
#196
05
07
b1111 9
b0011100000001100 :
b1010 ?
b1110010101011110 @
0C
b1010 E
b0100000001101111 F
b000 I
#197
15
0;
#198
05
17
b0101 9
b1101000111010101 :
1=
0>
b1100 ?
b0010111010101010 @
1C
b1001 E
b0010101101010000 F
b001 I
#199
15
1;
b0101011110111011 <
#200
05
b0111 9
b0011010011111011 :
1>
b0010 ?
b0000110110011111 @
b0111 E
b0010000111110001 F
#201
15
b0010000000000111 <
#202
05
07
18
b1101 9
b1010011111001110 :
0=
0>
b0101 ?
b1100010000011001 @
1D
b0100 E
b1001011011010000 F
b100 I
#203
b1001011011010000 '
15
0;
1G
#204
05
17
b0010 9
b1011111111000010 :
1>
b1011 ?
b0100011110011001 @
b1010000101101110 F
b001 I
#205
b1011111111000010 %
15
1;
0G
#206
05
08
b1001 9
b1110110110101001 :
1=
0>
b1011010110101000 @
0D
b1101 E
b0001100011000001 F
#207
15
b1110010101101110 <
#208
05
07
18
b1100 9
b1101010001001010 :
1>
b0000 ?
b1010101001100110 @
1D
b1001 E
b0001110100111000 F
b010 I
#209
b1010101001100110 #
13
15
0;
1A
b100 I
1J
#210
05
17
08
b1111 9
b0010001100010001 :
b1011 ?
b0000110111011000 @
0C
0D
b0111 E
b0010100111110011 F
b001 I
#211
15
1;
b0010000001101011 <
0A
#212
05
07
b1001 9
b0010001001000111 :
b1001 ?
b1000101111001111 @
1C
1D
b1011 E
b1100100001000111 F
b100 I
#213
b1100100001000111 .
03
15
0;
1G
b010 I
0J
#214
05
18
b0111 9
b0100010100011110 :
0>
b0011 ?
b0000010001001101 @
0C
0D
b1000 E
b0011101101110011 F
#215
13
15
1A
b0111010111110000 B
0G
1J
#216
05
17
b0101 9
b1001111001001111 :
1>
b1101 ?
b0100000000111011 @
1C
b0010 E
b0111110000000110 F
b001 I
#217
b1001111001001111 (
15
1;
0A
#218
05
08
b0000 9
b0010011011010010 :
0>
b0100 ?
b1011100101110011 @
0C
b0001 E
b1110010111000100 F
#219
15
b1010101001100110 <
#220
05
07
b0110 9
b1001101001110101 :
1>
b0000 ?
b0011001100001101 @
1C
1D
b1111 E
b1010010011000101 F
b100 I
#221
b1010010011000101 2
03
15
0;
1G
b010 I
0J
#222
05
18
b1111 9
b0010010100101001 :
b0001 ?
b1111111010111011 @
b0000 E
b0101010111111110 F
#223
b1111111010111011 $
13
15
1A
0G
b100 I
1J
#224
05
17
b0000 9
b0011111101110001 :
0=
0>
b1101 ?
b0101111011101100 @
0D
b1101 E
b1110100110001101 F
b001 I
#225
b0011111101110001 #
15
1;
0A
#226
05
08
b1101 9
b0110101101001111 :
1=
1>
b1011 ?
b0100110011000000 @
1D
b0010 E
b0111001101111110 F
#227
15
b0001000011100100 <
#228
05
07
b0000 9
b0111011111101110 :
0=
b1000 ?
b0100010111100000 @
0D
b1100 E
b1000000101110101 F
b100 I
#229
03
15
0;
1G
b1110011010011010 H
0J
#230
05
b0001110001111110 :
0>
b0010 ?
b1100100101100000 @
0C
b1000 E
b0101101110110010 F
b000 I
#231
15
0G
#232
05
18
b0011 9
b1101110110111011 :
1=
1>
b0011 ?
b0110000010111110 @
1D
b0001 E
b1001000010001001 F
b010 I
#233
b0110000010111110 &
13
15
1A
1J
#234
05
17
b1011 9
b1011100111000011 :
0=
0>
b0100 ?
b1100110011101001 @
1C
b1001 E
b0001100100011010 F
b001 I
#235
b1011100111000011 .
15
1;
0A
#236
05
07
b0011 9
b0110101001100001 :
1=
1>
b1100 ?
b1111011101000101 @
0C
0D
b1011 E
b0111101110111100 F
b010 I
#237
b1111011101000101 /
15
0;
1A
#238
05
b1111 9
b1011101110101111 :
b1111 ?
b1001011111101101 @
1C
1D
b0010 E
b1011001100110101 F
b100 I
#239
b1011001100110101 %
03
15
0A
1G
b010 I
0J
#240
05
b0111 9
b1010000000000010 :
b0111 ?
b0000100010110111 @
0C
b0000 E
b0110001000011110 F
#241
b0000100010110111 *
13
15
1A
0G
1J
#242
05
b1110 9
b1110101010111110 :
b0001 ?
b0000111101110100 @
1C
0D
b0100 E
b0001001010000111 F
b100 I
#243
03
15
0A
1G
b1001011011010000 H
b010 I
0J
#244
05
b0101001011101100 :
b0010 ?
b0111110001111011 @
1D
b1101 E
b0101010110001110 F
#245
b0111110001111011 %
13
15
1A
0G
b100 I
1J
#246
05
08
b0001 9
b1001000100111110 :
0>
b1001 ?
b1111010001001110 @
b0001 E
b0001000101000101 F
#247
b0001000101000101 $
03
15
0A
1G
b010 I
0J
#248
05
17
b0101 9
b1110101100000110 :
0=
1>
b0100 ?
b1010001001111110 @
b1011 E
b1101010010011101 F
b001 I
#249
15
1;
b1001111001001111 <
0G
#250
05
07
18
b0001 9
b0101110010011111 :
b0000 ?
b1101011001000011 @
b0011 E
b0000100010101001 F
b100 I
#251
b0000100010101001 &
15
0;
1G
#252
05
17
08
b0010 9
b0100101111011101 :
1=
0>
b0110 ?
b0101011000000100 @
b0000 E
b0100101111110111 F
b001 I
#253
15
1;
b0111110001111011 <
0G
#254
05
18
b0000 9
b1010010101000100 :
1>
b1000 ?
b1000100110000000 @
0C
b1111 E
b0000011010000101 F
#255
b1010010101000100 #
15
#256
05
07
b1111 9
b1100001011101010 :
0>
b0101 ?
b0101010001010101 @
1C
b1110 E
b1001100100101011 F
b010 I
#257
13
15
0;
1A
b1001111001001111 B
b100 I
1J
#258
05
17
b1011 9
b0100100011101001 :
0=
1>
b1000 ?
b1010010110010111 @
0C
0D
b0011 E
b1010010101110010 F
b001 I
#259
b0100100011101001 .
15
1;
0A
#260
05
07
b0101 9
b1111011101001100 :
1=
b1111101010111001 @
1C
1D
b0110 E
b0010101001111010 F
b100 I
#261
b0010101001111010 )
03
15
0;
1G
b010 I
0J
#262
05
08
b1100 9
b0011011100001100 :
0>
b0001 ?
b1001101010100101 @
0C
0D
b1001 E
b1001111011001011 F
#263
13
15
1A
b0001000101000101 B
0G
1J
#264
05
18
b1001 9
b0111110000000101 :
1>
b0110 ?
b1100100010000011 @
1D
b1111 E
b1101011001000100 F
#265
b1100100010000011 )
15
#266
05
08
b0101101011000010 :
0>
b0000 ?
b0010010111011100 @
1C
0D
b1110 E
b0001010101011001 F
b100 I
#267
03
15
0A
1G
b0011001110110110 H
b010 I
0J
#268
05
b0000 9
b1011111110000010 :
1>
b1100 ?
b1111010111100100 @
0C
b1101 E
b1001001100000100 F
#269
b1111010111100100 /
13
15
1A
0G
1J
#270
05
17
b1111 9
b0010011111100000 :
0=
b0011 ?
b0100111101001011 @
1C
b0100111001010110 F
b001 I
#271
15
1;
b1010010011000101 <
0A
#272
05
18
b0101 9
b0000001111100010 :
1=
0>
b0101 ?
b1101110010111111 @
0C
1D
b1110 E
b0000100110011100 F
#273
b0000001111100010 (
15
#274
05
b1011 9
b0001001110011000 :
b0000 ?
b0101101101001100 @
1C
0D
b1001 E
b0000100111010001 F
#275
b0001001110011000 .
15
#276
05
07
08
b0100 9
b0110000100100001 :
b0001 ?
b0001001111111001 @
b0010 E
b0001100101000111 F
b100 I
#277
03
15
0;
1G
b0111110001111011 H
b010 I
0J
#278
05
18
b0001 9
b0110000100001011 :
b1000 ?
b0011011000111011 @
1D
b0110 E
b1001111111100010 F
#279
13
15
1A
b1000000011001011 B
0G
b100 I
1J
#280
05
08
b1101 9
b1010000010110100 :
b0000 ?
b0111011111010111 @
b0000 E
b1001100111111110 F
#281
b1001100111111110 #
03
15
0A
1G
b010 I
0J
