sv_common_ips/12_noc_router_egress/top.sv
// top.sv - Lesson 12
//
// Use-case:
//  - NoC/router output arbitration: multiple virtual channels to one egress.
//  - Egress only sends when downstream credit is available.

module top (
    input  logic clk,
    input  logic rst_n,

    input  logic       vc0_valid,
    input  logic [7:0] vc0_flit,
    output logic       vc0_ready,

    input  logic       vc1_valid,
    input  logic [7:0] vc1_flit,
    output logic       vc1_ready,

    input  logic       vc2_valid,
    input  logic [7:0] vc2_flit,
    output logic       vc2_ready,

    input  logic       vc3_valid,
    input  logic [7:0] vc3_flit,
    output logic       vc3_ready,

    input  logic       egr_credit,
    output logic       egr_valid,
    output logic [7:0] egr_flit,
    output logic [1:0] egr_vc,

    output logic [3:0] grant,
    output logic [1:0] rr_ptr_dbg
);
    logic [1:0] rr_ptr;

    always_comb begin
        logic [3:0] valid;
        valid = {vc3_valid, vc2_valid, vc1_valid, vc0_valid};

        grant = 4'b0000;
        if (egr_credit) begin
            for (int off = 0; off < 4; off++) begin
                int idx;
                idx = int'(rr_ptr) + off;
                if (idx >= 4) idx = idx - 4;

                if (grant == 4'b0000 && valid[idx]) begin
                    grant[idx] = 1'b1;
                end
            end
        end

        vc0_ready = grant[0];
        vc1_ready = grant[1];
        vc2_ready = grant[2];
        vc3_ready = grant[3];

        egr_valid = |grant;
        egr_flit = 8'h00;
        egr_vc = 2'd0;

        unique case (1'b1)
            grant[0]: begin egr_flit = vc0_flit; egr_vc = 2'd0; end
            grant[1]: begin egr_flit = vc1_flit; egr_vc = 2'd1; end
            grant[2]: begin egr_flit = vc2_flit; egr_vc = 2'd2; end
            grant[3]: begin egr_flit = vc3_flit; egr_vc = 2'd3; end
            default: begin egr_flit = 8'h00;    egr_vc = 2'd0; end
        endcase
    end

    assign rr_ptr_dbg = rr_ptr;

    always_ff @(posedge clk) begin
        if (!rst_n) begin
            rr_ptr <= 2'd0;
        end else if (|grant) begin
            rr_ptr <= egr_vc + 2'd1;
        end
    end

    always_ff @(posedge clk) begin
        if (rst_n) begin
            assert ($onehot0(grant))
                else $fatal(1, "NoC egress violation: grant must be one-hot or zero");

            assert (egr_valid == (|grant))
                else $fatal(1, "NoC egress violation: egr_valid mismatch with grant");

            if (!egr_credit) begin
                assert (grant == 4'b0000)
                    else $fatal(1, "NoC egress violation: grant without credit");
            end
        end
    end

endmodule

sv_common_ips/12_noc_router_egress/waveform.vcd
$version Generated by VerilatedVcd $end
$timescale 1ps $end
 $scope module TOP $end
  $var wire 1 # clk $end
  $var wire 1 $ rst_n $end
  $var wire 1 % vc0_valid $end
  $var wire 8 & vc0_flit [7:0] $end
  $var wire 1 ' vc0_ready $end
  $var wire 1 ( vc1_valid $end
  $var wire 8 ) vc1_flit [7:0] $end
  $var wire 1 * vc1_ready $end
  $var wire 1 + vc2_valid $end
  $var wire 8 , vc2_flit [7:0] $end
  $var wire 1 - vc2_ready $end
  $var wire 1 . vc3_valid $end
  $var wire 8 / vc3_flit [7:0] $end
  $var wire 1 0 vc3_ready $end
  $var wire 1 1 egr_credit $end
  $var wire 1 2 egr_valid $end
  $var wire 8 3 egr_flit [7:0] $end
  $var wire 2 4 egr_vc [1:0] $end
  $var wire 4 5 grant [3:0] $end
  $var wire 2 6 rr_ptr_dbg [1:0] $end
  $scope module top $end
   $var wire 1 # clk $end
   $var wire 1 $ rst_n $end
   $var wire 1 % vc0_valid $end
   $var wire 8 & vc0_flit [7:0] $end
   $var wire 1 ' vc0_ready $end
   $var wire 1 ( vc1_valid $end
   $var wire 8 ) vc1_flit [7:0] $end
   $var wire 1 * vc1_ready $end
   $var wire 1 + vc2_valid $end
   $var wire 8 , vc2_flit [7:0] $end
   $var wire 1 - vc2_ready $end
   $var wire 1 . vc3_valid $end
   $var wire 8 / vc3_flit [7:0] $end
   $var wire 1 0 vc3_ready $end
   $var wire 1 1 egr_credit $end
   $var wire 1 2 egr_valid $end
   $var wire 8 3 egr_flit [7:0] $end
   $var wire 2 4 egr_vc [1:0] $end
   $var wire 4 5 grant [3:0] $end
   $var wire 2 6 rr_ptr_dbg [1:0] $end
   $var wire 2 7 rr_ptr [1:0] $end
   $scope module unnamedblk1 $end
    $var wire 4 8 valid [3:0] $end
    $scope module unnamedblk2 $end
     $var wire 32 9 off [31:0] $end
     $scope module unnamedblk3 $end
      $var wire 32 : idx [31:0] $end
     $upscope $end
    $upscope $end
   $upscope $end
  $upscope $end
 $upscope $end
$enddefinitions $end


#0
0#
0$
0%
b00000000 &
0'
0(
b00000000 )
0*
0+
b00000000 ,
0-
0.
b00000000 /
00
01
02
b00000000 3
b00 4
b0000 5
b00 6
b00 7
b0000 8
b00000000000000000000000000000000 9
b00000000000000000000000000000000 :
#1
1#
#2
0#
#3
1#
#4
0#
#5
1#
#6
0#
#7
1#
#8
0#
#9
1#
#10
0#
1$
1%
b01100100 &
b10101100 )
b01110000 ,
b01000001 /
b0001 8
#11
1#
#12
0#
0%
b01111100 &
b01000110 )
1+
b11011110 ,
1-
1.
b01100010 /
11
12
b11011110 3
b10 4
b0100 5
b1100 8
b00000000000000000000000000000100 9
b00000000000000000000000000000011 :
#13
1#
0-
10
b01100010 3
b11 4
b1000 5
b11 6
b11 7
b00000000000000000000000000000010 :
#14
0#
b01100010 &
b10111011 )
b11101000 ,
b00101110 /
00
01
02
b00000000 3
b00 4
b0000 5
#15
1#
#16
0#
b10110001 &
1(
b00101010 )
0+
b00011010 ,
b01110111 /
10
11
12
b01110111 3
b11 4
b1000 5
b1010 8
#17
1#
1*
00
b00101010 3
b01 4
b0010 5
b00 6
b00 7
b00000000000000000000000000000011 :
#18
0#
b00011000 &
b01011000 )
0*
b00110100 ,
b11010111 /
01
02
b00000000 3
b00 4
b0000 5
#19
1#
#20
0#
1%
b01100001 &
1'
b00100000 )
1+
b00000111 ,
b00001111 /
11
12
b01100001 3
b0001 5
b1111 8
#21
1#
0'
1*
b00100000 3
b01 4
b0010 5
b01 6
b01 7
b00000000000000000000000000000000 :
#22
0#
b00000100 &
0(
b00010111 )
0*
0+
b11100000 ,
b11000010 /
10
b11000010 3
b11 4
b1000 5
b1001 8
#23
1#
1'
00
b00000100 3
b00 4
b0001 5
b00 6
b00 7
b00000000000000000000000000000011 :
#24
0#
0%
b10011110 &
0'
1(
b11110011 )
1*
b10111011 ,
b01011110 /
b11110011 3
b01 4
b0010 5
b1010 8
#25
1#
0*
10
b01011110 3
b11 4
b1000 5
b10 6
b10 7
b00000000000000000000000000000001 :
#26
0#
1%
b01101101 &
b11100100 )
1+
b01101010 ,
b11011001 /
00
01
02
b00000000 3
b00 4
b0000 5
b1111 8
#27
1#
#28
0#
0%
b11100101 &
b11010100 )
b10010111 ,
1-
b00001010 /
11
12
b10010111 3
b10 4
b0100 5
b1110 8
#29
1#
0-
10
b00001010 3
b11 4
b1000 5
b11 6
b11 7
b00000000000000000000000000000010 :
#30
0#
1%
b00010111 &
0(
b00011101 )
0+
b00010011 ,
b00001000 /
b00001000 3
b1001 8
#31
1#
1'
00
b00010111 3
b00 4
b0001 5
b00 6
b00 7
b00000000000000000000000000000011 :
#32
0#
0%
b00111011 &
0'
b01011010 )
b01010111 ,
b10000100 /
10
b10000100 3
b11 4
b1000 5
b1000 8
#33
1#
#34
0#
1%
b01110111 &
1'
b11001000 )
1+
b00110011 ,
b00010000 /
00
b01110111 3
b00 4
b0001 5
b1101 8
#35
1#
0'
1-
b00110011 3
b10 4
b0100 5
b01 6
b01 7
b00000000000000000000000000000000 :
#36
0#
b00111101 &
b10011110 )
b01111010 ,
0-
b11100101 /
01
02
b00000000 3
b00 4
b0000 5
#37
1#
#38
0#
b00001110 &
b01011100 )
0+
b11100100 ,
b00000100 /
10
11
12
b00000100 3
b11 4
b1000 5
b1001 8
#39
1#
1'
00
b00001110 3
b00 4
b0001 5
b00 6
b00 7
b00000000000000000000000000000011 :
#40
0#
b11100101 &
0'
b10010101 )
1+
b10110100 ,
b11111111 /
01
02
b00000000 3
b0000 5
b1101 8
#41
1#
#42
0#
b10100001 &
1(
b00101110 )
b10010011 ,
b11111001 /
b1111 8
#43
1#
#44
0#
0%
b01000101 &
0(
b11000111 )
0+
b10011101 ,
0.
b00011010 /
11
b0000 8
#45
1#
#46
0#
b10110000 &
1(
b00100000 )
1*
b01000001 ,
b01011110 /
12
b00100000 3
b01 4
b0010 5
b0010 8
#47
1#
b10 6
b10 7
b00000000000000000000000000000001 :
#48
0#
b01000110 &
b10101010 )
0*
1+
b10100110 ,
1-
1.
b00101101 /
b10100110 3
b10 4
b0100 5
b1110 8
#49
1#
0-
10
b00101101 3
b11 4
b1000 5
b11 6
b11 7
b00000000000000000000000000000010 :
#50
0#
1%
b01100101 &
0(
b01110001 )
b00001000 ,
b11100111 /
b11100111 3
b1101 8
#51
1#
1'
00
b01100101 3
b00 4
b0001 5
b00 6
b00 7
b00000000000000000000000000000011 :
#52
0#
b00010001 &
1(
b11111000 )
b10111101 ,
0.
b10101111 /
b00010001 3
b0111 8
#53
1#
0'
1*
b11111000 3
b01 4
b0010 5
b01 6
b01 7
b00000000000000000000000000000000 :
#54
0#
0%
b01000101 &
0(
b10001010 )
0*
0+
b10000111 ,
1.
b10001001 /
10
b10001001 3
b11 4
b1000 5
b1000 8
#55
1#
b00 6
b00 7
b00000000000000000000000000000011 :
#56
0#
b11110100 &
b11001000 )
1+
b11101000 ,
1-
b10111011 /
00
b11101000 3
b10 4
b0100 5
b1100 8
#57
1#
0-
10
b10111011 3
b11 4
b1000 5
b11 6
b11 7
b00000000000000000000000000000010 :
#58
0#
1%
1'
b00010000 )
0+
b01100101 ,
0.
b00000111 /
00
b11110100 3
b00 4
b0001 5
b0001 8
#59
1#
b01 6
b01 7
b00000000000000000000000000000000 :
#60
0#
0%
b10001111 &
0'
b11100000 )
1+
b10000000 ,
1-
1.
b01001010 /
b10000000 3
b10 4
b0100 5
b1100 8
#61
1#
0-
10
b01001010 3
b11 4
b1000 5
b11 6
b11 7
b00000000000000000000000000000010 :
#62
0#
1%
b00001010 &
1(
b11011010 )
0+
b00000110 ,
b01111000 /
b01111000 3
b1011 8
#63
1#
1'
00
b00001010 3
b00 4
b0001 5
b00 6
b00 7
b00000000000000000000000000000011 :
#64
0#
0%
b11000111 &
0'
0(
b10011010 )
1+
b01100101 ,
1-
0.
b00100001 /
b01100101 3
b10 4
b0100 5
b0100 8
#65
1#
b11 6
b11 7
b00000000000000000000000000000010 :
#66
0#
1%
b00101000 &
1(
b11100011 )
b10110001 ,
0-
1.
b10011111 /
10
b10011111 3
b11 4
b1000 5
b1111 8
#67
1#
1'
00
b00101000 3
b00 4
b0001 5
b00 6
b00 7
b00000000000000000000000000000011 :
#68
0#
b01000000 &
b10011110 )
0+
b10010100 ,
b01010010 /
b01000000 3
b1011 8
#69
1#
0'
1*
b10011110 3
b01 4
b0010 5
b01 6
b01 7
b00000000000000000000000000000000 :
#70
0#
b10110100 &
b11100010 )
0*
1+
b10100110 ,
b01110001 /
01
02
b00000000 3
b00 4
b0000 5
b1111 8
#71
1#
#72
0#
0%
b00011001 &
0(
b00010010 )
b10111000 ,
1-
0.
b00001010 /
11
12
b10111000 3
b10 4
b0100 5
b0100 8
#73
1#
b11 6
b11 7
b00000000000000000000000000000010 :
#74
0#
b11101110 &
b11000110 )
b01011000 ,
b10010001 /
b01011000 3
#75
1#
#76
0#
b10110100 &
1(
b11010110 )
b10000110 ,
0-
1.
b01111010 /
10
b01111010 3
b11 4
b1000 5
b1110 8
#77
1#
1*
00
b11010110 3
b01 4
b0010 5
b00 6
b00 7
b00000000000000000000000000000011 :
#78
0#
1%
b10011010 &
1'
0(
b11010101 )
0*
b01110010 ,
b10001011 /
b10011010 3
b00 4
b0001 5
b1101 8
#79
1#
0'
1-
b01110010 3
b10 4
b0100 5
b01 6
b01 7
b00000000000000000000000000000000 :
#80
0#
0%
b10111111 &
1(
b10110011 )
1*
b00000110 ,
0-
0.
b00101101 /
b10110011 3
b01 4
b0010 5
b0110 8
#81
1#
0*
1-
b00000110 3
b10 4
b0100 5
b10 6
b10 7
b00000000000000000000000000000001 :
#82
0#
1%
b10001011 &
b11101101 )
b11100101 ,
1.
b10000000 /
b11100101 3
b1111 8
#83
1#
0-
10
b10000000 3
b11 4
b1000 5
b11 6
b11 7
b00000000000000000000000000000010 :
#84
0#
b01000011 &
b11001110 )
0+
b01110001 ,
0.
b00010110 /
00
01
02
b00000000 3
b00 4
b0000 5
b0011 8
#85
1#
#86
0#
b00001100 &
0(
b01110111 )
1+
b01001010 ,
1.
b00111110 /
b1101 8
#87
1#
#88
0#
0%
b01010000 &
b11001010 )
b01111000 ,
b00011100 /
b1100 8
#89
1#
#90
0#
b01010001 &
1(
b10111111 )
b11110101 ,
0.
b10111001 /
b0110 8
#91
1#
#92
0#
1%
b10111111 &
b01001000 )
0+
b01100101 ,
b01111101 /
b0011 8
#93
1#
#94
0#
b11010110 &
0(
b01101110 )
1+
b11100001 ,
1.
b11111010 /
10
11
12
b11111010 3
b11 4
b1000 5
b1101 8
#95
1#
1'
00
b11010110 3
b00 4
b0001 5
b00 6
b00 7
b00000000000000000000000000000011 :
#96
0#
b11011011 &
b11000110 )
b00110111 ,
0.
b10001001 /
b11011011 3
b0101 8
#97
1#
0'
1-
b00110111 3
b10 4
b0100 5
b01 6
b01 7
b00000000000000000000000000000000 :
#98
0#
0%
b11110101 &
b01011110 )
b00001011 ,
0-
1.
b11010011 /
01
02
b00000000 3
b00 4
b0000 5
b1100 8
#99
1#
#100
0#
1%
b00110001 &
b00001110 )
b00011010 ,
1-
b11001010 /
11
12
b00011010 3
b10 4
b0100 5
b1101 8
#101
1#
0-
10
b11001010 3
b11 4
b1000 5
b11 6
b11 7
b00000000000000000000000000000010 :
#102
0#
0%
b00010110 &
b10111110 )
0+
b10001010 ,
0.
b10101011 /
00
02
b00000000 3
b00 4
b0000 5
b0000 8
#103
1#
#104
0#
b01011011 &
b00111000 )
1+
b00001111 ,
1.
b11110100 /
10
12
b11110100 3
b11 4
b1000 5
b1100 8
#105
1#
1-
00
b00001111 3
b10 4
b0100 5
b00 6
b00 7
b00000000000000000000000000000011 :
#106
0#
b11011001 &
1(
b10010101 )
1*
b10010000 ,
0-
b11110011 /
b10010101 3
b01 4
b0010 5
b1110 8
#107
1#
0*
1-
b10010000 3
b10 4
b0100 5
b10 6
b10 7
b00000000000000000000000000000001 :
#108
0#
1%
b11000001 &
b01111110 )
0+
b01101111 ,
0-
b01010111 /
01
02
b00000000 3
b00 4
b0000 5
b1011 8
#109
1#
#110
0#
b01010111 &
0(
b10000010 )
b01100110 ,
b00101010 /
10
11
12
b00101010 3
b11 4
b1000 5
b1001 8
#111
1#
1'
00
b01010111 3
b00 4
b0001 5
b00 6
b00 7
b00000000000000000000000000000011 :
#112
0#
b00010011 &
0'
1(
b01110101 )
1+
b11111000 ,
0.
b00011000 /
01
02
b00000000 3
b0000 5
b0111 8
#113
1#
#114
0#
0%
b10001100 &
b10100110 )
1*
0+
b00101110 ,
b10010010 /
11
12
b10100110 3
b01 4
b0010 5
b0010 8
#115
1#
b10 6
b10 7
b00000000000000000000000000000001 :
#116
0#
1%
b10000110 &
b10001011 )
0*
1+
b10100100 ,
1-
b10001101 /
b10100100 3
b10 4
b0100 5
b0111 8
#117
1#
1'
0-
b10000110 3
b00 4
b0001 5
b11 6
b11 7
b00000000000000000000000000000010 :
#118
0#
0%
b11111101 &
0'
b01101111 )
0+
b00101101 ,
1.
b00000100 /
01
02
b00000000 3
b0000 5
b1010 8
#119
1#
#120
0#
1%
b01001000 &
0(
b01101001 )
1+
b10101010 ,
b10000000 /
10
11
12
b10000000 3
b11 4
b1000 5
b1101 8
#121
1#
1'
00
b01001000 3
b00 4
b0001 5
b00 6
b00 7
b00000000000000000000000000000011 :
#122
0#
b00011101 &
0'
1(
b00110101 )
b10101100 ,
b00111010 /
01
02
b00000000 3
b0000 5
b1111 8
#123
1#
#124
0#
0%
b11111001 &
b00111110 )
0+
b01111111 ,
b11110101 /
b1010 8
#125
1#
#126
0#
1%
b10100101 &
1'
b00001000 )
1+
b00110011 ,
0.
b10010000 /
11
12
b10100101 3
b0001 5
b0111 8
#127
1#
0'
1*
b00001000 3
b01 4
b0010 5
b01 6
b01 7
b00000000000000000000000000000000 :
#128
0#
b11001011 &
b00111110 )
0*
b01101010 ,
1.
b11010110 /
01
02
b00000000 3
b00 4
b0000 5
b1111 8
#129
1#
#130
0#
0%
b00011110 &
0(
b00011001 )
0+
b00001101 /
10
11
12
b00001101 3
b11 4
b1000 5
b1000 8
#131
1#
b00 6
b00 7
b00000000000000000000000000000011 :
#132
0#
1%
b11101000 &
1'
b11100011 )
1+
b01011001 ,
0.
b01111001 /
00
b11101000 3
b00 4
b0001 5
b0101 8
#133
1#
0'
1-
b01011001 3
b10 4
b0100 5
b01 6
b01 7
b00000000000000000000000000000000 :
#134
0#
0%
b11010000 &
b01011100 )
b11001001 ,
b11011110 /
b11001001 3
b0100 8
#135
1#
b11 6
b11 7
b00000000000000000000000000000010 :
#136
0#
b01001100 &
1(
b01110010 )
1*
0+
b10111010 ,
0-
b10110101 /
b01110010 3
b01 4
b0010 5
b0010 8
#137
1#
b10 6
b10 7
b00000000000000000000000000000001 :
#138
0#
1%
b11000011 &
0(
b10011000 )
0*
1+
b01000111 ,
1.
b01000010 /
01
02
b00000000 3
b00 4
b0000 5
b1101 8
#139
1#
#140
0#
0%
b11101100 &
b00010011 )
b10000110 ,
1-
b10000100 /
11
12
b10000110 3
b10 4
b0100 5
b1100 8
#141
1#
0-
10
b10000100 3
b11 4
b1000 5
b11 6
b11 7
b00000000000000000000000000000010 :
#142
0#
1%
b00001000 &
b00001001 )
b10101001 ,
b11000010 /
b11000010 3
b1101 8
#143
1#
1'
00
b00001000 3
b00 4
b0001 5
b00 6
b00 7
b00000000000000000000000000000011 :
#144
0#
b10011000 &
0'
1(
b10001101 )
0+
b10111111 ,
b11010000 /
01
02
b00000000 3
b0000 5
b1011 8
#145
1#
#146
0#
0%
b01000111 &
0(
b00111001 )
1+
b11100011 ,
0.
b10011100 /
b0100 8
#147
1#
#148
0#
b10100101 &
1(
b00101111 )
1*
b10111100 ,
1.
b01101011 /
11
12
b00101111 3
b01 4
b0010 5
b1110 8
#149
1#
0*
1-
b10111100 3
b10 4
b0100 5
b10 6
b10 7
b00000000000000000000000000000001 :
#150
0#
1%
b10001111 &
b01111010 )
0+
b10110100 ,
0-
b10101100 /
01
02
b00000000 3
b00 4
b0000 5
b1011 8
#151
1#
#152
0#
b01000101 &
1'
b00111101 )
b11100001 ,
0.
b01110000 /
11
12
b01000101 3
b0001 5
b0011 8
#153
1#
0'
1*
b00111101 3
b01 4
b0010 5
b01 6
b01 7
b00000000000000000000000000000000 :
#154
0#
0%
b01101100 &
b00100000 )
0*
b10101111 ,
b01111001 /
01
02
b00000000 3
b00 4
b0000 5
b0010 8
#155
1#
#156
0#
1%
b11011010 &
b11111100 )
1+
b11000110 ,
b11110000 /
b0111 8
#157
1#
#158
0#
b01010000 &
b10101001 )
1*
b00110001 ,
1.
b10001010 /
11
12
b10101001 3
b01 4
b0010 5
b1111 8
#159
1#
0*
1-
b00110001 3
b10 4
b0100 5
b10 6
b10 7
b00000000000000000000000000000001 :
#160
0#
0%
b00110010 &
b00110001 )
b10011100 ,
0.
b10001100 /
b10011100 3
b0110 8
#161
1#
1*
0-
b00110001 3
b01 4
b0010 5
b11 6
b11 7
b00000000000000000000000000000010 :
#162
0#
b01010000 &
b00101010 )
0*
0+
b10111011 ,
1.
b00111000 /
10
b00111000 3
b11 4
b1000 5
b1010 8
#163
1#
1*
00
b00101010 3
b01 4
b0010 5
b00 6
b00 7
b00000000000000000000000000000011 :
#164
0#
1%
b00110100 &
1'
0(
b11110011 )
0*
1+
b11011101 ,
b11100001 /
b00110100 3
b00 4
b0001 5
b1101 8
#165
1#
0'
1-
b11011101 3
b10 4
b0100 5
b01 6
b01 7
b00000000000000000000000000000000 :
#166
0#
0%
b01010110 &
b11111100 )
b10001100 ,
0-
0.
b01000111 /
01
02
b00000000 3
b00 4
b0000 5
b0100 8
#167
1#
#168
0#
1%
b00100010 &
b10000111 )
0+
b10011110 ,
1.
b10110000 /
b1001 8
#169
1#
#170
0#
b11101100 &
1(
b01101100 )
1*
1+
b11110001 ,
0.
b11101101 /
11
12
b01101100 3
b01 4
b0010 5
b0111 8
#171
1#
0*
1-
b11110001 3
b10 4
b0100 5
b10 6
b10 7
b00000000000000000000000000000001 :
#172
0#
b11100000 &
b01001101 )
0+
b10000100 ,
0-
1.
b10001001 /
10
b10001001 3
b11 4
b1000 5
b1011 8
#173
1#
1'
00
b11100000 3
b00 4
b0001 5
b00 6
b00 7
b00000000000000000000000000000011 :
#174
0#
0%
b01001111 &
0'
b10100011 )
1*
b01001010 ,
0.
b00111100 /
b10100011 3
b01 4
b0010 5
b0010 8
#175
1#
b10 6
b10 7
b00000000000000000000000000000001 :
#176
0#
1%
b11000011 &
b11110100 )
0*
1+
b11010001 ,
1-
b01111001 /
b11010001 3
b10 4
b0100 5
b0111 8
#177
1#
1'
0-
b11000011 3
b00 4
b0001 5
b11 6
b11 7
b00000000000000000000000000000010 :
#178
0#
0%
b01111100 &
0'
b00011011 )
b01110101 ,
1.
b01101101 /
10
b01101101 3
b11 4
b1000 5
b1110 8
#179
1#
1*
00
b00011011 3
b01 4
b0010 5
b00 6
b00 7
b00000000000000000000000000000011 :
#180
0#
b11000111 &
b01000000 )
b00010101 ,
b00101001 /
b01000000 3
#181
1#
0*
1-
b00010101 3
b10 4
b0100 5
b10 6
b10 7
b00000000000000000000000000000001 :
#182
0#
1%
b01010000 &
b01111111 )
b00101001 ,
b11111101 /
b00101001 3
b1111 8
#183
1#
0-
10
b11111101 3
b11 4
b1000 5
b11 6
b11 7
b00000000000000000000000000000010 :
#184
0#
0%
b00101010 &
b00100101 )
1*
b01111110 ,
0.
b00111001 /
00
b00100101 3
b01 4
b0010 5
b0110 8
#185
1#
0*
1-
b01111110 3
b10 4
b0100 5
b10 6
b10 7
b00000000000000000000000000000001 :
#186
0#
1%
b00101011 &
b10001110 )
b11010010 ,
1.
b10010000 /
b11010010 3
b1111 8
#187
1#
0-
10
b10010000 3
b11 4
b1000 5
b11 6
b11 7
b00000000000000000000000000000010 :
#188
0#
0%
b11010110 &
b00110010 )
1*
0+
b10111001 ,
0.
b11011111 /
00
b00110010 3
b01 4
b0010 5
b0010 8
#189
1#
b10 6
b10 7
b00000000000000000000000000000001 :
#190
0#
b11010010 &
0(
b11101010 )
0*
b11111010 ,
1.
b11001001 /
01
02
b00000000 3
b00 4
b0000 5
b1000 8
#191
1#
#192
0#
1%
b11010111 &
b11110010 )
b10000110 ,
b00001111 /
10
11
12
b00001111 3
b11 4
b1000 5
b1001 8
#193
1#
1'
00
b11010111 3
b00 4
b0001 5
b00 6
b00 7
b00000000000000000000000000000011 :
#194
0#
b01010100 &
b10110100 )
b01011111 ,
0.
b10001111 /
b01010100 3
b0001 8
#195
1#
b01 6
b01 7
b00000000000000000000000000000000 :
#196
0#
b00101001 &
b00000000 )
b01101110 ,
b10011110 /
b00101001 3
#197
1#
#198
0#
0%
b01110001 &
0'
b11100101 )
1+
b01101000 ,
1.
b00101101 /
01
02
b00000000 3
b0000 5
b1100 8
#199
1#
#200
0#
1%
b10110010 &
1'
b10001010 )
0+
b10011100 ,
0.
b00101010 /
11
12
b10110010 3
b0001 5
b0001 8
#201
1#
#202
0#
b10010111 &
0'
b00100010 )
1+
b00010111 ,
b11101110 /
01
02
b00000000 3
b0000 5
b0101 8
#203
1#
#204
0#
b10110101 &
b01011110 )
b01011100 ,
1-
b01101001 /
11
12
b01011100 3
b10 4
b0100 5
#205
1#
1'
0-
b10110101 3
b00 4
b0001 5
b11 6
b11 7
b00000000000000000000000000000010 :
#206
0#
b10100001 &
0'
1(
b10111000 )
b00001110 ,
1.
b11110000 /
10
b11110000 3
b11 4
b1000 5
b1111 8
#207
1#
1'
00
b10100001 3
b00 4
b0001 5
b00 6
b00 7
b00000000000000000000000000000011 :
#208
0#
b10000100 &
b11010100 )
0+
b00111110 ,
b01100011 /
b10000100 3
b1011 8
#209
1#
0'
1*
b11010100 3
b01 4
b0010 5
b01 6
b01 7
b00000000000000000000000000000000 :
#210
0#
0%
b11001011 &
b11001101 )
b00010010 ,
0.
b01101100 /
b11001101 3
b0010 8
#211
1#
b10 6
b10 7
b00000000000000000000000000000001 :
#212
0#
1%
b00001101 &
b00001111 )
0*
1+
b00001010 ,
1-
1.
b01010101 /
b00001010 3
b10 4
b0100 5
b1111 8
#213
1#
0-
10
b01010101 3
b11 4
b1000 5
b11 6
b11 7
b00000000000000000000000000000010 :
#214
0#
0%
b00101111 &
b10000101 )
0+
b10110011 ,
b11000111 /
b11000111 3
b1010 8
#215
1#
1*
00
b10000101 3
b01 4
b0010 5
b00 6
b00 7
b00000000000000000000000000000011 :
#216
0#
1%
b10010011 &
1'
0(
b01100001 )
0*
1+
b01001100 ,
b00111100 /
b10010011 3
b00 4
b0001 5
b1101 8
#217
1#
0'
1-
b01001100 3
b10 4
b0100 5
b01 6
b01 7
b00000000000000000000000000000000 :
#218
0#
b11100101 &
1(
b10001100 )
b10000111 ,
0-
b10010110 /
01
02
b00000000 3
b00 4
b0000 5
b1111 8
#219
1#
#220
0#
b10101101 &
0(
b10001001 )
0+
b01000000 ,
b00111110 /
b1001 8
#221
1#
#222
0#
b10110110 &
b10111111 )
1+
b00000001 ,
1-
0.
b10010011 /
11
12
b00000001 3
b10 4
b0100 5
b0101 8
#223
1#
1'
0-
b10110110 3
b00 4
b0001 5
b11 6
b11 7
b00000000000000000000000000000010 :
#224
0#
0%
b10000011 &
0'
1(
b01100101 )
b01110111 ,
1.
b11010001 /
10
b11010001 3
b11 4
b1000 5
b1110 8
#225
1#
1*
00
b01100101 3
b01 4
b0010 5
b00 6
b00 7
b00000000000000000000000000000011 :
#226
0#
1%
b00110110 &
b00101111 )
0*
b11101100 ,
b01100111 /
01
02
b00000000 3
b00 4
b0000 5
b1111 8
#227
1#
#228
0#
0%
b00010100 &
0(
b10100000 )
b01000111 ,
1-
b00101010 /
11
12
b01000111 3
b10 4
b0100 5
b1100 8
#229
1#
0-
10
b00101010 3
b11 4
b1000 5
b11 6
b11 7
b00000000000000000000000000000010 :
#230
0#
b01101010 &
b10000111 )
b11001000 ,
1-
0.
b11100011 /
00
b11001000 3
b10 4
b0100 5
b0100 8
#231
1#
#232
0#
1%
b10101110 &
b01100110 )
b11001111 ,
0-
1.
b10111110 /
10
b10111110 3
b11 4
b1000 5
b1101 8
#233
1#
1'
00
b10101110 3
b00 4
b0001 5
b00 6
b00 7
b00000000000000000000000000000011 :
#234
0#
0%
b00100100 &
0'
1(
b11110010 )
1*
b00110111 ,
b00101000 /
b11110010 3
b01 4
b0010 5
b1110 8
#235
1#
0*
1-
b00110111 3
b10 4
b0100 5
b10 6
b10 7
b00000000000000000000000000000001 :
#236
0#
1%
b01000010 &
0(
b01001000 )
b11001010 ,
0-
b00101111 /
01
02
b00000000 3
b00 4
b0000 5
b1101 8
#237
1#
#238
0#
b00110010 &
b00001000 )
b11010000 ,
b00101010 /
#239
1#
#240
0#
0%
b10011000 &
1(
b10100001 )
1*
0+
b00010111 ,
0.
b01010010 /
11
12
b10100001 3
b01 4
b0010 5
b0010 8
#241
1#
#242
0#
b11100100 &
0(
b10011001 )
0*
b00000011 ,
b00010011 /
02
b00000000 3
b00 4
b0000 5
b0000 8
#243
1#
#244
0#
b10100101 &
b10011111 )
1+
b11001011 ,
1.
b00011111 /
01
b1100 8
#245
1#
#246
0#
b01111001 &
1(
b11101111 )
b00000010 ,
0.
b10110100 /
b0110 8
#247
1#
#248
0#
1%
b10000011 &
b11111100 )
b11100111 ,
1-
b10110000 /
11
12
b11100111 3
b10 4
b0100 5
b0111 8
#249
1#
1'
0-
b10000011 3
b00 4
b0001 5
b11 6
b11 7
b00000000000000000000000000000010 :
#250
0#
0%
b10100000 &
0'
b00111001 )
0+
b10111111 ,
1.
b00110110 /
10
b00110110 3
b11 4
b1000 5
b1010 8
#251
1#
1*
00
b00111001 3
b01 4
b0010 5
b00 6
b00 7
b00000000000000000000000000000011 :
#252
0#
1%
b11010100 &
0(
b11100001 )
0*
1+
b11011101 ,
0.
b00001101 /
01
02
b00000000 3
b00 4
b0000 5
b0101 8
#253
1#
#254
0#
0%
b00110001 &
1(
b10111000 )
1*
0+
b01011101 ,
1.
b01011101 /
11
12
b10111000 3
b01 4
b0010 5
b1010 8
#255
1#
0*
10
b01011101 3
b11 4
b1000 5
b10 6
b10 7
b00000000000000000000000000000001 :
#256
0#
1%
b10010000 &
0(
b10000100 )
b00000100 ,
b11110011 /
b11110011 3
b1001 8
#257
1#
1'
00
b10010000 3
b00 4
b0001 5
b00 6
b00 7
b00000000000000000000000000000011 :
#258
0#
b11100001 &
b11111101 )
1+
b11111011 ,
b00111100 /
b11100001 3
b1101 8
#259
1#
0'
1-
b11111011 3
b10 4
b0100 5
b01 6
b01 7
b00000000000000000000000000000000 :
#260
0#
b10100001 &
1(
b10100110 )
1*
0+
b10011100 ,
0-
0.
b11000001 /
b10100110 3
b01 4
b0010 5
b0011 8
#261
1#
1'
0*
b10100001 3
b00 4
b0001 5
b10 6
b10 7
b00000000000000000000000000000001 :
#262
0#
b11010101 &
0'
b11111001 )
1+
b00101010 ,
b01001100 /
01
02
b00000000 3
b0000 5
b0111 8
#263
1#
#264
0#
b11101010 &
0(
b01100001 )
0+
b11011010 ,
1.
b01111011 /
10
11
12
b01111011 3
b11 4
b1000 5
b1001 8
#265
1#
1'
00
b11101010 3
b00 4
b0001 5
b00 6
b00 7
b00000000000000000000000000000011 :
