sv_common_ips/08_constrained_like_generation/top.sv
// top.sv - Lesson 08
//
// Focus:
//  - Same FIFO-style DUT boundary as Lesson 07
//  - Assertions at the DUT boundary to verify stimulus constraints
//
// This lets C++ do the constrained-like generation while SV still enforces
// protocol/data rules at the interface.

module top (
    input  logic clk,
    input  logic rst_n,

    input  logic       in_valid,
    input  logic [7:0] in_data,
    output logic       in_ready,

    input  logic       out_ready,
    output logic       out_valid,
    output logic [7:0] out_data,

    output logic [3:0] count
);
    localparam int DEPTH = 8;
    localparam int AW = $clog2(DEPTH);

    logic [7:0] mem [0:DEPTH-1];
    logic [AW-1:0] wptr;
    logic [AW-1:0] rptr;
    logic [AW:0] used;

    logic push;
    logic pop;

    assign in_ready = (int'(used) < DEPTH);
    assign out_valid = (used != 0);
    assign out_data = mem[rptr];
    assign count = used[3:0];

    assign push = in_valid && in_ready;
    assign pop = out_ready && out_valid;

    always_ff @(posedge clk) begin
        if (!rst_n) begin
            wptr <= '0;
            rptr <= '0;
            used <= '0;
        end else begin
            if (push) begin
                mem[wptr] <= in_data;
                wptr <= wptr + 1'b1;
            end

            if (pop) begin
                rptr <= rptr + 1'b1;
            end

            unique case ({push, pop})
                2'b10: used <= used + 1'b1;
                2'b01: used <= used - 1'b1;
                default: used <= used;
            endcase
        end
    end

    // Boundary checks:
    //  - no push when full
    //  - no pop when empty
    //  - pushed data obeys the C++ generator's constraints
    always_ff @(posedge clk) begin
        if (rst_n) begin
            assert (!(in_valid && !in_ready))
                else $fatal(1, "Constraint violated: push attempted while full");

            assert (!(out_ready && !out_valid))
                else $fatal(1, "Constraint violated: pop attempted while empty");

            if (push) begin
                assert (in_data[0] == 1'b1)
                    else $fatal(1, "Constraint violated: pushed data must be odd");

                assert (in_data != 8'hFF)
                    else $fatal(1, "Constraint violated: pushed data must not be 0xFF");

                assert (in_data[7:4] != 4'hF)
                    else $fatal(1, "Constraint violated: pushed data upper nibble must not be 0xF");
            end
        end
    end

endmodule

sv_common_ips/08_constrained_like_generation/waveform.vcd
$version Generated by VerilatedVcd $end
$timescale 1ps $end
 $scope module TOP $end
  $var wire 1 . clk $end
  $var wire 1 / rst_n $end
  $var wire 1 0 in_valid $end
  $var wire 8 1 in_data [7:0] $end
  $var wire 1 2 in_ready $end
  $var wire 1 3 out_ready $end
  $var wire 1 4 out_valid $end
  $var wire 8 5 out_data [7:0] $end
  $var wire 4 6 count [3:0] $end
  $scope module top $end
   $var wire 1 . clk $end
   $var wire 1 / rst_n $end
   $var wire 1 0 in_valid $end
   $var wire 8 1 in_data [7:0] $end
   $var wire 1 2 in_ready $end
   $var wire 1 3 out_ready $end
   $var wire 1 4 out_valid $end
   $var wire 8 5 out_data [7:0] $end
   $var wire 4 6 count [3:0] $end
   $var wire 32 9 DEPTH [31:0] $end
   $var wire 32 : AW [31:0] $end
   $var wire 8 # mem[0] [7:0] $end
   $var wire 8 $ mem[1] [7:0] $end
   $var wire 8 % mem[2] [7:0] $end
   $var wire 8 & mem[3] [7:0] $end
   $var wire 8 ' mem[4] [7:0] $end
   $var wire 8 ( mem[5] [7:0] $end
   $var wire 8 ) mem[6] [7:0] $end
   $var wire 8 * mem[7] [7:0] $end
   $var wire 3 + wptr [2:0] $end
   $var wire 3 , rptr [2:0] $end
   $var wire 4 - used [3:0] $end
   $var wire 1 7 push $end
   $var wire 1 8 pop $end
  $upscope $end
 $upscope $end
$enddefinitions $end


#0
b00000000 #
b00000000 $
b00000000 %
b00000000 &
b00000000 '
b00000000 (
b00000000 )
b00000000 *
b000 +
b000 ,
b0000 -
0.
0/
00
b00000000 1
12
03
04
b00000000 5
b0000 6
07
08
b00000000000000000000000000001000 9
b00000000000000000000000000000011 :
#1
1.
#2
0.
#3
1.
#4
0.
#5
1.
#6
0.
#7
1.
#8
0.
#9
1.
#10
0.
1/
b10111110 1
#11
1.
#12
0.
10
b10100001 1
17
#13
b10100001 #
b001 +
b0001 -
1.
14
b10100001 5
b0001 6
#14
0.
b01000101 1
13
18
#15
b01000101 $
b010 +
b001 ,
1.
b01000101 5
#16
0.
b11010111 1
03
08
#17
b11010111 %
b011 +
b0010 -
1.
b0010 6
#18
0.
b01000101 1
13
18
#19
b01000101 &
b100 +
b010 ,
1.
b11010111 5
#20
0.
b00101111 1
#21
b00101111 '
b101 +
b011 ,
1.
b01000101 5
#22
0.
00
b11111000 1
07
#23
b100 ,
b0001 -
1.
b00101111 5
b0001 6
#24
0.
10
b11011011 1
17
#25
b11011011 (
b110 +
b101 ,
1.
b11011011 5
#26
0.
b01110001 1
#27
b01110001 )
b111 +
b110 ,
1.
b01110001 5
#28
0.
b01011011 1
#29
b01011011 *
b000 +
b111 ,
1.
b01011011 5
#30
0.
b11011101 1
03
08
#31
b11011101 #
b001 +
b0010 -
1.
b0010 6
#32
0.
00
b11110000 1
13
07
18
#33
b000 ,
b0001 -
1.
b11011101 5
b0001 6
#34
0.
10
b11010001 1
03
17
08
#35
b11010001 $
b010 +
b0010 -
1.
b0010 6
#36
0.
b10010001 1
13
18
#37
b10010001 %
b011 +
b001 ,
1.
b11010001 5
#38
0.
b10100001 1
#39
b10100001 &
b100 +
b010 ,
1.
b10010001 5
#40
0.
b01000111 1
03
08
#41
b01000111 '
b101 +
b0011 -
1.
b0011 6
#42
0.
b00011111 1
#43
b00011111 (
b110 +
b0100 -
1.
b0100 6
#44
0.
00
b10111011 1
07
#45
1.
#46
0.
b10110001 1
#47
1.
#48
0.
10
b01101101 1
13
17
18
#49
b01101101 )
b111 +
b011 ,
1.
b10100001 5
#50
0.
00
b01010011 1
03
07
08
#51
1.
#52
0.
10
b00100011 1
13
17
18
#53
b00100011 *
b000 +
b100 ,
1.
b01000111 5
#54
0.
b00101011 1
#55
b00101011 #
b001 +
b101 ,
1.
b00011111 5
#56
0.
00
b00101001 1
07
#57
b110 ,
b0011 -
1.
b01101101 5
b0011 6
#58
0.
10
b00011011 1
17
#59
b00011011 $
b010 +
b111 ,
1.
b00100011 5
#60
0.
b01000011 1
#61
b01000011 %
b011 +
b000 ,
1.
b00101011 5
#62
0.
00
b00111101 1
07
#63
b001 ,
b0010 -
1.
b00011011 5
b0010 6
#64
0.
10
b00101111 1
17
#65
b00101111 &
b100 +
b010 ,
1.
b01000011 5
#66
0.
b11101001 1
#67
b11101001 '
b101 +
b011 ,
1.
b00101111 5
#68
0.
00
b11110110 1
07
#69
b100 ,
b0001 -
1.
b11101001 5
b0001 6
#70
0.
b10101101 1
#71
b101 ,
b0000 -
1.
04
b00011111 5
b0000 6
08
#72
0.
10
b01010001 1
03
17
#73
b01010001 (
b110 +
b0001 -
1.
14
b01010001 5
b0001 6
#74
0.
b10010111 1
#75
b10010111 )
b111 +
b0010 -
1.
b0010 6
#76
0.
b10000111 1
#77
b10000111 *
b000 +
b0011 -
1.
b0011 6
#78
0.
b01011001 1
13
18
#79
b01011001 #
b001 +
b110 ,
1.
b10010111 5
#80
0.
00
b11100011 1
03
07
08
#81
1.
#82
0.
b00010110 1
13
18
#83
b111 ,
b0010 -
1.
b10000111 5
b0010 6
#84
0.
b10001010 1
#85
b000 ,
b0001 -
1.
b01011001 5
b0001 6
#86
0.
b01110101 1
03
08
#87
1.
#88
0.
b00110101 1
13
18
#89
b001 ,
b0000 -
1.
04
b00011011 5
b0000 6
08
#90
0.
10
b00010111 1
03
17
#91
b00010111 $
b010 +
b0001 -
1.
14
b00010111 5
b0001 6
#92
0.
00
b11100110 1
07
#93
1.
#94
0.
10
b10010101 1
17
#95
b10010101 %
b011 +
b0010 -
1.
b0010 6
#96
0.
00
b10000011 1
13
07
18
#97
b010 ,
b0001 -
1.
b10010101 5
b0001 6
#98
0.
b00000111 1
03
08
#99
1.
#100
0.
10
b11000101 1
13
17
18
#101
b11000101 &
b100 +
b011 ,
1.
b11000101 5
#102
0.
00
b11100011 1
03
07
08
#103
1.
#104
0.
10
b11000001 1
13
17
18
#105
b11000001 '
b101 +
b100 ,
1.
b11000001 5
#106
0.
b01110011 1
#107
b01110011 (
b110 +
b101 ,
1.
b01110011 5
#108
0.
b01100011 1
#109
b01100011 )
b111 +
b110 ,
1.
b01100011 5
#110
0.
00
b00000000 1
03
07
08
#111
1.
#112
0.
b00100100 1
13
18
#113
b111 ,
b0000 -
1.
04
b10000111 5
b0000 6
08
#114
0.
b11100101 1
03
#115
1.
#116
0.
10
b01011001 1
17
#117
b01011001 *
b000 +
b0001 -
1.
14
b01011001 5
b0001 6
#118
0.
00
b11101000 1
13
07
18
#119
b000 ,
b0000 -
1.
04
b0000 6
08
#120
0.
10
b11010001 1
03
17
#121
b11010001 #
b001 +
b0001 -
1.
14
b11010001 5
b0001 6
#122
0.
00
b01110011 1
13
07
18
#123
b001 ,
b0000 -
1.
04
b00010111 5
b0000 6
08
#124
0.
b01100100 1
03
#125
1.
#126
0.
10
b01100001 1
17
#127
b01100001 $
b010 +
b0001 -
1.
14
b01100001 5
b0001 6
#128
0.
00
b01000111 1
13
07
18
#129
b010 ,
b0000 -
1.
04
b10010101 5
b0000 6
08
#130
0.
b00110010 1
03
#131
1.
#132
0.
10
b10110111 1
17
#133
b10110111 %
b011 +
b0001 -
1.
14
b10110111 5
b0001 6
#134
0.
b10111101 1
13
18
#135
b10111101 &
b100 +
b011 ,
1.
b10111101 5
#136
0.
00
b01111110 1
07
#137
b100 ,
b0000 -
1.
04
b11000001 5
b0000 6
08
#138
0.
b10001110 1
03
#139
1.
#140
0.
b00001010 1
#141
1.
#142
0.
b01111010 1
#143
1.
#144
0.
b00011110 1
#145
1.
#146
0.
10
b01001111 1
17
#147
b01001111 '
b101 +
b0001 -
1.
14
b01001111 5
b0001 6
#148
0.
00
b11101011 1
13
07
18
#149
b101 ,
b0000 -
1.
04
b01110011 5
b0000 6
08
#150
0.
b11111001 1
03
#151
1.
#152
0.
b01101011 1
#153
1.
#154
0.
10
b00000101 1
17
#155
b00000101 (
b110 +
b0001 -
1.
14
b00000101 5
b0001 6
#156
0.
b01101001 1
#157
b01101001 )
b111 +
b0010 -
1.
b0010 6
#158
0.
00
b11111111 1
07
#159
1.
#160
0.
b01011011 1
#161
1.
#162
0.
10
b10001101 1
13
17
18
#163
b10001101 *
b000 +
b110 ,
1.
b01101001 5
#164
0.
00
b00010110 1
03
07
08
#165
1.
#166
0.
10
b01110111 1
13
17
18
#167
b01110111 #
b001 +
b111 ,
1.
b10001101 5
#168
0.
00
b10011011 1
07
#169
b000 ,
b0001 -
1.
b01110111 5
b0001 6
#170
0.
10
b00110111 1
17
#171
b00110111 $
b010 +
b001 ,
1.
b00110111 5
#172
0.
b10110111 1
03
08
#173
b011 +
b0010 -
1.
b0010 6
#174
0.
00
b01110000 1
13
07
18
#175
b010 ,
b0001 -
1.
b10110111 5
b0001 6
#176
0.
10
b00110011 1
17
#177
b00110011 &
b100 +
b011 ,
1.
b00110011 5
#178
0.
00
b01100100 1
07
#179
b100 ,
b0000 -
1.
04
b01001111 5
b0000 6
08
#180
0.
b11011011 1
03
#181
1.
#182
0.
b11100001 1
#183
1.
#184
0.
b01110101 1
#185
1.
#186
0.
b01110010 1
#187
1.
#188
0.
b00000001 1
#189
1.
#190
0.
b00100001 1
#191
1.
#192
0.
b11101101 1
#193
1.
#194
0.
10
b01100001 1
17
#195
b01100001 '
b101 +
b0001 -
1.
14
b01100001 5
b0001 6
#196
0.
00
b11010101 1
13
07
18
#197
b101 ,
b0000 -
1.
04
b00000101 5
b0000 6
08
#198
0.
10
b00000101 1
03
17
#199
b110 +
b0001 -
1.
14
b0001 6
#200
0.
b11011001 1
#201
b11011001 )
b111 +
b0010 -
1.
b0010 6
#202
0.
00
b00101010 1
13
07
18
#203
b110 ,
b0001 -
1.
b11011001 5
b0001 6
#204
0.
10
b10110001 1
17
#205
b10110001 *
b000 +
b111 ,
1.
b10110001 5
#206
0.
b01000011 1
03
08
#207
b01000011 #
b001 +
b0010 -
1.
b0010 6
#208
0.
b00010011 1
13
18
#209
b00010011 $
b010 +
b000 ,
1.
b01000011 5
#210
0.
b00100101 1
03
08
#211
b00100101 %
b011 +
b0011 -
1.
b0011 6
#212
0.
b01001001 1
13
18
#213
b01001001 &
b100 +
b001 ,
1.
b00010011 5
#214
0.
b00111001 1
#215
b00111001 '
b101 +
b010 ,
1.
b00100101 5
#216
0.
b11000011 1
#217
b11000011 (
b110 +
b011 ,
1.
b01001001 5
#218
0.
00
b00011010 1
07
#219
b100 ,
b0010 -
1.
b00111001 5
b0010 6
#220
0.
10
b10101011 1
17
#221
b10101011 )
b111 +
b101 ,
1.
b11000011 5
#222
0.
00
b00001110 1
03
07
08
#223
1.
#224
0.
10
b00101001 1
17
#225
b00101001 *
b000 +
b0011 -
1.
b0011 6
#226
0.
00
b11001000 1
07
#227
1.
#228
0.
b00101011 1
13
18
#229
b110 ,
b0010 -
1.
b10101011 5
b0010 6
#230
0.
10
b01111111 1
17
#231
b01111111 #
b001 +
b111 ,
1.
b00101001 5
#232
0.
b10101001 1
03
08
#233
b10101001 $
b010 +
b0011 -
1.
b0011 6
#234
0.
00
b10101100 1
13
07
18
#235
b000 ,
b0010 -
1.
b01111111 5
b0010 6
#236
0.
b11110100 1
#237
b001 ,
b0001 -
1.
b10101001 5
b0001 6
#238
0.
10
b00001001 1
17
#239
b00001001 %
b011 +
b010 ,
1.
b00001001 5
#240
0.
00
b10010000 1
07
#241
b011 ,
b0000 -
1.
04
b01001001 5
b0000 6
08
#242
0.
b10000000 1
03
#243
1.
#244
0.
b10111111 1
#245
1.
#246
0.
10
b01110001 1
17
#247
b01110001 &
b100 +
b0001 -
1.
14
b01110001 5
b0001 6
#248
0.
00
b01001010 1
13
07
18
#249
b100 ,
b0000 -
1.
04
b00111001 5
b0000 6
08
#250
0.
b11101000 1
03
#251
1.
#252
0.
10
b11011101 1
17
#253
b11011101 '
b101 +
b0001 -
1.
14
b11011101 5
b0001 6
#254
0.
b11011001 1
13
18
#255
b11011001 (
b110 +
b101 ,
1.
b11011001 5
#256
0.
b00100101 1
#257
b00100101 )
b111 +
b110 ,
1.
b00100101 5
#258
0.
00
b01010011 1
07
#259
b111 ,
b0000 -
1.
04
b00101001 5
b0000 6
08
#260
0.
b01011111 1
03
#261
1.
#262
0.
b00001100 1
#263
1.
#264
0.
10
b01100111 1
17
#265
b01100111 *
b000 +
b0001 -
1.
14
b01100111 5
b0001 6
#266
0.
b11010111 1
#267
b11010111 #
b001 +
b0010 -
1.
b0010 6
#268
0.
00
b11010100 1
07
#269
1.
#270
0.
b11110011 1
#271
1.
#272
0.
10
b01011011 1
13
17
18
#273
b01011011 $
b010 +
b000 ,
1.
b11010111 5
#274
0.
00
b01010101 1
03
07
08
#275
1.
#276
0.
10
b00001101 1
13
17
18
#277
b00001101 %
b011 +
b001 ,
1.
b01011011 5
#278
0.
00
b11000100 1
03
07
08
#279
1.
#280
0.
b01100110 1
13
18
#281
b010 ,
b0001 -
1.
b00001101 5
b0001 6
#282
0.
b00000110 1
#283
b011 ,
b0000 -
1.
04
b01110001 5
b0000 6
08
#284
0.
10
b00110101 1
03
17
#285
b00110101 &
b100 +
b0001 -
1.
14
b00110101 5
b0001 6
#286
0.
b01100001 1
#287
b01100001 '
b101 +
b0010 -
1.
b0010 6
#288
0.
b10001001 1
13
18
#289
b10001001 (
b110 +
b100 ,
1.
b01100001 5
#290
0.
b01110001 1
03
08
#291
b01110001 )
b111 +
b0011 -
1.
b0011 6
#292
0.
00
b00000000 1
07
#293
1.
#294
0.
10
b01110111 1
13
17
18
#295
b01110111 *
b000 +
b101 ,
1.
b10001001 5
#296
0.
b10110001 1
#297
b10110001 #
b001 +
b110 ,
1.
b01110001 5
#298
0.
00
b11011101 1
03
07
08
#299
1.
#300
0.
b11001101 1
13
18
#301
b111 ,
b0010 -
1.
b01110111 5
b0010 6
#302
0.
b11001011 1
#303
b000 ,
b0001 -
1.
b10110001 5
b0001 6
#304
0.
b10101110 1
#305
b001 ,
b0000 -
1.
04
b01011011 5
b0000 6
08
#306
0.
10
b10110001 1
03
17
#307
b10110001 $
b010 +
b0001 -
1.
14
b10110001 5
b0001 6
#308
0.
00
b01111000 1
07
#309
1.
#310
0.
b11111100 1
#311
1.
#312
0.
b00101010 1
#313
1.
#314
0.
b01111111 1
13
18
#315
b010 ,
b0000 -
1.
04
b00001101 5
b0000 6
08
#316
0.
10
b10001001 1
03
17
#317
b10001001 %
b011 +
b0001 -
1.
14
b10001001 5
b0001 6
#318
0.
b00001001 1
#319
b00001001 &
b100 +
b0010 -
1.
b0010 6
#320
0.
b01010101 1
#321
b01010101 '
b101 +
b0011 -
1.
b0011 6
#322
0.
b10011101 1
13
18
#323
b10011101 (
b110 +
b011 ,
1.
b00001001 5
#324
0.
00
b11101101 1
07
#325
b100 ,
b0010 -
1.
b01010101 5
b0010 6
#326
0.
b10011110 1
#327
b101 ,
b0001 -
1.
b10011101 5
b0001 6
#328
0.
b10110111 1
#329
b110 ,
b0000 -
1.
04
b01110001 5
b0000 6
08
#330
0.
10
b00100011 1
03
17
#331
b00100011 )
b111 +
b0001 -
1.
14
b00100011 5
b0001 6
#332
0.
b10111001 1
#333
b10111001 *
b000 +
b0010 -
1.
b0010 6
#334
0.
b11000011 1
#335
b11000011 #
b001 +
b0011 -
1.
b0011 6
#336
0.
b00000001 1
#337
b00000001 $
b010 +
b0100 -
1.
b0100 6
#338
0.
00
b10000111 1
07
#339
1.
#340
0.
10
b00101011 1
17
#341
b00101011 %
b011 +
b0101 -
1.
b0101 6
#342
0.
00
b11101101 1
13
07
18
#343
b111 ,
b0100 -
1.
b10111001 5
b0100 6
#344
0.
10
b01101011 1
03
17
08
#345
b01101011 &
b100 +
b0101 -
1.
b0101 6
#346
0.
00
b00101110 1
13
07
18
#347
b000 ,
b0100 -
1.
b11000011 5
b0100 6
#348
0.
10
b10101101 1
03
17
08
#349
b10101101 '
b101 +
b0101 -
1.
b0101 6
#350
0.
00
b01110101 1
07
#351
1.
#352
0.
b00011101 1
#353
1.
#354
0.
b10010000 1
13
18
#355
b001 ,
b0100 -
1.
b00000001 5
b0100 6
#356
0.
10
b00110111 1
03
17
08
#357
b00110111 (
b110 +
b0101 -
1.
b0101 6
#358
0.
00
b11110100 1
07
#359
1.
#360
0.
b00100011 1
#361
1.
#362
0.
b00110101 1
#363
1.
#364
0.
10
b00001011 1
13
17
18
#365
b00001011 )
b111 +
b010 ,
1.
b00101011 5
#366
0.
b10000011 1
#367
b10000011 *
b000 +
b011 ,
1.
b01101011 5
#368
0.
00
b00100011 1
07
#369
b100 ,
b0100 -
1.
b10101101 5
b0100 6
#370
0.
10
b00111111 1
03
17
08
#371
b00111111 #
b001 +
b0101 -
1.
b0101 6
#372
0.
00
b00000000 1
13
07
18
#373
b101 ,
b0100 -
1.
b00110111 5
b0100 6
#374
0.
b01000000 1
03
08
#375
1.
#376
0.
10
b10001111 1
17
#377
b10001111 $
b010 +
b0101 -
1.
b0101 6
#378
0.
00
b01001101 1
13
07
18
#379
b110 ,
b0100 -
1.
b00001011 5
b0100 6
#380
0.
b00100111 1
03
08
#381
1.
#382
0.
10
b11000001 1
13
17
18
#383
b11000001 %
b011 +
b111 ,
1.
b10000011 5
#384
0.
00
b11011000 1
07
#385
b000 ,
b0011 -
1.
b00111111 5
b0011 6
#386
0.
b01110000 1
03
08
#387
1.
#388
0.
10
b10101101 1
17
#389
b10101101 &
b100 +
b0100 -
1.
b0100 6
#390
0.
b00100011 1
13
18
#391
b00100011 '
b101 +
b001 ,
1.
b10001111 5
#392
0.
00
b00100000 1
03
07
08
#393
1.
#394
0.
b10101100 1
13
18
#395
b010 ,
b0011 -
1.
b11000001 5
b0011 6
#396
0.
b01100101 1
#397
b011 ,
b0010 -
1.
b10101101 5
b0010 6
#398
0.
10
b10111001 1
03
17
08
#399
b10111001 (
b110 +
b0011 -
1.
b0011 6
#400
0.
b01011001 1
#401
b01011001 )
b111 +
b0100 -
1.
b0100 6
#402
0.
00
b00110000 1
07
#403
1.
#404
0.
b11101000 1
13
18
#405
b100 ,
b0011 -
1.
b00100011 5
b0011 6
#406
0.
b01011001 1
#407
b101 ,
b0010 -
1.
b10111001 5
b0010 6
#408
0.
10
b01101011 1
17
#409
b01101011 *
b000 +
b110 ,
1.
b01011001 5
#410
0.
00
b00100011 1
07
#411
b111 ,
b0001 -
1.
b01101011 5
b0001 6
#412
0.
10
b11100011 1
03
17
08
#413
b11100011 #
b001 +
b0010 -
1.
b0010 6
#414
0.
b10000001 1
13
18
#415
b10000001 $
b010 +
b000 ,
1.
b11100011 5
#416
0.
b00000011 1
03
08
#417
b00000011 %
b011 +
b0011 -
1.
b0011 6
#418
0.
b10110011 1
13
18
#419
b10110011 &
b100 +
b001 ,
1.
b10000001 5
#420
0.
00
b10000100 1
07
#421
b010 ,
b0010 -
1.
b00000011 5
b0010 6
#422
0.
b10001011 1
#423
b011 ,
b0001 -
1.
b10110011 5
b0001 6
#424
0.
b00100010 1
#425
b100 ,
b0000 -
1.
04
b00100011 5
b0000 6
08
#426
0.
10
b10010101 1
03
17
#427
b10010101 '
b101 +
b0001 -
1.
14
b10010101 5
b0001 6
#428
0.
00
b10011111 1
07
#429
1.
#430
0.
10
b10110101 1
13
17
18
#431
b10110101 (
b110 +
b101 ,
1.
b10110101 5
#432
0.
00
b00110011 1
03
07
08
#433
1.
#434
0.
b11011001 1
#435
1.
#436
0.
10
b00001011 1
13
17
18
#437
b00001011 )
b111 +
b110 ,
1.
b00001011 5
#438
0.
00
b01010010 1
07
#439
b111 ,
b0000 -
1.
04
b01101011 5
b0000 6
08
#440
0.
b11111111 1
03
#441
1.
#442
0.
10
b11011101 1
17
#443
b11011101 *
b000 +
b0001 -
1.
14
b11011101 5
b0001 6
#444
0.
00
b10111000 1
13
07
18
#445
b000 ,
b0000 -
1.
04
b11100011 5
b0000 6
08
#446
0.
10
b00101111 1
03
17
#447
b00101111 #
b001 +
b0001 -
1.
14
b00101111 5
b0001 6
#448
0.
b01110101 1
13
18
#449
b01110101 $
b010 +
b001 ,
1.
b01110101 5
#450
0.
b11001101 1
03
08
#451
b11001101 %
b011 +
b0010 -
1.
b0010 6
#452
0.
b00100011 1
#453
b00100011 &
b100 +
b0011 -
1.
b0011 6
#454
0.
00
b01110101 1
13
07
18
#455
b010 ,
b0010 -
1.
b11001101 5
b0010 6
#456
0.
10
b10011011 1
03
17
08
#457
b10011011 '
b101 +
b0011 -
1.
b0011 6
#458
0.
b01011011 1
13
18
#459
b01011011 (
b110 +
b011 ,
1.
b00100011 5
#460
0.
b11011101 1
03
08
#461
b11011101 )
b111 +
b0100 -
1.
b0100 6
#462
0.
b00111101 1
13
18
#463
b00111101 *
b000 +
b100 ,
1.
b10011011 5
#464
0.
b10111011 1
#465
b10111011 #
b001 +
b101 ,
1.
b01011011 5
#466
0.
b01110011 1
03
08
#467
b01110011 $
b010 +
b0101 -
1.
b0101 6
#468
0.
00
b01111010 1
07
#469
1.
#470
0.
b10011100 1
#471
1.
#472
0.
b01010111 1
13
18
#473
b110 ,
b0100 -
1.
b11011101 5
b0100 6
#474
0.
10
b00110111 1
17
#475
b00110111 %
b011 +
b111 ,
1.
b00111101 5
#476
0.
00
b01101111 1
03
07
08
#477
1.
#478
0.
b10010010 1
#479
1.
#480
0.
10
b01100011 1
17
#481
b01100011 &
b100 +
b0101 -
1.
b0101 6
#482
0.
b10110101 1
#483
b10110101 '
b101 +
b0110 -
1.
b0110 6
#484
0.
00
b11101111 1
07
#485
1.
#486
0.
b10101110 1
13
18
#487
b000 ,
b0101 -
1.
b10111011 5
b0101 6
#488
0.
b01110110 1
03
08
#489
1.
#490
0.
b00000000 1
13
18
#491
b001 ,
b0100 -
1.
b01110011 5
b0100 6
#492
0.
#493
b010 ,
b0011 -
1.
b00110111 5
b0011 6
#494
0.
#495
b011 ,
b0010 -
1.
b01100011 5
b0010 6
#496
0.
#497
b100 ,
b0001 -
1.
b10110101 5
b0001 6
#498
0.
#499
b101 ,
b0000 -
1.
04
b01011011 5
b0000 6
08
