sv_common_ips/09_arbiter_round_robin/top.sv
// top.sv - Lesson 09
//
// Focus:
//  - 4-way round-robin arbiter
//  - one-hot grant/protocol assertions
//  - structure that is easy to mirror in a C++ reference model

module top (
    input  logic clk,
    input  logic rst_n,

    input  logic [3:0] req,
    output logic [3:0] gnt,

    output logic [1:0] rr_ptr_dbg
);
    logic [1:0] rr_ptr;
    logic [3:0] gnt_next;

    // Pick one request using round-robin priority starting at rr_ptr.
    always_comb begin
        logic found;
        gnt_next = 4'b0000;
        found = 1'b0;

        for (int off = 0; off < 4; off++) begin
            int idx;
            idx = int'(rr_ptr) + off;
            if (idx >= 4) idx = idx - 4;

            if (!found && req[idx]) begin
                gnt_next[idx] = 1'b1;
                found = 1'b1;
            end
        end
    end

    assign gnt = gnt_next;
    assign rr_ptr_dbg = rr_ptr;

    // Move pointer to the slot after the granted requester.
    always_ff @(posedge clk) begin
        if (!rst_n) begin
            rr_ptr <= 2'd0;
        end else if (|gnt_next) begin
            unique case (1'b1)
                gnt_next[0]: rr_ptr <= 2'd1;
                gnt_next[1]: rr_ptr <= 2'd2;
                gnt_next[2]: rr_ptr <= 2'd3;
                gnt_next[3]: rr_ptr <= 2'd0;
                default: rr_ptr <= rr_ptr;
            endcase
        end
    end

    // Protocol/boundary checks.
    always_ff @(posedge clk) begin
        if (rst_n) begin
            assert ($onehot0(gnt))
                else $fatal(1, "Arbiter violation: gnt must be one-hot or zero");

            assert ((gnt & ~req) == 4'b0000)
                else $fatal(1, "Arbiter violation: grant without matching request");

            if (req == 4'b0000) begin
                assert (gnt == 4'b0000)
                    else $fatal(1, "Arbiter violation: nonzero grant when no requests");
            end
        end
    end

endmodule

sv_common_ips/09_arbiter_round_robin/waveform.vcd
$version Generated by VerilatedVcd $end
$timescale 1ps $end
 $scope module TOP $end
  $var wire 1 # clk $end
  $var wire 1 $ rst_n $end
  $var wire 4 % req [3:0] $end
  $var wire 4 & gnt [3:0] $end
  $var wire 2 ' rr_ptr_dbg [1:0] $end
  $scope module top $end
   $var wire 1 # clk $end
   $var wire 1 $ rst_n $end
   $var wire 4 % req [3:0] $end
   $var wire 4 & gnt [3:0] $end
   $var wire 2 ' rr_ptr_dbg [1:0] $end
   $var wire 2 ( rr_ptr [1:0] $end
   $var wire 4 ) gnt_next [3:0] $end
   $scope module unnamedblk1 $end
    $var wire 1 * found $end
    $scope module unnamedblk2 $end
     $var wire 32 , off [31:0] $end
     $scope module unnamedblk3 $end
      $var wire 32 + idx [31:0] $end
     $upscope $end
    $upscope $end
   $upscope $end
  $upscope $end
 $upscope $end
$enddefinitions $end


#0
0#
0$
b0000 %
b0000 &
b00 '
b00 (
b0000 )
0*
b00000000000000000000000000000011 +
b00000000000000000000000000000100 ,
#1
1#
#2
0#
#3
1#
#4
0#
#5
1#
#6
0#
#7
1#
#8
0#
#9
1#
#10
0#
1$
b1111 %
b0001 &
b0001 )
1*
#11
1#
b0010 &
b01 '
b01 (
b0010 )
b00000000000000000000000000000000 +
#12
0#
#13
1#
b0100 &
b10 '
b10 (
b0100 )
b00000000000000000000000000000001 +
#14
0#
#15
1#
b1000 &
b11 '
b11 (
b1000 )
b00000000000000000000000000000010 +
#16
0#
#17
1#
b0001 &
b00 '
b00 (
b0001 )
b00000000000000000000000000000011 +
#18
0#
#19
1#
b0010 &
b01 '
b01 (
b0010 )
b00000000000000000000000000000000 +
#20
0#
#21
1#
b0100 &
b10 '
b10 (
b0100 )
b00000000000000000000000000000001 +
#22
0#
#23
1#
b1000 &
b11 '
b11 (
b1000 )
b00000000000000000000000000000010 +
#24
0#
#25
1#
b0001 &
b00 '
b00 (
b0001 )
b00000000000000000000000000000011 +
#26
0#
#27
1#
b0010 &
b01 '
b01 (
b0010 )
b00000000000000000000000000000000 +
#28
0#
#29
1#
b0100 &
b10 '
b10 (
b0100 )
b00000000000000000000000000000001 +
#30
0#
#31
1#
b1000 &
b11 '
b11 (
b1000 )
b00000000000000000000000000000010 +
#32
0#
#33
1#
b0001 &
b00 '
b00 (
b0001 )
b00000000000000000000000000000011 +
#34
0#
#35
1#
b0010 &
b01 '
b01 (
b0010 )
b00000000000000000000000000000000 +
#36
0#
#37
1#
b0100 &
b10 '
b10 (
b0100 )
b00000000000000000000000000000001 +
#38
0#
#39
1#
b1000 &
b11 '
b11 (
b1000 )
b00000000000000000000000000000010 +
#40
0#
#41
1#
b0001 &
b00 '
b00 (
b0001 )
b00000000000000000000000000000011 +
#42
0#
#43
1#
b0010 &
b01 '
b01 (
b0010 )
b00000000000000000000000000000000 +
#44
0#
#45
1#
b0100 &
b10 '
b10 (
b0100 )
b00000000000000000000000000000001 +
#46
0#
#47
1#
b1000 &
b11 '
b11 (
b1000 )
b00000000000000000000000000000010 +
#48
0#
#49
1#
b0001 &
b00 '
b00 (
b0001 )
b00000000000000000000000000000011 +
#50
0#
#51
1#
b0010 &
b01 '
b01 (
b0010 )
b00000000000000000000000000000000 +
#52
0#
#53
1#
b0100 &
b10 '
b10 (
b0100 )
b00000000000000000000000000000001 +
#54
0#
#55
1#
b1000 &
b11 '
b11 (
b1000 )
b00000000000000000000000000000010 +
#56
0#
#57
1#
b0001 &
b00 '
b00 (
b0001 )
b00000000000000000000000000000011 +
#58
0#
b1110 %
b0010 &
b0010 )
#59
1#
b0100 &
b10 '
b10 (
b0100 )
b00000000000000000000000000000001 +
#60
0#
b1111 %
#61
1#
b1000 &
b11 '
b11 (
b1000 )
b00000000000000000000000000000010 +
#62
0#
b1110 %
#63
1#
b0010 &
b00 '
b00 (
b0010 )
b00000000000000000000000000000011 +
#64
0#
b0111 %
b0001 &
b0001 )
#65
1#
b0010 &
b01 '
b01 (
b0010 )
b00000000000000000000000000000000 +
#66
0#
b1110 %
#67
1#
b0100 &
b10 '
b10 (
b0100 )
b00000000000000000000000000000001 +
#68
0#
b1111 %
#69
1#
b1000 &
b11 '
b11 (
b1000 )
b00000000000000000000000000000010 +
#70
0#
b0000 %
b0000 &
b0000 )
0*
#71
1#
#72
0#
b0110 %
b0010 &
b0010 )
1*
#73
1#
b0100 &
b10 '
b10 (
b0100 )
b00000000000000000000000000000001 +
#74
0#
b1111 %
#75
1#
b1000 &
b11 '
b11 (
b1000 )
b00000000000000000000000000000010 +
#76
0#
#77
1#
b0001 &
b00 '
b00 (
b0001 )
b00000000000000000000000000000011 +
#78
0#
b1011 %
#79
1#
b0010 &
b01 '
b01 (
b0010 )
b00000000000000000000000000000000 +
#80
0#
#81
1#
b1000 &
b10 '
b10 (
b1000 )
b00000000000000000000000000000001 +
#82
0#
b1111 %
b0100 &
b0100 )
#83
1#
b1000 &
b11 '
b11 (
b1000 )
b00000000000000000000000000000010 +
#84
0#
b1100 %
#85
1#
b0100 &
b00 '
b00 (
b0100 )
b00000000000000000000000000000011 +
#86
0#
#87
1#
b1000 &
b11 '
b11 (
b1000 )
b00000000000000000000000000000010 +
#88
0#
b1011 %
#89
1#
b0001 &
b00 '
b00 (
b0001 )
b00000000000000000000000000000011 +
#90
0#
b1010 %
b0010 &
b0010 )
#91
1#
b1000 &
b10 '
b10 (
b1000 )
b00000000000000000000000000000001 +
#92
0#
b1101 %
b0100 &
b0100 )
#93
1#
b1000 &
b11 '
b11 (
b1000 )
b00000000000000000000000000000010 +
#94
0#
b1011 %
#95
1#
b0001 &
b00 '
b00 (
b0001 )
b00000000000000000000000000000011 +
#96
0#
b1111 %
#97
1#
b0010 &
b01 '
b01 (
b0010 )
b00000000000000000000000000000000 +
#98
0#
#99
1#
b0100 &
b10 '
b10 (
b0100 )
b00000000000000000000000000000001 +
#100
0#
b1101 %
#101
1#
b1000 &
b11 '
b11 (
b1000 )
b00000000000000000000000000000010 +
#102
0#
b1111 %
#103
1#
b0001 &
b00 '
b00 (
b0001 )
b00000000000000000000000000000011 +
#104
0#
#105
1#
b0010 &
b01 '
b01 (
b0010 )
b00000000000000000000000000000000 +
#106
0#
b1011 %
#107
1#
b1000 &
b10 '
b10 (
b1000 )
b00000000000000000000000000000001 +
#108
0#
b1111 %
b0100 &
b0100 )
#109
1#
b1000 &
b11 '
b11 (
b1000 )
b00000000000000000000000000000010 +
#110
0#
b1000 %
#111
1#
b00 '
b00 (
b00000000000000000000000000000011 +
#112
0#
b1100 %
b0100 &
b0100 )
#113
1#
b1000 &
b11 '
b11 (
b1000 )
b00000000000000000000000000000010 +
#114
0#
b1010 %
#115
1#
b0010 &
b00 '
b00 (
b0010 )
b00000000000000000000000000000011 +
#116
0#
b0001 %
b0001 &
b0001 )
#117
1#
b01 '
b01 (
b00000000000000000000000000000000 +
#118
0#
b1111 %
b0010 &
b0010 )
#119
1#
b0100 &
b10 '
b10 (
b0100 )
b00000000000000000000000000000001 +
#120
0#
#121
1#
b1000 &
b11 '
b11 (
b1000 )
b00000000000000000000000000000010 +
#122
0#
b0100 %
b0100 &
b0100 )
#123
1#
#124
0#
b1111 %
b1000 &
b1000 )
#125
1#
b0001 &
b00 '
b00 (
b0001 )
b00000000000000000000000000000011 +
#126
0#
b0000 %
b0000 &
b0000 )
0*
#127
1#
#128
0#
b1111 %
b0001 &
b0001 )
1*
#129
1#
b0010 &
b01 '
b01 (
b0010 )
b00000000000000000000000000000000 +
#130
0#
b1100 %
b0100 &
b0100 )
#131
1#
b1000 &
b11 '
b11 (
b1000 )
b00000000000000000000000000000010 +
#132
0#
b1111 %
#133
1#
b0001 &
b00 '
b00 (
b0001 )
b00000000000000000000000000000011 +
#134
0#
b1100 %
b0100 &
b0100 )
#135
1#
b1000 &
b11 '
b11 (
b1000 )
b00000000000000000000000000000010 +
#136
0#
b1111 %
#137
1#
b0001 &
b00 '
b00 (
b0001 )
b00000000000000000000000000000011 +
#138
0#
b1101 %
#139
1#
b0100 &
b01 '
b01 (
b0100 )
b00000000000000000000000000000000 +
#140
0#
b0110 %
b0010 &
b0010 )
#141
1#
b0100 &
b10 '
b10 (
b0100 )
b00000000000000000000000000000001 +
#142
0#
b1001 %
b1000 &
b1000 )
#143
1#
b0001 &
b00 '
b00 (
b0001 )
b00000000000000000000000000000011 +
#144
0#
#145
1#
b1000 &
b01 '
b01 (
b1000 )
b00000000000000000000000000000000 +
#146
0#
b0011 %
b0010 &
b0010 )
#147
1#
b0001 &
b10 '
b10 (
b0001 )
b00000000000000000000000000000001 +
#148
0#
b1010 %
b1000 &
b1000 )
#149
1#
b0010 &
b00 '
b00 (
b0010 )
b00000000000000000000000000000011 +
#150
0#
b1111 %
b0001 &
b0001 )
#151
1#
b0010 &
b01 '
b01 (
b0010 )
b00000000000000000000000000000000 +
#152
0#
b0011 %
#153
1#
b0001 &
b10 '
b10 (
b0001 )
b00000000000000000000000000000001 +
#154
0#
b1011 %
b1000 &
b1000 )
#155
1#
b0001 &
b00 '
b00 (
b0001 )
b00000000000000000000000000000011 +
#156
0#
b0100 %
b0100 &
b0100 )
#157
1#
b11 '
b11 (
b00000000000000000000000000000010 +
#158
0#
b1101 %
b1000 &
b1000 )
#159
1#
b0001 &
b00 '
b00 (
b0001 )
b00000000000000000000000000000011 +
#160
0#
b1111 %
#161
1#
b0010 &
b01 '
b01 (
b0010 )
b00000000000000000000000000000000 +
#162
0#
b1101 %
b0100 &
b0100 )
#163
1#
b1000 &
b11 '
b11 (
b1000 )
b00000000000000000000000000000010 +
#164
0#
b1111 %
#165
1#
b0001 &
b00 '
b00 (
b0001 )
b00000000000000000000000000000011 +
#166
0#
b0110 %
b0010 &
b0010 )
#167
1#
b0100 &
b10 '
b10 (
b0100 )
b00000000000000000000000000000001 +
#168
0#
#169
1#
b0010 &
b11 '
b11 (
b0010 )
b00000000000000000000000000000010 +
#170
0#
b0111 %
b0001 &
b0001 )
#171
1#
b0010 &
b01 '
b01 (
b0010 )
b00000000000000000000000000000000 +
#172
0#
b1111 %
#173
1#
b0100 &
b10 '
b10 (
b0100 )
b00000000000000000000000000000001 +
#174
0#
b0110 %
#175
1#
b0010 &
b11 '
b11 (
b0010 )
b00000000000000000000000000000010 +
#176
0#
b1110 %
b1000 &
b1000 )
#177
1#
b0010 &
b00 '
b00 (
b0010 )
b00000000000000000000000000000011 +
#178
0#
b1010 %
#179
1#
b1000 &
b10 '
b10 (
b1000 )
b00000000000000000000000000000001 +
#180
0#
b0001 %
b0001 &
b0001 )
#181
1#
b01 '
b01 (
b00000000000000000000000000000000 +
#182
0#
b0101 %
b0100 &
b0100 )
#183
1#
b0001 &
b11 '
b11 (
b0001 )
b00000000000000000000000000000010 +
#184
0#
b1111 %
b1000 &
b1000 )
#185
1#
b0001 &
b00 '
b00 (
b0001 )
b00000000000000000000000000000011 +
#186
0#
b1001 %
#187
1#
b1000 &
b01 '
b01 (
b1000 )
b00000000000000000000000000000000 +
#188
0#
b1111 %
b0010 &
b0010 )
#189
1#
b0100 &
b10 '
b10 (
b0100 )
b00000000000000000000000000000001 +
#190
0#
b1110 %
#191
1#
b1000 &
b11 '
b11 (
b1000 )
b00000000000000000000000000000010 +
#192
0#
b0010 %
b0010 &
b0010 )
#193
1#
b10 '
b10 (
b00000000000000000000000000000001 +
#194
0#
b1011 %
b1000 &
b1000 )
#195
1#
b0001 &
b00 '
b00 (
b0001 )
b00000000000000000000000000000011 +
#196
0#
b0001 %
#197
1#
b01 '
b01 (
b00000000000000000000000000000000 +
#198
0#
b0010 %
b0010 &
b0010 )
#199
1#
b10 '
b10 (
b00000000000000000000000000000001 +
#200
0#
b0100 %
b0100 &
b0100 )
#201
1#
b11 '
b11 (
b00000000000000000000000000000010 +
#202
0#
b1011 %
b1000 &
b1000 )
#203
1#
b0001 &
b00 '
b00 (
b0001 )
b00000000000000000000000000000011 +
#204
0#
b1101 %
#205
1#
b0100 &
b01 '
b01 (
b0100 )
b00000000000000000000000000000000 +
#206
0#
b1000 %
b1000 &
b1000 )
#207
1#
b00 '
b00 (
b00000000000000000000000000000011 +
#208
0#
b1110 %
b0010 &
b0010 )
#209
1#
b0100 &
b10 '
b10 (
b0100 )
b00000000000000000000000000000001 +
#210
0#
b0110 %
#211
1#
b0010 &
b11 '
b11 (
b0010 )
b00000000000000000000000000000010 +
#212
0#
#213
1#
b0100 &
b10 '
b10 (
b0100 )
b00000000000000000000000000000001 +
#214
0#
b0000 %
b0000 &
b0000 )
0*
#215
1#
#216
0#
b0111 %
b0100 &
b0100 )
1*
#217
1#
b0001 &
b11 '
b11 (
b0001 )
b00000000000000000000000000000010 +
#218
0#
b1111 %
b1000 &
b1000 )
#219
1#
b0001 &
b00 '
b00 (
b0001 )
b00000000000000000000000000000011 +
#220
0#
#221
1#
b0010 &
b01 '
b01 (
b0010 )
b00000000000000000000000000000000 +
#222
0#
b1101 %
b0100 &
b0100 )
#223
1#
b1000 &
b11 '
b11 (
b1000 )
b00000000000000000000000000000010 +
#224
0#
b1100 %
#225
1#
b0100 &
b00 '
b00 (
b0100 )
b00000000000000000000000000000011 +
#226
0#
b1110 %
b0010 &
b0010 )
#227
1#
b0100 &
b10 '
b10 (
b0100 )
b00000000000000000000000000000001 +
#228
0#
b1111 %
#229
1#
b1000 &
b11 '
b11 (
b1000 )
b00000000000000000000000000000010 +
#230
0#
#231
1#
b0001 &
b00 '
b00 (
b0001 )
b00000000000000000000000000000011 +
#232
0#
#233
1#
b0010 &
b01 '
b01 (
b0010 )
b00000000000000000000000000000000 +
#234
0#
#235
1#
b0100 &
b10 '
b10 (
b0100 )
b00000000000000000000000000000001 +
#236
0#
b0110 %
#237
1#
b0010 &
b11 '
b11 (
b0010 )
b00000000000000000000000000000010 +
#238
0#
b1010 %
b1000 &
b1000 )
#239
1#
b0010 &
b00 '
b00 (
b0010 )
b00000000000000000000000000000011 +
#240
0#
b0110 %
#241
1#
b0100 &
b10 '
b10 (
b0100 )
b00000000000000000000000000000001 +
#242
0#
b1111 %
#243
1#
b1000 &
b11 '
b11 (
b1000 )
b00000000000000000000000000000010 +
#244
0#
b0111 %
b0001 &
b0001 )
#245
1#
b0010 &
b01 '
b01 (
b0010 )
b00000000000000000000000000000000 +
#246
0#
b1111 %
#247
1#
b0100 &
b10 '
b10 (
b0100 )
b00000000000000000000000000000001 +
#248
0#
#249
1#
b1000 &
b11 '
b11 (
b1000 )
b00000000000000000000000000000010 +
#250
0#
#251
1#
b0001 &
b00 '
b00 (
b0001 )
b00000000000000000000000000000011 +
#252
0#
#253
1#
b0010 &
b01 '
b01 (
b0010 )
b00000000000000000000000000000000 +
#254
0#
#255
1#
b0100 &
b10 '
b10 (
b0100 )
b00000000000000000000000000000001 +
#256
0#
b1000 %
b1000 &
b1000 )
#257
1#
b00 '
b00 (
b00000000000000000000000000000011 +
#258
0#
b1010 %
b0010 &
b0010 )
#259
1#
b1000 &
b10 '
b10 (
b1000 )
b00000000000000000000000000000001 +
#260
0#
b1111 %
b0100 &
b0100 )
#261
1#
b1000 &
b11 '
b11 (
b1000 )
b00000000000000000000000000000010 +
#262
0#
#263
1#
b0001 &
b00 '
b00 (
b0001 )
b00000000000000000000000000000011 +
#264
0#
b0111 %
#265
1#
b0010 &
b01 '
b01 (
b0010 )
b00000000000000000000000000000000 +
#266
0#
b0101 %
b0100 &
b0100 )
#267
1#
b0001 &
b11 '
b11 (
b0001 )
b00000000000000000000000000000010 +
#268
0#
b0011 %
#269
1#
b0010 &
b01 '
b01 (
b0010 )
b00000000000000000000000000000000 +
#270
0#
b0010 %
#271
1#
b10 '
b10 (
b00000000000000000000000000000001 +
#272
0#
b1111 %
b0100 &
b0100 )
#273
1#
b1000 &
b11 '
b11 (
b1000 )
b00000000000000000000000000000010 +
#274
0#
b0101 %
b0001 &
b0001 )
#275
1#
b0100 &
b01 '
b01 (
b0100 )
b00000000000000000000000000000000 +
#276
0#
b0010 %
b0010 &
b0010 )
#277
1#
b10 '
b10 (
b00000000000000000000000000000001 +
#278
0#
b1111 %
b0100 &
b0100 )
#279
1#
b1000 &
b11 '
b11 (
b1000 )
b00000000000000000000000000000010 +
#280
0#
b1100 %
#281
1#
b0100 &
b00 '
b00 (
b0100 )
b00000000000000000000000000000011 +
#282
0#
b0001 %
b0001 &
b0001 )
#283
1#
b01 '
b01 (
b00000000000000000000000000000000 +
#284
0#
b1111 %
b0010 &
b0010 )
#285
1#
b0100 &
b10 '
b10 (
b0100 )
b00000000000000000000000000000001 +
#286
0#
b0101 %
#287
1#
b0001 &
b11 '
b11 (
b0001 )
b00000000000000000000000000000010 +
#288
0#
b1111 %
b1000 &
b1000 )
#289
1#
b0001 &
b00 '
b00 (
b0001 )
b00000000000000000000000000000011 +
#290
0#
b1101 %
#291
1#
b0100 &
b01 '
b01 (
b0100 )
b00000000000000000000000000000000 +
#292
0#
b1111 %
b0010 &
b0010 )
#293
1#
b0100 &
b10 '
b10 (
b0100 )
b00000000000000000000000000000001 +
#294
0#
b0010 %
b0010 &
b0010 )
#295
1#
#296
0#
b1111 %
b0100 &
b0100 )
#297
1#
b1000 &
b11 '
b11 (
b1000 )
b00000000000000000000000000000010 +
#298
0#
b0001 %
b0001 &
b0001 )
#299
1#
b01 '
b01 (
b00000000000000000000000000000000 +
#300
0#
b1111 %
b0010 &
b0010 )
#301
1#
b0100 &
b10 '
b10 (
b0100 )
b00000000000000000000000000000001 +
#302
0#
b0010 %
b0010 &
b0010 )
#303
1#
#304
0#
b1010 %
b1000 &
b1000 )
#305
1#
b0010 &
b00 '
b00 (
b0010 )
b00000000000000000000000000000011 +
#306
0#
b0111 %
b0001 &
b0001 )
#307
1#
b0010 &
b01 '
b01 (
b0010 )
b00000000000000000000000000000000 +
#308
0#
b0010 %
#309
1#
b10 '
b10 (
b00000000000000000000000000000001 +
#310
0#
b1100 %
b0100 &
b0100 )
#311
1#
b1000 &
b11 '
b11 (
b1000 )
b00000000000000000000000000000010 +
#312
0#
b1111 %
#313
1#
b0001 &
b00 '
b00 (
b0001 )
b00000000000000000000000000000011 +
#314
0#
b0100 %
b0100 &
b0100 )
#315
1#
b11 '
b11 (
b00000000000000000000000000000010 +
#316
0#
b0010 %
b0010 &
b0010 )
#317
1#
b10 '
b10 (
b00000000000000000000000000000001 +
#318
0#
b0001 %
b0001 &
b0001 )
#319
1#
b01 '
b01 (
b00000000000000000000000000000000 +
#320
0#
b1111 %
b0010 &
b0010 )
#321
1#
b0100 &
b10 '
b10 (
b0100 )
b00000000000000000000000000000001 +
#322
0#
b0111 %
#323
1#
b0001 &
b11 '
b11 (
b0001 )
b00000000000000000000000000000010 +
#324
0#
b1111 %
b1000 &
b1000 )
#325
1#
b0001 &
b00 '
b00 (
b0001 )
b00000000000000000000000000000011 +
#326
0#
b0100 %
b0100 &
b0100 )
#327
1#
b11 '
b11 (
b00000000000000000000000000000010 +
#328
0#
b1111 %
b1000 &
b1000 )
#329
1#
b0001 &
b00 '
b00 (
b0001 )
b00000000000000000000000000000011 +
#330
0#
#331
1#
b0010 &
b01 '
b01 (
b0010 )
b00000000000000000000000000000000 +
#332
0#
b0001 %
b0001 &
b0001 )
#333
1#
#334
0#
b1110 %
b0010 &
b0010 )
#335
1#
b0100 &
b10 '
b10 (
b0100 )
b00000000000000000000000000000001 +
#336
0#
b1111 %
#337
1#
b1000 &
b11 '
b11 (
b1000 )
b00000000000000000000000000000010 +
#338
0#
b1000 %
#339
1#
b00 '
b00 (
b00000000000000000000000000000011 +
#340
0#
#341
1#
#342
0#
b0000 %
b0000 &
b0000 )
0*
#343
1#
#344
0#
b0101 %
b0001 &
b0001 )
1*
#345
1#
b0100 &
b01 '
b01 (
b0100 )
b00000000000000000000000000000000 +
#346
0#
b1111 %
b0010 &
b0010 )
#347
1#
b0100 &
b10 '
b10 (
b0100 )
b00000000000000000000000000000001 +
#348
0#
#349
1#
b1000 &
b11 '
b11 (
b1000 )
b00000000000000000000000000000010 +
#350
0#
b0001 %
b0001 &
b0001 )
#351
1#
b01 '
b01 (
b00000000000000000000000000000000 +
#352
0#
b1111 %
b0010 &
b0010 )
#353
1#
b0100 &
b10 '
b10 (
b0100 )
b00000000000000000000000000000001 +
#354
0#
b0111 %
#355
1#
b0001 &
b11 '
b11 (
b0001 )
b00000000000000000000000000000010 +
#356
0#
b1111 %
b1000 &
b1000 )
#357
1#
b0001 &
b00 '
b00 (
b0001 )
b00000000000000000000000000000011 +
#358
0#
#359
1#
b0010 &
b01 '
b01 (
b0010 )
b00000000000000000000000000000000 +
#360
0#
#361
1#
b0100 &
b10 '
b10 (
b0100 )
b00000000000000000000000000000001 +
#362
0#
b0100 %
#363
1#
b11 '
b11 (
b00000000000000000000000000000010 +
#364
0#
b1110 %
b1000 &
b1000 )
#365
1#
b0010 &
b00 '
b00 (
b0010 )
b00000000000000000000000000000011 +
#366
0#
b1111 %
b0001 &
b0001 )
#367
1#
b0010 &
b01 '
b01 (
b0010 )
b00000000000000000000000000000000 +
#368
0#
#369
1#
b0100 &
b10 '
b10 (
b0100 )
b00000000000000000000000000000001 +
#370
0#
b0011 %
b0001 &
b0001 )
#371
1#
b0010 &
b01 '
b01 (
b0010 )
b00000000000000000000000000000000 +
#372
0#
b0111 %
#373
1#
b0100 &
b10 '
b10 (
b0100 )
b00000000000000000000000000000001 +
#374
0#
#375
1#
b0001 &
b11 '
b11 (
b0001 )
b00000000000000000000000000000010 +
#376
0#
b1111 %
b1000 &
b1000 )
#377
1#
b0001 &
b00 '
b00 (
b0001 )
b00000000000000000000000000000011 +
#378
0#
b0011 %
#379
1#
b0010 &
b01 '
b01 (
b0010 )
b00000000000000000000000000000000 +
#380
0#
b0110 %
#381
1#
b0100 &
b10 '
b10 (
b0100 )
b00000000000000000000000000000001 +
#382
0#
b0001 %
b0001 &
b0001 )
#383
1#
b01 '
b01 (
b00000000000000000000000000000000 +
#384
0#
b1011 %
b0010 &
b0010 )
#385
1#
b1000 &
b10 '
b10 (
b1000 )
b00000000000000000000000000000001 +
#386
0#
b0000 %
b0000 &
b0000 )
0*
#387
1#
#388
0#
b1111 %
b0100 &
b0100 )
1*
#389
1#
b1000 &
b11 '
b11 (
b1000 )
b00000000000000000000000000000010 +
#390
0#
#391
1#
b0001 &
b00 '
b00 (
b0001 )
b00000000000000000000000000000011 +
#392
0#
b0101 %
#393
1#
b0100 &
b01 '
b01 (
b0100 )
b00000000000000000000000000000000 +
#394
0#
b0100 %
#395
1#
b11 '
b11 (
b00000000000000000000000000000010 +
#396
0#
b1110 %
b1000 &
b1000 )
#397
1#
b0010 &
b00 '
b00 (
b0010 )
b00000000000000000000000000000011 +
#398
0#
b1111 %
b0001 &
b0001 )
#399
1#
b0010 &
b01 '
b01 (
b0010 )
b00000000000000000000000000000000 +
#400
0#
#401
1#
b0100 &
b10 '
b10 (
b0100 )
b00000000000000000000000000000001 +
#402
0#
b1010 %
b1000 &
b1000 )
#403
1#
b0010 &
b00 '
b00 (
b0010 )
b00000000000000000000000000000011 +
#404
0#
b1111 %
b0001 &
b0001 )
#405
1#
b0010 &
b01 '
b01 (
b0010 )
b00000000000000000000000000000000 +
#406
0#
#407
1#
b0100 &
b10 '
b10 (
b0100 )
b00000000000000000000000000000001 +
#408
0#
b1110 %
#409
1#
b1000 &
b11 '
b11 (
b1000 )
b00000000000000000000000000000010 +
#410
0#
b1000 %
#411
1#
b00 '
b00 (
b00000000000000000000000000000011 +
#412
0#
b1110 %
b0010 &
b0010 )
#413
1#
b0100 &
b10 '
b10 (
b0100 )
b00000000000000000000000000000001 +
#414
0#
b1111 %
#415
1#
b1000 &
b11 '
b11 (
b1000 )
b00000000000000000000000000000010 +
#416
0#
#417
1#
b0001 &
b00 '
b00 (
b0001 )
b00000000000000000000000000000011 +
#418
0#
b0010 %
b0010 &
b0010 )
#419
1#
b10 '
b10 (
b00000000000000000000000000000001 +
#420
0#
b1111 %
b0100 &
b0100 )
#421
1#
b1000 &
b11 '
b11 (
b1000 )
b00000000000000000000000000000010 +
#422
0#
#423
1#
b0001 &
b00 '
b00 (
b0001 )
b00000000000000000000000000000011 +
#424
0#
#425
1#
b0010 &
b01 '
b01 (
b0010 )
b00000000000000000000000000000000 +
#426
0#
b0010 %
#427
1#
b10 '
b10 (
b00000000000000000000000000000001 +
#428
0#
#429
1#
#430
0#
b1111 %
b0100 &
b0100 )
#431
1#
b1000 &
b11 '
b11 (
b1000 )
b00000000000000000000000000000010 +
#432
0#
b0011 %
b0001 &
b0001 )
#433
1#
b0010 &
b01 '
b01 (
b0010 )
b00000000000000000000000000000000 +
#434
0#
b1111 %
#435
1#
b0100 &
b10 '
b10 (
b0100 )
b00000000000000000000000000000001 +
#436
0#
b0000 %
b0000 &
b0000 )
0*
#437
1#
#438
0#
b0010 %
b0010 &
b0010 )
1*
#439
1#
#440
0#
b1001 %
b1000 &
b1000 )
#441
1#
b0001 &
b00 '
b00 (
b0001 )
b00000000000000000000000000000011 +
#442
0#
b0101 %
#443
1#
b0100 &
b01 '
b01 (
b0100 )
b00000000000000000000000000000000 +
#444
0#
b0100 %
#445
1#
b11 '
b11 (
b00000000000000000000000000000010 +
#446
0#
b0111 %
b0001 &
b0001 )
#447
1#
b0010 &
b01 '
b01 (
b0010 )
b00000000000000000000000000000000 +
#448
0#
b1111 %
#449
1#
b0100 &
b10 '
b10 (
b0100 )
b00000000000000000000000000000001 +
#450
0#
b1000 %
b1000 &
b1000 )
#451
1#
b00 '
b00 (
b00000000000000000000000000000011 +
#452
0#
b0011 %
b0001 &
b0001 )
#453
1#
b0010 &
b01 '
b01 (
b0010 )
b00000000000000000000000000000000 +
#454
0#
b1111 %
#455
1#
b0100 &
b10 '
b10 (
b0100 )
b00000000000000000000000000000001 +
#456
0#
b0110 %
#457
1#
b0010 &
b11 '
b11 (
b0010 )
b00000000000000000000000000000010 +
#458
0#
b1001 %
b1000 &
b1000 )
#459
1#
b0001 &
b00 '
b00 (
b0001 )
b00000000000000000000000000000011 +
#460
0#
b1101 %
#461
1#
b0100 &
b01 '
b01 (
b0100 )
b00000000000000000000000000000000 +
#462
0#
b1011 %
b0010 &
b0010 )
#463
1#
b1000 &
b10 '
b10 (
b1000 )
b00000000000000000000000000000001 +
#464
0#
b1111 %
b0100 &
b0100 )
#465
1#
b1000 &
b11 '
b11 (
b1000 )
b00000000000000000000000000000010 +
#466
0#
b1001 %
#467
1#
b0001 &
b00 '
b00 (
b0001 )
b00000000000000000000000000000011 +
#468
0#
b0110 %
b0010 &
b0010 )
#469
1#
b0100 &
b10 '
b10 (
b0100 )
b00000000000000000000000000000001 +
#470
0#
b1111 %
#471
1#
b1000 &
b11 '
b11 (
b1000 )
b00000000000000000000000000000010 +
#472
0#
#473
1#
b0001 &
b00 '
b00 (
b0001 )
b00000000000000000000000000000011 +
#474
0#
b0000 %
b0000 &
b0000 )
0*
#475
1#
#476
0#
b0111 %
b0001 &
b0001 )
1*
#477
1#
b0010 &
b01 '
b01 (
b0010 )
b00000000000000000000000000000000 +
#478
0#
b0011 %
#479
1#
b0001 &
b10 '
b10 (
b0001 )
b00000000000000000000000000000001 +
#480
0#
b1111 %
b0100 &
b0100 )
#481
1#
b1000 &
b11 '
b11 (
b1000 )
b00000000000000000000000000000010 +
#482
0#
#483
1#
b0001 &
b00 '
b00 (
b0001 )
b00000000000000000000000000000011 +
#484
0#
b0001 %
#485
1#
b01 '
b01 (
b00000000000000000000000000000000 +
#486
0#
b1101 %
b0100 &
b0100 )
#487
1#
b1000 &
b11 '
b11 (
b1000 )
b00000000000000000000000000000010 +
#488
0#
b1111 %
#489
1#
b0001 &
b00 '
b00 (
b0001 )
b00000000000000000000000000000011 +
#490
0#
b0011 %
#491
1#
b0010 &
b01 '
b01 (
b0010 )
b00000000000000000000000000000000 +
#492
0#
b1111 %
#493
1#
b0100 &
b10 '
b10 (
b0100 )
b00000000000000000000000000000001 +
#494
0#
#495
1#
b1000 &
b11 '
b11 (
b1000 )
b00000000000000000000000000000010 +
