sv_common_ips/10_shared_sram_register_file_ports/top.sv
// top.sv - Lesson 10
//
// Use-case:
//  - Shared SRAM/register-file port accessed by two clients.
//  - Single physical memory port, so requests are arbitrated.

module top (
    input  logic clk,
    input  logic rst_n,

    input  logic        c0_req,
    input  logic        c0_we,
    input  logic [3:0]  c0_addr,
    input  logic [15:0] c0_wdata,
    output logic        c0_ready,
    output logic [15:0] c0_rdata,

    input  logic        c1_req,
    input  logic        c1_we,
    input  logic [3:0]  c1_addr,
    input  logic [15:0] c1_wdata,
    output logic        c1_ready,
    output logic [15:0] c1_rdata,

    output logic [1:0]  grant,
    output logic        rr_turn_dbg
);
    logic [15:0] mem [0:15];
    logic rr_turn;

    always_comb begin
        grant = 2'b00;
        if (c0_req && c1_req) begin
            grant = rr_turn ? 2'b10 : 2'b01;
        end else if (c0_req) begin
            grant = 2'b01;
        end else if (c1_req) begin
            grant = 2'b10;
        end
    end

    assign rr_turn_dbg = rr_turn;

    always_ff @(posedge clk) begin
        if (!rst_n) begin
            rr_turn <= 1'b0;
            c0_ready <= 1'b0;
            c1_ready <= 1'b0;
            c0_rdata <= '0;
            c1_rdata <= '0;
            for (int i = 0; i < 16; i++) begin
                mem[i] <= 16'h1000 + i[15:0];
            end
        end else begin
            c0_ready <= 1'b0;
            c1_ready <= 1'b0;

            if (grant[0]) begin
                c0_ready <= 1'b1;
                if (c0_we) mem[c0_addr] <= c0_wdata;
                else       c0_rdata <= mem[c0_addr];
                rr_turn <= 1'b1;
            end

            if (grant[1]) begin
                c1_ready <= 1'b1;
                if (c1_we) mem[c1_addr] <= c1_wdata;
                else       c1_rdata <= mem[c1_addr];
                rr_turn <= 1'b0;
            end
        end
    end

    always_ff @(posedge clk) begin
        if (rst_n) begin
            assert ($onehot0(grant))
                else $fatal(1, "Shared SRAM arbiter violation: grant must be one-hot or zero");

            assert (!(c0_ready && c1_ready))
                else $fatal(1, "Shared SRAM violation: both clients ready in one cycle");
        end
    end

endmodule

sv_common_ips/10_shared_sram_register_file_ports/waveform.vcd
$version Generated by VerilatedVcd $end
$timescale 1ps $end
 $scope module TOP $end
  $var wire 1 5 clk $end
  $var wire 1 6 rst_n $end
  $var wire 1 7 c0_req $end
  $var wire 1 8 c0_we $end
  $var wire 4 9 c0_addr [3:0] $end
  $var wire 16 : c0_wdata [15:0] $end
  $var wire 1 ; c0_ready $end
  $var wire 16 < c0_rdata [15:0] $end
  $var wire 1 = c1_req $end
  $var wire 1 > c1_we $end
  $var wire 4 ? c1_addr [3:0] $end
  $var wire 16 @ c1_wdata [15:0] $end
  $var wire 1 A c1_ready $end
  $var wire 16 B c1_rdata [15:0] $end
  $var wire 2 C grant [1:0] $end
  $var wire 1 D rr_turn_dbg $end
  $scope module top $end
   $var wire 1 5 clk $end
   $var wire 1 6 rst_n $end
   $var wire 1 7 c0_req $end
   $var wire 1 8 c0_we $end
   $var wire 4 9 c0_addr [3:0] $end
   $var wire 16 : c0_wdata [15:0] $end
   $var wire 1 ; c0_ready $end
   $var wire 16 < c0_rdata [15:0] $end
   $var wire 1 = c1_req $end
   $var wire 1 > c1_we $end
   $var wire 4 ? c1_addr [3:0] $end
   $var wire 16 @ c1_wdata [15:0] $end
   $var wire 1 A c1_ready $end
   $var wire 16 B c1_rdata [15:0] $end
   $var wire 2 C grant [1:0] $end
   $var wire 1 D rr_turn_dbg $end
   $var wire 16 # mem[0] [15:0] $end
   $var wire 16 $ mem[1] [15:0] $end
   $var wire 16 % mem[2] [15:0] $end
   $var wire 16 & mem[3] [15:0] $end
   $var wire 16 ' mem[4] [15:0] $end
   $var wire 16 ( mem[5] [15:0] $end
   $var wire 16 ) mem[6] [15:0] $end
   $var wire 16 * mem[7] [15:0] $end
   $var wire 16 + mem[8] [15:0] $end
   $var wire 16 , mem[9] [15:0] $end
   $var wire 16 - mem[10] [15:0] $end
   $var wire 16 . mem[11] [15:0] $end
   $var wire 16 / mem[12] [15:0] $end
   $var wire 16 0 mem[13] [15:0] $end
   $var wire 16 1 mem[14] [15:0] $end
   $var wire 16 2 mem[15] [15:0] $end
   $var wire 1 3 rr_turn $end
   $scope module unnamedblk1 $end
    $var wire 32 4 i [31:0] $end
   $upscope $end
  $upscope $end
 $upscope $end
$enddefinitions $end


#0
b0000000000000000 #
b0000000000000000 $
b0000000000000000 %
b0000000000000000 &
b0000000000000000 '
b0000000000000000 (
b0000000000000000 )
b0000000000000000 *
b0000000000000000 +
b0000000000000000 ,
b0000000000000000 -
b0000000000000000 .
b0000000000000000 /
b0000000000000000 0
b0000000000000000 1
b0000000000000000 2
03
b00000000000000000000000000000000 4
05
06
07
08
b0000 9
b0000000000000000 :
0;
b0000000000000000 <
0=
0>
b0000 ?
b0000000000000000 @
0A
b0000000000000000 B
b00 C
0D
#1
b0001000000000000 #
b0001000000000001 $
b0001000000000010 %
b0001000000000011 &
b0001000000000100 '
b0001000000000101 (
b0001000000000110 )
b0001000000000111 *
b0001000000001000 +
b0001000000001001 ,
b0001000000001010 -
b0001000000001011 .
b0001000000001100 /
b0001000000001101 0
b0001000000001110 1
b0001000000001111 2
b00000000000000000000000000010000 4
15
#2
05
#3
15
#4
05
#5
15
#6
05
#7
15
#8
05
#9
15
#10
05
16
17
b0011 9
b1110101100010110 :
1=
b1010 ?
b1110110001001000 @
b01 C
#11
13
15
1;
b0001000000000011 <
b10 C
1D
#12
05
07
b0100 9
b0000000101000100 :
b1011 ?
b1110001111100010 @
#13
03
15
0;
1A
b0001000000001011 B
0D
#14
05
17
18
b1100 9
b1110001110110001 :
1>
b1000 ?
b0111100100110001 @
b01 C
#15
b1110001110110001 /
13
15
1;
0A
b10 C
1D
#16
05
b0100 9
b0011000001010100 :
b0000 ?
b0111111111100110 @
#17
b0111111111100110 #
03
15
0;
1A
b01 C
0D
#18
05
07
08
b1110110111001001 :
0=
b0010 ?
b0010111001011100 @
b00 C
#19
15
0A
#20
05
17
18
b1010 9
b1010101110000100 :
1=
0>
b1000 ?
b1010110010100111 @
b01 C
#21
b1010101110000100 -
13
15
1;
b10 C
1D
#22
05
07
08
b1111 9
b1000011101000101 :
b1100 ?
b1100010110110111 @
#23
03
15
0;
1A
b1110001110110001 B
0D
#24
05
17
b1110 9
b1110111110101111 :
b1001 ?
b0001100101000001 @
b01 C
#25
13
15
1;
b0001000000001110 <
0A
b10 C
1D
#26
05
b0000 9
b0110000010110100 :
1>
b0001 ?
b1001111011111101 @
#27
b1001111011111101 $
03
15
0;
1A
b01 C
0D
#28
05
07
18
b0101 9
b0101101011001100 :
0=
b1011 ?
b0110110011100101 @
b00 C
#29
15
0A
#30
05
b1111 9
b1011101001110010 :
1=
0>
b1000 ?
b1100010111110110 @
b10 C
#31
15
1A
b0001000000001000 B
#32
05
b0000 9
b1000110010111111 :
b0111 ?
b0010101001011010 @
#33
15
b0001000000000111 B
#34
05
b0111 9
b1101110000011101 :
1>
b0010 ?
b1101000001100110 @
#35
b1101000001100110 %
15
#36
05
17
b0101 9
b0111111000100001 :
b1100 ?
b0111111101010011 @
b01 C
#37
b0111111000100001 (
13
15
1;
0A
b10 C
1D
#38
05
08
b1000 9
b1100111100101010 :
0>
b0001 ?
b1001100101011000 @
#39
03
15
0;
1A
b1001111011111101 B
b01 C
0D
#40
05
07
18
b1011 9
b0110000101011110 :
0=
b0100 ?
b0100111011001000 @
b00 C
#41
15
0A
#42
05
17
08
b0001 9
b1101000101110101 :
b0001 ?
b0011110100001001 @
b01 C
#43
13
15
1;
b1001111011111101 <
1D
#44
05
18
b0000 9
b1000010000001100 :
1=
b1011 ?
b1111111100001110 @
b10 C
#45
03
15
0;
1A
b0001000000001011 B
b01 C
0D
#46
05
b0111 9
b0111110001010101 :
b0001 ?
b1000101011110110 @
#47
b0111110001010101 *
13
15
1;
0A
b10 C
1D
#48
05
07
08
b0000 9
b1100001001010000 :
1>
b0110 ?
b0011011111111010 @
#49
b0011011111111010 )
03
15
0;
1A
0D
#50
05
17
b0101 9
b1111100111101001 :
b1000 ?
b0010100011111010 @
b01 C
#51
13
15
1;
b0111111000100001 <
0A
b10 C
1D
#52
05
b0010 9
b0011101110110101 :
0=
b1010 ?
b0100100101110000 @
b01 C
#53
15
b1101000001100110 <
#54
05
07
18
b1101 9
b0110011101010001 :
1=
b1100 ?
b0011010101011101 @
b10 C
#55
b0011010101011101 /
03
15
0;
1A
0D
#56
05
17
08
b0010 9
b1101100100000000 :
0=
0>
b0100 ?
b0001111101110000 @
b01 C
#57
13
15
1;
0A
1D
#58
05
07
b0100 9
b1101110011011010 :
1=
1>
b0101 ?
b1101011011110000 @
b10 C
#59
b1101011011110000 (
03
15
0;
1A
0D
#60
05
b0110 9
b1100110100110110 :
b0111 ?
b1001011000101010 @
#61
b1001011000101010 *
15
#62
05
17
b1011 9
b1000100111100110 :
b0100 ?
b0010011011010010 @
b01 C
#63
13
15
1;
b0001000000001011 <
0A
b10 C
1D
#64
05
18
b1111 9
b1110100010100110 :
b1101 ?
b0111111001000011 @
#65
b0111111001000011 0
03
15
0;
1A
b01 C
0D
#66
05
08
b1110 9
b1110110000010101 :
0>
b0011 ?
b0110101011110101 @
#67
13
15
1;
b0001000000001110 <
0A
b10 C
1D
#68
05
b0111 9
b0010001010110000 :
0=
1>
b0010 ?
b1110000011111111 @
b01 C
#69
15
b1001011000101010 <
#70
05
b0000 9
b0010101110010110 :
1=
0>
b1111 ?
b0001101110001110 @
b10 C
#71
03
15
0;
1A
b0001000000001111 B
b01 C
0D
#72
05
b1010 9
b1011010110011000 :
1>
b1100 ?
b0101100100111000 @
#73
13
15
1;
b1010101110000100 <
0A
b10 C
1D
#74
05
07
b0110 9
b1101100011010110 :
0>
b0000 ?
b1100100110011010 @
#75
03
15
0;
1A
b0111111111100110 B
0D
#76
05
17
b0101 9
b0110110110101111 :
0=
b0011 ?
b1111011000000011 @
b01 C
#77
13
15
1;
b1101011011110000 <
0A
1D
#78
05
b1111 9
b0110101001101111 :
1=
1>
b1100 ?
b1101011100001111 @
b10 C
#79
b1101011100001111 /
03
15
0;
1A
b01 C
0D
#80
05
b1010 9
b0101000101111101 :
0=
0>
b0101 ?
b1000011110111011 @
#81
13
15
1;
b1010101110000100 <
0A
1D
#82
05
07
b0000 9
b1111011100111010 :
1=
b1011 ?
b1000100010010100 @
b10 C
#83
03
15
0;
1A
b0001000000001011 B
0D
#84
05
17
b1011 9
b0011110110101010 :
0=
1>
b1010 ?
b0100110101100100 @
b01 C
#85
13
15
1;
b0001000000001011 <
0A
1D
#86
05
b1000 9
b0011001011100001 :
1=
0>
b1100 ?
b0111110101110011 @
b10 C
#87
03
15
0;
1A
b1101011100001111 B
b01 C
0D
#88
05
18
b1110 9
b1011101110001010 :
1>
b0100 ?
b1010110001011110 @
#89
b1011101110001010 1
13
15
1;
0A
b10 C
1D
#90
05
b1111 9
b0011011100100001 :
b1100 ?
b1101100100111110 @
#91
b1101100100111110 /
03
15
0;
1A
b01 C
0D
#92
05
b0111 9
b1100101011010011 :
0=
b1111 ?
b1111010111011011 @
#93
b1100101011010011 *
13
15
1;
0A
1D
#94
05
07
08
b1110 9
b0000110111000110 :
0>
b1110 ?
b0001111011001011 @
b00 C
#95
15
0;
#96
05
17
18
b1011 9
b1001100101001001 :
1=
b0111 ?
b1001111110001001 @
b10 C
#97
03
15
1A
b1100101011010011 B
b01 C
0D
#98
05
07
08
b0111 9
b1000100001110101 :
1>
b1111 ?
b1101011000000001 @
b10 C
#99
b1101011000000001 2
15
#100
05
b1011 9
b0010101100101001 :
0=
0>
b0100 ?
b1011110000010001 @
b00 C
#101
15
0A
#102
05
17
b0111 9
b1111000111000010 :
1=
b1111 ?
b0111010000110100 @
b01 C
#103
13
15
1;
b1100101011010011 <
b10 C
1D
#104
05
07
18
b1001 9
b1010111110001111 :
0=
1>
b1101 ?
b1110110110111110 @
b00 C
#105
15
0;
#106
05
17
08
b0110 9
b1111001111011110 :
1=
0>
b0000 ?
b0000001010000110 @
b10 C
#107
03
15
1A
b0111111111100110 B
b01 C
0D
#108
05
07
b1011001010000000 :
b1111 ?
b0000000100001100 @
b10 C
#109
15
b1101011000000001 B
#110
05
b0010 9
b1100111001101101 :
0=
1>
b0000 ?
b1001110001101011 @
b00 C
#111
15
0A
#112
05
17
18
b1001 9
b0011110000000111 :
1=
b1110 ?
b1001010100001001 @
b01 C
#113
b0011110000000111 ,
13
15
1;
b10 C
1D
#114
05
07
08
b1111 9
b1010010111011101 :
0=
0>
b0110 ?
b1001011111011110 @
b00 C
#115
15
0;
#116
05
17
18
b0100 9
b0010100101001010 :
1=
b1001 ?
b1010011110000111 @
b10 C
#117
03
15
1A
b0011110000000111 B
b01 C
0D
#118
05
07
08
b1101 9
b0000101010101101 :
1>
b1011 ?
b1010001100111010 @
b10 C
#119
b1010001100111010 .
15
#120
05
17
b0011 9
b1011111110111000 :
b0111 ?
b0001111001010101 @
b01 C
#121
13
15
1;
b0001000000000011 <
0A
b10 C
1D
#122
05
b1010 9
b1100001011111010 :
0>
b0110 ?
b1010111111011101 @
#123
03
15
0;
1A
b0011011111111010 B
b01 C
0D
#124
05
18
b0010 9
b1101101000100101 :
b0101 ?
b0000101101010110 @
#125
b1101101000100101 %
13
15
1;
0A
b10 C
1D
#126
05
07
08
b0101 9
b0010111101010001 :
1>
b1111 ?
b1100011010111100 @
#127
b1100011010111100 2
03
15
0;
1A
0D
#128
05
17
18
b1111 9
b1110000000010001 :
0=
0>
b1011 ?
b0000011111000011 @
b01 C
#129
b1110000000010001 2
13
15
1;
0A
1D
#130
05
b1000 9
b0110100000011110 :
1=
1>
b0110 ?
b0001101100100110 @
b10 C
#131
b0001101100100110 )
03
15
0;
1A
b01 C
0D
#132
05
08
b1110 9
b1010101011100110 :
0>
b1010 ?
b1001001011100100 @
#133
13
15
1;
b1011101110001010 <
0A
b10 C
1D
#134
05
18
b0001 9
b1001001000111001 :
1>
b0011 ?
b1100010011110111 @
#135
b1100010011110111 &
03
15
0;
1A
b01 C
0D
#136
05
07
08
b0101 9
b1110010100010100 :
0>
b0111 ?
b0001111100111001 @
b10 C
#137
15
b1100101011010011 B
#138
05
17
18
b0111 9
b0111101111000011 :
b1100 ?
b0101000110110110 @
b01 C
#139
b0111101111000011 *
13
15
1;
0A
b10 C
1D
#140
05
08
b1100 9
b1100000001100101 :
1>
b0110 ?
b0110001100010111 @
#141
b0110001100010111 )
03
15
0;
1A
b01 C
0D
#142
05
18
b1001 9
b1000000110010000 :
b1111 ?
b1010110110010001 @
#143
b1000000110010000 ,
13
15
1;
0A
b10 C
1D
#144
05
07
b0011 9
b0001011010111001 :
b0001 ?
b1000010110001101 @
#145
b1000010110001101 $
03
15
0;
1A
0D
#146
05
08
b1010 9
b1010110001011001 :
b0100 ?
b1111101110111100 @
#147
b1111101110111100 '
15
#148
05
17
18
b1111 9
b1011111101111011 :
0=
b0001 ?
b0100111001011011 @
b01 C
#149
b1011111101111011 2
13
15
1;
0A
1D
#150
05
08
b1011 9
b1001000000010101 :
1=
0>
b1100 ?
b0011100011111100 @
b10 C
#151
03
15
0;
1A
b1101100100111110 B
b01 C
0D
#152
05
07
18
b0110 9
b0011101111101011 :
1>
b0111 ?
b0001101111111110 @
b10 C
#153
b0001101111111110 *
15
#154
05
17
b0111 9
b0111101101110110 :
0>
b1101 ?
b0000111101001000 @
b01 C
#155
b0111101101110110 *
13
15
1;
0A
b10 C
1D
#156
05
07
08
b1101 9
b1000101000000010 :
b1011 ?
b0000100110011000 @
#157
03
15
0;
1A
b1010001100111010 B
0D
#158
05
17
b0010 9
b0011110001111010 :
b1111 ?
b1000001001000110 @
b01 C
#159
13
15
1;
b1101101000100101 <
0A
b10 C
1D
#160
05
b0101 9
b1010010011101011 :
b1010 ?
b1110101100000110 @
#161
03
15
0;
1A
b1010101110000100 B
b01 C
0D
#162
05
07
18
b1001 9
b1100110101100010 :
1>
b1110 ?
b0000011101100101 @
b10 C
#163
b0000011101100101 1
15
#164
05
b1010 9
b0001000101101010 :
b1100 ?
b1011100001110010 @
#165
b1011100001110010 /
15
#166
05
17
b0110 9
b1011000101110000 :
b0000 ?
b1111010010000100 @
b01 C
#167
b1011000101110000 )
13
15
1;
0A
b10 C
1D
#168
05
08
b1001 9
b1001111000011110 :
0>
b0001 ?
b1011101011111011 @
#169
03
15
0;
1A
b1000010110001101 B
b01 C
0D
#170
05
18
b1110 9
b0100110110000011 :
1>
b0111 ?
b0011001101100100 @
#171
b0100110110000011 1
13
15
1;
0A
b10 C
1D
#172
05
08
b0011 9
b1011011110011100 :
b1011 ?
b0110010001100000 @
#173
b0110010001100000 .
03
15
0;
1A
b01 C
0D
#174
05
b1100 9
b1101100001011010 :
b0011 ?
b0011100011110111 @
#175
13
15
1;
b1011100001110010 <
0A
b10 C
1D
#176
05
18
b0111 9
b0100001111111010 :
0=
0>
b0011101000110010 @
b01 C
#177
b0100001111111010 *
15
#178
05
07
b1000 9
b0100010101011001 :
1>
b1010 ?
b1100011111100110 @
b00 C
#179
15
0;
#180
05
17
b0010 9
b0100000100011010 :
1=
0>
b1100 ?
b0001111000101101 @
b10 C
#181
03
15
1A
b1011100001110010 B
b01 C
0D
#182
05
08
b1010 9
b1011010000110000 :
b1011 ?
b0100100011000000 @
#183
13
15
1;
b1010101110000100 <
0A
b10 C
1D
#184
05
b0111 9
b1110101110110001 :
b1110 ?
b1101110100110000 @
#185
03
15
0;
1A
b0100110110000011 B
b01 C
0D
#186
05
18
b0000 9
b0000110001001001 :
1>
b0110 ?
b1001001101110000 @
#187
b0000110001001001 #
13
15
1;
0A
b10 C
1D
#188
05
08
b0110 9
b1101111101001010 :
0=
0>
b1101 ?
b0100110001000001 @
b01 C
#189
15
b1011000101110000 <
#190
05
07
18
b1001 9
b1000100000010101 :
1=
b1010 ?
b0101001101110011 @
b10 C
#191
03
15
0;
1A
b1010101110000100 B
0D
#192
05
08
b1100 9
b0101100000001000 :
b1101 ?
b1100011101111001 @
#193
15
b0111111001000011 B
#194
05
17
b1010 9
b0010000000111111 :
0=
b0010 ?
b0001001001001010 @
b01 C
#195
13
15
1;
b1010101110000100 <
0A
1D
#196
05
b1110 9
b1101010010111110 :
1>
b0011 ?
b1000110011011101 @
#197
15
b0100110110000011 <
#198
05
07
18
b0101 9
b1100000010111101 :
b0111 ?
b1110001111101001 @
b00 C
#199
15
0;
#200
05
b0010100110110111 :
1=
0>
b0010 ?
b1110011100101011 @
b10 C
#201
03
15
1A
b1101101000100101 B
0D
#202
05
08
b0011 9
b0110110110000011 :
1>
b1111 ?
b1011111001110111 @
#203
b1011111001110111 2
15
#204
05
17
18
b0000 9
b0010001100010101 :
0>
b0110 ?
b1000111011101111 @
b01 C
#205
b0010001100010101 #
13
15
1;
0A
b10 C
1D
#206
05
b1001 9
b0111111110100100 :
0=
1>
b0000 ?
b1110100100010100 @
b01 C
#207
b0111111110100100 ,
15
#208
05
07
08
b0100 9
b1101000000101010 :
1=
b0010 ?
b0010001001001100 @
b10 C
#209
b0010001001001100 %
03
15
0;
1A
0D
#210
05
17
b1011 9
b1010100111110001 :
0=
b0111 ?
b0110111101001101 @
b01 C
#211
13
15
1;
b0110010001100000 <
0A
1D
#212
05
b1001 9
b1010111101100111 :
1=
b0000 ?
b1110001111001001 @
b10 C
#213
b1110001111001001 #
03
15
0;
1A
b01 C
0D
#214
05
b0100 9
b1111000000011011 :
0=
b1011 ?
b1011001110100011 @
#215
13
15
1;
b1111101110111100 <
0A
1D
#216
05
b0110 9
b0111001010111100 :
0>
b1110 ?
b1100010011001011 @
#217
15
b1011000101110000 <
#218
05
b1011 9
b0111101000101110 :
b1000 ?
b0001001111110100 @
#219
15
b0110010001100000 <
#220
05
07
b1110 9
b1111100010010001 :
1=
b1100 ?
b1100000001100100 @
b10 C
#221
03
15
0;
1A
b1011100001110010 B
0D
#222
05
17
18
b0100 9
b1010001010111011 :
b0101 ?
b0011111001001011 @
b01 C
#223
b1010001010111011 '
13
15
1;
0A
b10 C
1D
#224
05
b0101 9
b0100000111111101 :
0=
1>
b1110111001001000 @
b01 C
#225
b0100000111111101 (
15
#226
05
08
b0001 9
b0000010111001111 :
1=
b0000 ?
b1001011001100100 @
b10 C
#227
b1001011001100100 #
03
15
0;
1A
b01 C
0D
#228
05
07
18
b0010 9
b1100101010110001 :
b1100 ?
b1110111001101110 @
b10 C
#229
b1110111001101110 /
15
#230
05
17
b1110 9
b0100011010010011 :
b1010 ?
b1100000000101111 @
b01 C
#231
b0100011010010011 1
13
15
1;
0A
b10 C
1D
#232
05
b1010 9
b1101011010100100 :
0>
b0010101000111011 @
#233
03
15
0;
1A
b1010101110000100 B
b01 C
0D
#234
05
07
b0000 9
b0000101001110010 :
0=
1>
b1110 ?
b0000110001100110 @
b00 C
#235
15
0A
#236
05
08
b1100 9
b1111000110111000 :
1=
b0001 ?
b0100011011000001 @
b10 C
#237
b0100011011000001 $
15
1A
#238
05
17
b0001 9
b1001101001000001 :
b1010 ?
b0100101110100100 @
b01 C
#239
13
15
1;
b0100011011000001 <
0A
b10 C
1D
#240
05
07
b1101 9
b1111001000000101 :
0=
0>
b0001 ?
b1111111100001100 @
b00 C
#241
15
0;
#242
05
18
b0001 9
b0110000110111010 :
b0000 ?
b1001000001111110 @
#243
15
#244
05
17
b1100 9
b0111110101101111 :
1=
1>
b1100 ?
b0110010110010100 @
b10 C
#245
b0110010110010100 /
03
15
1A
b01 C
0D
#246
05
07
08
b0111 9
b1011010001001001 :
0=
0>
b0110 ?
b0111111100001111 @
b00 C
#247
15
0A
#248
05
17
b1000 9
b1001100000011000 :
1=
1>
b0100 ?
b1000010011100001 @
b01 C
#249
13
15
1;
b0001000000001000 <
b10 C
1D
#250
05
07
b0011 9
b1110111111110101 :
b0010 ?
b0100000010011001 @
#251
b0100000010011001 %
03
15
0;
1A
0D
#252
05
17
18
b0010 9
b0010001110000100 :
0>
b1101 ?
b0000011011111101 @
b01 C
#253
b0010001110000100 %
13
15
1;
0A
b10 C
1D
#254
05
b1011 9
b0111111101000011 :
0=
b0000 ?
b1001101001101001 @
b01 C
#255
b0111111101000011 .
15
#256
05
b0011 9
b1110100110011000 :
1>
b0111 ?
b0000011011011110 @
#257
b1110100110011000 &
15
#258
05
08
b0100 9
b0110100001011000 :
1=
b0001 ?
b1011011110011110 @
b10 C
#259
b1011011110011110 $
03
15
0;
1A
b01 C
0D
#260
05
b1010 9
b1100011111100101 :
0>
b0111 ?
b1000101111000000 @
#261
13
15
1;
b1010101110000100 <
0A
b10 C
1D
#262
05
b1110 9
b1101101011110011 :
b1101 ?
b0101110101001010 @
#263
03
15
0;
1A
b0111111001000011 B
b01 C
0D
#264
05
07
b1010 9
b1111001100100101 :
1>
b0111 ?
b0110010111001101 @
b10 C
#265
b0110010111001101 *
15
#266
05
17
18
b0101 9
b0000101001110100 :
0>
b1010 ?
b0010111110101110 @
b01 C
#267
b0000101001110100 (
13
15
1;
0A
b10 C
1D
#268
05
08
b0111 9
b1000011010100001 :
b0111 ?
b0010100101100000 @
#269
03
15
0;
1A
b0110010111001101 B
b01 C
0D
#270
05
18
b0101 9
b0111001100110001 :
0=
b0000 ?
b0110001100001111 @
#271
b0111001100110001 (
13
15
1;
0A
1D
#272
05
08
b1001 9
b1001101101110100 :
1=
1>
b1010 ?
b1001011001100101 @
b10 C
#273
b1001011001100101 -
03
15
0;
1A
b01 C
0D
#274
05
18
b1101 9
b0100010011000111 :
b0000 ?
b1101000100100110 @
#275
b0100010011000111 0
13
15
1;
0A
b10 C
1D
#276
05
b0100 9
b1001011111111001 :
0>
b0110101111000101 @
#277
03
15
0;
1A
b1001011001100100 B
b01 C
0D
#278
05
07
08
b1101 9
b1101111101011000 :
b1010 ?
b0100110100110101 @
b10 C
#279
15
b1001011001100101 B
#280
05
b0110 9
b0000110011101011 :
0=
1>
b1111 ?
b0110010111001111 @
b00 C
#281
15
0A
#282
05
17
b1111 9
b1011011000010000 :
0>
b0010 ?
b1011111000101101 @
b01 C
#283
13
15
1;
b1011111001110111 <
1D
#284
05
b1100 9
b1011110111110101 :
1=
1>
b1111 ?
b1010000001010001 @
b10 C
#285
b1010000001010001 2
03
15
0;
1A
b01 C
0D
#286
05
07
18
b0100 9
b0000100001000010 :
0=
b0010 ?
b1110000011110110 @
b00 C
#287
15
0A
#288
05
17
08
b0001 9
b0011110111001111 :
0>
b0110 ?
b0101101111101100 @
b01 C
#289
13
15
1;
b1011011110011110 <
1D
#290
05
18
b0111 9
b1000010001101010 :
1=
b0010 ?
b0011101100110111 @
b10 C
#291
03
15
0;
1A
b0010001110000100 B
b01 C
0D
#292
05
07
b1001 9
b0010110010100010 :
b1010 ?
b1110111111010101 @
b10 C
#293
15
b1001011001100101 B
#294
05
17
08
b1000 9
b0101101101000011 :
b0110101111111001 @
b01 C
#295
13
15
1;
b0001000000001000 <
0A
b10 C
1D
#296
05
07
b1010 9
b1111101010100101 :
1>
b0101 ?
b1101000110000101 @
#297
b1101000110000101 (
03
15
0;
1A
0D
#298
05
18
b0001 9
b0101111001001011 :
b0100 ?
b0111100010100011 @
#299
b0111100010100011 '
15
#300
05
08
b1110111001001101 :
0=
0>
b0000 ?
b1010110010110110 @
b00 C
#301
15
0A
#302
05
17
18
b1011 9
b0101111101111001 :
1=
1>
b0100 ?
b0011000001100011 @
b01 C
#303
b0101111101111001 .
13
15
1;
b10 C
1D
#304
05
b0100 9
b1111010100100111 :
b1111 ?
b0101111101001000 @
#305
b0101111101001000 2
03
15
0;
1A
b01 C
0D
#306
05
07
08
b0010 9
b0111101000000000 :
0=
0>
b0101 ?
b1001111101111100 @
b00 C
#307
15
0A
#308
05
b1000 9
b1100000010101101 :
b1011 ?
b1110101000100010 @
#309
15
#310
05
17
18
b1010 9
b0101110000110000 :
1>
b1100 ?
b0011111010010110 @
b01 C
#311
b0101110000110000 -
13
15
1;
1D
#312
05
07
b1000 9
b0010100110000011 :
b0000111101001111 @
b00 C
#313
15
0;
#314
05
17
08
b1001 9
b0010110111110011 :
1=
0>
b1101010110111011 @
b10 C
#315
03
15
1A
b0110010110010100 B
b01 C
0D
#316
05
b0111 9
b0010110100101111 :
0=
1>
b0100 ?
b1111101011111110 @
#317
13
15
1;
b0110010111001101 <
0A
1D
#318
05
b1100 9
b1000010011100101 :
1=
0>
b0101 ?
b1101000100101011 @
b10 C
#319
03
15
0;
1A
b1101000110000101 B
b01 C
0D
#320
05
07
18
b0110 9
b1011111011010000 :
1>
b1011 ?
b1000011011111000 @
b10 C
#321
b1000011011111000 .
15
#322
05
17
08
b1100 9
b0100000100111110 :
0>
b0001 ?
b0000101110010111 @
b01 C
#323
13
15
1;
b0110010110010100 <
0A
b10 C
1D
#324
05
07
18
b0110 9
b0010001011110000 :
1>
b1110 ?
b1001010001110110 @
#325
b1001010001110110 1
03
15
0;
1A
0D
#326
05
17
b1010 9
b0001011101011101 :
0=
b1101 ?
b0111010000001101 @
b01 C
#327
b0001011101011101 -
13
15
1;
0A
1D
#328
05
b1101 9
b1010110100001010 :
1=
b1011 ?
b1111001110101101 @
b10 C
#329
b1111001110101101 .
03
15
0;
1A
b01 C
0D
#330
05
08
b1100 9
b0011101000101000 :
0=
0>
b1000000100000001 @
#331
13
15
1;
0A
1D
#332
05
18
b1010 9
b0001111101110110 :
1=
1>
b0100 ?
b0111011000111111 @
b10 C
#333
b0111011000111111 '
03
15
0;
1A
b01 C
0D
#334
05
b0000 9
b0010001010101000 :
b1011 ?
b0101000111100110 @
#335
b0010001010101000 #
13
15
1;
0A
b10 C
1D
#336
05
07
08
b1000 9
b0101001010011010 :
b0000 ?
b0000100000000101 @
#337
b0000100000000101 #
03
15
0;
1A
0D
#338
05
17
18
b1010001100100001 :
b0101 ?
b1100110011011100 @
b01 C
#339
b1010001100100001 +
13
15
1;
0A
b10 C
1D
#340
05
b0101 9
b0000000100110001 :
0>
b1111011001011011 @
#341
03
15
0;
1A
b01 C
0D
#342
05
08
b0001 9
b0100100000010001 :
0=
b0001 ?
b0011001010000110 @
#343
13
15
1;
b1011011110011110 <
0A
1D
#344
05
07
18
b0111 9
b1001000100010001 :
1=
1>
b1100 ?
b1011111110100010 @
b10 C
#345
b1011111110100010 /
03
15
0;
1A
0D
#346
05
17
b1100 9
b1111101011011010 :
0>
b1110 ?
b1111100001100001 @
b01 C
#347
b1111101011011010 /
13
15
1;
0A
b10 C
1D
#348
05
08
b0110 9
b0100101100101110 :
1>
b1111 ?
b1001101011010000 @
#349
b1001101011010000 2
03
15
0;
1A
b01 C
0D
#350
05
b0011 9
b0010000101010010 :
0>
b1110 ?
b1101001010101011 @
#351
13
15
1;
b1110100110011000 <
0A
b10 C
1D
#352
05
b1111 9
b0101010100011001 :
0=
1>
b1011 ?
b0001011000011001 @
b01 C
#353
15
b1001101011010000 <
#354
05
18
b0010111000101001 :
b1000 ?
b0011101001000100 @
#355
b0010111000101001 2
15
#356
05
08
b1001 9
b1011000100101111 :
1=
0>
b1111 ?
b0001000000011111 @
b10 C
#357
03
15
0;
1A
b0010111000101001 B
b01 C
0D
#358
05
b0101 9
b0000000111101010 :
1>
b0011 ?
b0010010100010110 @
#359
13
15
1;
b1101000110000101 <
0A
b10 C
1D
#360
05
18
b0000 9
b1110110101011101 :
0>
b0111 ?
b0001001010000011 @
#361
03
15
0;
1A
b0110010111001101 B
b01 C
0D
#362
05
07
08
b0110 9
b0011001111110000 :
0=
1>
b1000 ?
b0001110101100101 @
b00 C
#363
15
0A
#364
05
17
b0010 9
b1011110001100110 :
b1101 ?
b1011101101000101 @
b01 C
#365
13
15
1;
b0010001110000100 <
1D
#366
05
07
18
b1010 9
b0100001111100000 :
b0111 ?
b0111010111110100 @
b00 C
#367
15
0;
